Workbook

Sheet A_N_B_vol_plein
A1: Geldig/valable | C1: Volledige werkloosheidsuitkeringen - dagbedrag van de volle uitkering | U1: Multiplicat(o)(eu)r | W1: =Basisbedragen!$I$2 -> 1.8114
A2: 46266 | C2: Allocations de chômage complet - montant journalier de l'allocation entière
C4: Werknemers met gezinslast Travailleurs ayant charge de famille | I4: Alleenwonenden Isolés | O4: Samenwonenden Cohabitants
C6: 1e periode | G6: 2e per | I6: 1e periode | M6: 2e per | O6: 1e periode | S6: 2e per | T6: 2ème pér
D7: 1ère période | G7: 2ème pér | J7: 1ère période | M7: 2ème pér | P7: 1ère période | S7: BV+ / PP+ | T7: BV- / PP-
A9: Code | C9: AA1 | D9: AA2 | E9: AA3 | G9: AB AX | I9: NA1 | J9: NA2 | K9: NA3 | M9: NB NX | O9: BA1 | P9: BA2 | Q9: BA3 | S9: BX | T9: BB
O10: 0.65 | P10: 0.6 | Q10: 0.6
C11: 0.65 | D11: 0.6 | E11: 0.6 | I11: 0.65 | J11: 0.6 | K11: 0.6 | O11: 0.65 | P11: 0.6 | Q11: 0.6
A12: MIN | C12: =ROUND(Basisbedragen!$D$34*$W$1,2) -> 78.09 | D12: =$C$12 -> 78.09 | E12: =ROUND(Basisbedragen!$D$35*$W$1,2) -> 70.99 | G12: =$E$12 -> 70.99 | I12: =ROUND(Basisbedragen!$D$36*$W$1,2) -> 63.29 | J12: =$I$12 -> 63.29 | K12: =ROUND(Basisbedragen!$D$37*$W$1,2) -> 57.53 | M12: =$K$12 -> 57.53 | O12: =ROUND(Basisbedragen!$D$38*$W$1,2) -> 60.92 | P12: =ROUND(Basisbedragen!$D$39*$W$1,2) -> 56.23 | Q12: =ROUND(Basisbedragen!$D$40*$W$1,2) -> 51.12 | S12: =ROUND(Basisbedragen!D41*$W$1,2) -> 42.37 | T12: =ROUND(Basisbedragen!D42*$W$1,2) -> 29.85
A13: 1 | C13: =IF(MIN(MAX(ROUND(ROUND('Loonschijven_Tranches salariale'!$Q8*0.65,4)*Basisbedragen!$I$7,2),ROUND(Basisbedragen!$D$34*Basisbedragen!$I$7,2)),ROUND(ROUND(Basisbedragen!$D$27*0.65,4)*Basisbedragen!$I$7,2))<= Basisbedragen!$I$8,MIN(MAX(ROUND(ROUND('Loonschijven_Tranches salariale'!$Q8*0.65,4)*Basisbedragen!$I$2,2),ROUND(Basisbedragen!$D$34*Basisbedragen!$I$2,2)),ROUND(ROUND(Basisbedragen!$D$27*0.65,4)*Basisbedragen!$I$2,2)),MIN(MAX(ROUND(ROUND('Loonschijven_Tranches salariale'!$Q8*0.65,4)*Basisbedragen!$I$7,2),ROUND(Basisbedragen!$D$34*Basisbedragen!$I$7,2)),ROUND(ROUND(Basisbedragen!$D$27*0.65,4)*Basisbedragen!$I$7,2))+Basisbedragen!$I$10) -> 78.09 | D13: =IF(MIN(MAX(ROUND(ROUND('Loonschijven_Tranches salariale'!$Q8*0.6,4)*Basisbedragen!$I$7,2),ROUND(Basisbedragen!$D$34*Basisbedragen!$I$7,2)),ROUND(ROUND(Basisbedragen!$D$28*0.6,4)*Basisbedragen!$I$7,2))<= Basisbedragen!$I$8,MIN(MAX(ROUND(ROUND('Loonschijven_Tranches salariale'!$Q8*0.6,4)*Basisbedragen!$I$2,2),ROUND(Basisbedragen!$D$34*Basisbedragen!$I$2,2)),ROUND(ROUND(Basisbedragen!$D$28*0.6,4)*Basisbedragen!$I$2,2)),MIN(MAX(ROUND(ROUND('Loonschijven_Tranches salariale'!$Q8*0.6,4)*Basisbedragen!$I$7,2),ROUND(Basisbedragen!$D$34*Basisbedragen!$I$7,2)),ROUND(ROUND(Basisbedragen!$D$28*0.6,4)*Basisbedragen!$I$7,2))+Basisbedragen!$I$10) -> 78.09 | E13: =MIN(MAX(ROUND(ROUND('Loonschijven_Tranches salariale'!$Q8*0.6,4)*Basisbedragen!$I$2,2),ROUND(Basisbedragen!$D$35*Basisbedragen!$I$2,2)),ROUND(ROUND(Basisbedragen!$D$29*0.6,4)*Basisbedragen!$I$2,2)) -> 70.99 | G13: =$E$12 -> 70.99 | I13: =IF(MIN(MAX(ROUND(ROUND('Loonschijven_Tranches salariale'!$Q8*0.65,4)*Basisbedragen!$I$7,2),ROUND(Basisbedragen!$D$36*Basisbedragen!$I$7,2)),ROUND(ROUND(Basisbedragen!$D$27*0.65,4)*Basisbedragen!$I$7,2))<= Basisbedragen!$I$8,MIN(MAX(ROUND(ROUND('Loonschijven_Tranches salariale'!$Q8*0.65,4)*Basisbedragen!$I$2,2),ROUND(Basisbedragen!$D$36*Basisbedragen!$I$2,2)),ROUND(ROUND(Basisbedragen!$D$27*0.65,4)*Basisbedragen!$I$2,2)),MIN(MAX(ROUND(ROUND('Loonschijven_Tranches salariale'!$Q8*0.65,4)*Basisbedragen!$I$7,2),ROUND(Basisbedragen!$D$36*Basisbedragen!$I$7,2)),ROUND(ROUND(Basisbedragen!$D$27*0.65,4)*Basisbedragen!$I$7,2))+Basisbedragen!$I$10) -> 63.29 | J13: =IF(MIN(MAX(ROUND(ROUND('Loonschijven_Tranches salariale'!$Q8*0.6,4)*Basisbedragen!$I$7,2),ROUND(Basisbedragen!$D$36*Basisbedragen!$I$7,2)),ROUND(ROUND(Basisbedragen!$D$28*0.6,4)*Basisbedragen!$I$7,2))<= Basisbedragen!$I$8,MIN(MAX(ROUND(ROUND('Loonschijven_Tranches salariale'!$Q8*0.6,4)*Basisbedragen!$I$2,2),ROUND(Basisbedragen!$D$36*Basisbedragen!$I$2,2)),ROUND(ROUND(Basisbedragen!$D$28*0.6,4)*Basisbedragen!$I$2,2)),MIN(MAX(ROUND(ROUND('Loonschijven_Tranches salariale'!$Q8*0.6,4)*Basisbedragen!$I$7,2),ROUND(Basisbedragen!$D$36*Basisbedragen!$I$7,2)),ROUND(ROUND(Basisbedragen!$D$28*0.6,4)*Basisbedragen!$I$7,2))+Basisbedragen!$I$10) -> 63.29 | K13: =MIN(MAX(ROUND(ROUND('Loonschijven_Tranches salariale'!$Q8*0.6,4)*Basisbedragen!$I$2,2),ROUND(Basisbedragen!$D$37*Basisbedragen!$I$2,2)),ROUND(ROUND(Basisbedragen!$D$29*0.6,4)*Basisbedragen!$I$2,2)) -> 57.53 | M13: =$K$12 -> 57.53 | O13: =IF(MIN(MAX(ROUND(ROUND('Loonschijven_Tranches salariale'!$Q8*0.65,4)*Basisbedragen!$I$7,2),ROUND(Basisbedragen!$D$38*Basisbedragen!$I$7,2)),ROUND(ROUND(Basisbedragen!$D$27*0.65,4)*Basisbedragen!$I$7,2))<= Basisbedragen!$I$8,MIN(MAX(ROUND(ROUND('Loonschijven_Tranches salariale'!$Q8*0.65,4)*Basisbedragen!$I$2,2),ROUND(Basisbedragen!$D$38*Basisbedragen!$I$2,2)),ROUND(ROUND(Basisbedragen!$D$27*0.65,4)*Basisbedragen!$I$2,2)),MIN(MAX(ROUND(ROUND('Loonschijven_Tranches salariale'!$Q8*0.65,4)*Basisbedragen!$I$7,2),ROUND(Basisbedragen!$D$38*Basisbedragen!$I$7,2)),ROUND(ROUND(Basisbedragen!$D$27*0.65,4)*Basisbedragen!$I$7,2))+Basisbedragen!$I$10) -> 60.92 | P13: =IF(MIN(MAX(ROUND(ROUND('Loonschijven_Tranches salariale'!$Q8*0.6,4)*Basisbedragen!$I$7,2),ROUND(Basisbedragen!$D$39*Basisbedragen!$I$7,2)),ROUND(ROUND(Basisbedragen!$D$28*0.6,4)*Basisbedragen!$I$7,2))<= Basisbedragen!$I$8,MIN(MAX(ROUND(ROUND('Loonschijven_Tranches salariale'!$Q8*0.6,4)*Basisbedragen!$I$2,2),ROUND(Basisbedragen!$D$39*Basisbedragen!$I$2,2)),ROUND(ROUND(Basisbedragen!$D$28*0.6,4)*Basisbedragen!$I$2,2)),MIN(MAX(ROUND(ROUND('Loonschijven_Tranches salariale'!$Q8*0.6,4)*Basisbedragen!$I$7,2),ROUND(Basisbedragen!$D$39*Basisbedragen!$I$7,2)),ROUND(ROUND(Basisbedragen!$D$28*0.6,4)*Basisbedragen!$I$7,2))+Basisbedragen!$I$10) -> 56.23 | Q13: =MIN(MAX(ROUND(ROUND('Loonschijven_Tranches salariale'!$Q8*0.6,4)*Basisbedragen!$I$2,2),ROUND(Basisbedragen!$D$40*Basisbedragen!$I$2,2)),ROUND(ROUND(Basisbedragen!$D$29*0.6,4)*Basisbedragen!$I$2,2)) -> 51.12 | S13: =$S$12 -> 42.37 | T13: =$T$12 -> 29.85
A14: =A13+1 -> 2 | C14: =IF(MIN(MAX(ROUND(ROUND('Loonschijven_Tranches salariale'!$Q9*0.65,4)*Basisbedragen!$I$7,2),ROUND(Basisbedragen!$D$34*Basisbedragen!$I$7,2)),ROUND(ROUND(Basisbedragen!$D$27*0.65,4)*Basisbedragen!$I$7,2))<= Basisbedragen!$I$8,MIN(MAX(ROUND(ROUND('Loonschijven_Tranches salariale'!$Q9*0.65,4)*Basisbedragen!$I$2,2),ROUND(Basisbedragen!$D$34*Basisbedragen!$I$2,2)),ROUND(ROUND(Basisbedragen!$D$27*0.65,4)*Basisbedragen!$I$2,2)),MIN(MAX(ROUND(ROUND('Loonschijven_Tranches salariale'!$Q9*0.65,4)*Basisbedragen!$I$7,2),ROUND(Basisbedragen!$D$34*Basisbedragen!$I$7,2)),ROUND(ROUND(Basisbedragen!$D$27*0.65,4)*Basisbedragen!$I$7,2))+Basisbedragen!$I$10) -> 78.09 | D14: =IF(MIN(MAX(ROUND(ROUND('Loonschijven_Tranches salariale'!$Q9*0.6,4)*Basisbedragen!$I$7,2),ROUND(Basisbedragen!$D$34*Basisbedragen!$I$7,2)),ROUND(ROUND(Basisbedragen!$D$28*0.6,4)*Basisbedragen!$I$7,2))<= Basisbedragen!$I$8,MIN(MAX(ROUND(ROUND('Loonschijven_Tranches salariale'!$Q9*0.6,4)*Basisbedragen!$I$2,2),ROUND(Basisbedragen!$D$34*Basisbedragen!$I$2,2)),ROUND(ROUND(Basisbedragen!$D$28*0.6,4)*Basisbedragen!$I$2,2)),MIN(MAX(ROUND(ROUND('Loonschijven_Tranches salariale'!$Q9*0.6,4)*Basisbedragen!$I$7,2),ROUND(Basisbedragen!$D$34*Basisbedragen!$I$7,2)),ROUND(ROUND(Basisbedragen!$D$28*0.6,4)*Basisbedragen!$I$7,2))+Basisbedragen!$I$10) -> 78.09 | E14: =MIN(MAX(ROUND(ROUND('Loonschijven_Tranches salariale'!$Q9*0.6,4)*Basisbedragen!$I$2,2),ROUND(Basisbedragen!$D$35*Basisbedragen!$I$2,2)),ROUND(ROUND(Basisbedragen!$D$29*0.6,4)*Basisbedragen!$I$2,2)) -> 70.99 | G14: =$E$12 -> 70.99 | I14: =IF(MIN(MAX(ROUND(ROUND('Loonschijven_Tranches salariale'!$Q9*0.65,4)*Basisbedragen!$I$7,2),ROUND(Basisbedragen!$D$36*Basisbedragen!$I$7,2)),ROUND(ROUND(Basisbedragen!$D$27*0.65,4)*Basisbedragen!$I$7,2))<= Basisbedragen!$I$8,MIN(MAX(ROUND(ROUND('Loonschijven_Tranches salariale'!$Q9*0.65,4)*Basisbedragen!$I$2,2),ROUND(Basisbedragen!$D$36*Basisbedragen!$I$2,2)),ROUND(ROUND(Basisbedragen!$D$27*0.65,4)*Basisbedragen!$I$2,2)),MIN(MAX(ROUND(ROUND('Loonschijven_Tranches salariale'!$Q9*0.65,4)*Basisbedragen!$I$7,2),ROUND(Basisbedragen!$D$36*Basisbedragen!$I$7,2)),ROUND(ROUND(Basisbedragen!$D$27*0.65,4)*Basisbedragen!$I$7,2))+Basisbedragen!$I$10) -> 63.29 | J14: =IF(MIN(MAX(ROUND(ROUND('Loonschijven_Tranches salariale'!$Q9*0.6,4)*Basisbedragen!$I$7,2),ROUND(Basisbedragen!$D$36*Basisbedragen!$I$7,2)),ROUND(ROUND(Basisbedragen!$D$28*0.6,4)*Basisbedragen!$I$7,2))<= Basisbedragen!$I$8,MIN(MAX(ROUND(ROUND('Loonschijven_Tranches salariale'!$Q9*0.6,4)*Basisbedragen!$I$2,2),ROUND(Basisbedragen!$D$36*Basisbedragen!$I$2,2)),ROUND(ROUND(Basisbedragen!$D$28*0.6,4)*Basisbedragen!$I$2,2)),MIN(MAX(ROUND(ROUND('Loonschijven_Tranches salariale'!$Q9*0.6,4)*Basisbedragen!$I$7,2),ROUND(Basisbedragen!$D$36*Basisbedragen!$I$7,2)),ROUND(ROUND(Basisbedragen!$D$28*0.6,4)*Basisbedragen!$I$7,2))+Basisbedragen!$I$10) -> 63.29 | K14: =MIN(MAX(ROUND(ROUND('Loonschijven_Tranches salariale'!$Q9*0.6,4)*Basisbedragen!$I$2,2),ROUND(Basisbedragen!$D$37*Basisbedragen!$I$2,2)),ROUND(ROUND(Basisbedragen!$D$29*0.6,4)*Basisbedragen!$I$2,2)) -> 57.53 | M14: =$K$12 -> 57.53 | O14: =IF(MIN(MAX(ROUND(ROUND('Loonschijven_Tranches salariale'!$Q9*0.65,4)*Basisbedragen!$I$7,2),ROUND(Basisbedragen!$D$38*Basisbedragen!$I$7,2)),ROUND(ROUND(Basisbedragen!$D$27*0.65,4)*Basisbedragen!$I$7,2))<= Basisbedragen!$I$8,MIN(MAX(ROUND(ROUND('Loonschijven_Tranches salariale'!$Q9*0.65,4)*Basisbedragen!$I$2,2),ROUND(Basisbedragen!$D$38*Basisbedragen!$I$2,2)),ROUND(ROUND(Basisbedragen!$D$27*0.65,4)*Basisbedragen!$I$2,2)),MIN(MAX(ROUND(ROUND('Loonschijven_Tranches salariale'!$Q9*0.65,4)*Basisbedragen!$I$7,2),ROUND(Basisbedragen!$D$38*Basisbedragen!$I$7,2)),ROUND(ROUND(Basisbedragen!$D$27*0.65,4)*Basisbedragen!$I$7,2))+Basisbedragen!$I$10) -> 60.92 | P14: =IF(MIN(MAX(ROUND(ROUND('Loonschijven_Tranches salariale'!$Q9*0.6,4)*Basisbedragen!$I$7,2),ROUND(Basisbedragen!$D$39*Basisbedragen!$I$7,2)),ROUND(ROUND(Basisbedragen!$D$28*0.6,4)*Basisbedragen!$I$7,2))<= Basisbedragen!$I$8,MIN(MAX(ROUND(ROUND('Loonschijven_Tranches salariale'!$Q9*0.6,4)*Basisbedragen!$I$2,2),ROUND(Basisbedragen!$D$39*Basisbedragen!$I$2,2)),ROUND(ROUND(Basisbedragen!$D$28*0.6,4)*Basisbedragen!$I$2,2)),MIN(MAX(ROUND(ROUND('Loonschijven_Tranches salariale'!$Q9*0.6,4)*Basisbedragen!$I$7,2),ROUND(Basisbedragen!$D$39*Basisbedragen!$I$7,2)),ROUND(ROUND(Basisbedragen!$D$28*0.6,4)*Basisbedragen!$I$7,2))+Basisbedragen!$I$10) -> 56.23 | Q14: =MIN(MAX(ROUND(ROUND('Loonschijven_Tranches salariale'!$Q9*0.6,4)*Basisbedragen!$I$2,2),ROUND(Basisbedragen!$D$40*Basisbedragen!$I$2,2)),ROUND(ROUND(Basisbedragen!$D$29*0.6,4)*Basisbedragen!$I$2,2)) -> 51.12 | S14: =$S$12 -> 42.37 | T14: =$T$12 -> 29.85
A15: =A14+1 -> 3 | C15: =IF(MIN(MAX(ROUND(ROUND('Loonschijven_Tranches salariale'!$Q10*0.65,4)*Basisbedragen!$I$7,2),ROUND(Basisbedragen!$D$34*Basisbedragen!$I$7,2)),ROUND(ROUND(Basisbedragen!$D$27*0.65,4)*Basisbedragen!$I$7,2))<= Basisbedragen!$I$8,MIN(MAX(ROUND(ROUND('Loonschijven_Tranches salariale'!$Q10*0.65,4)*Basisbedragen!$I$2,2),ROUND(Basisbedragen!$D$34*Basisbedragen!$I$2,2)),ROUND(ROUND(Basisbedragen!$D$27*0.65,4)*Basisbedragen!$I$2,2)),MIN(MAX(ROUND(ROUND('Loonschijven_Tranches salariale'!$Q10*0.65,4)*Basisbedragen!$I$7,2),ROUND(Basisbedragen!$D$34*Basisbedragen!$I$7,2)),ROUND(ROUND(Basisbedragen!$D$27*0.65,4)*Basisbedragen!$I$7,2))+Basisbedragen!$I$10) -> 78.09 | D15: =IF(MIN(MAX(ROUND(ROUND('Loonschijven_Tranches salariale'!$Q10*0.6,4)*Basisbedragen!$I$7,2),ROUND(Basisbedragen!$D$34*Basisbedragen!$I$7,2)),ROUND(ROUND(Basisbedragen!$D$28*0.6,4)*Basisbedragen!$I$7,2))<= Basisbedragen!$I$8,MIN(MAX(ROUND(ROUND('Loonschijven_Tranches salariale'!$Q10*0.6,4)*Basisbedragen!$I$2,2),ROUND(Basisbedragen!$D$34*Basisbedragen!$I$2,2)),ROUND(ROUND(Basisbedragen!$D$28*0.6,4)*Basisbedragen!$I$2,2)),MIN(MAX(ROUND(ROUND('Loonschijven_Tranches salariale'!$Q10*0.6,4)*Basisbedragen!$I$7,2),ROUND(Basisbedragen!$D$34*Basisbedragen!$I$7,2)),ROUND(ROUND(Basisbedragen!$D$28*0.6,4)*Basisbedragen!$I$7,2))+Basisbedragen!$I$10) -> 78.09 | E15: =MIN(MAX(ROUND(ROUND('Loonschijven_Tranches salariale'!$Q10*0.6,4)*Basisbedragen!$I$2,2),ROUND(Basisbedragen!$D$35*Basisbedragen!$I$2,2)),ROUND(ROUND(Basisbedragen!$D$29*0.6,4)*Basisbedragen!$I$2,2)) -> 70.99 | G15: =$E$12 -> 70.99 | I15: =IF(MIN(MAX(ROUND(ROUND('Loonschijven_Tranches salariale'!$Q10*0.65,4)*Basisbedragen!$I$7,2),ROUND(Basisbedragen!$D$36*Basisbedragen!$I$7,2)),ROUND(ROUND(Basisbedragen!$D$27*0.65,4)*Basisbedragen!$I$7,2))<= Basisbedragen!$I$8,MIN(MAX(ROUND(ROUND('Loonschijven_Tranches salariale'!$Q10*0.65,4)*Basisbedragen!$I$2,2),ROUND(Basisbedragen!$D$36*Basisbedragen!$I$2,2)),ROUND(ROUND(Basisbedragen!$D$27*0.65,4)*Basisbedragen!$I$2,2)),MIN(MAX(ROUND(ROUND('Loonschijven_Tranches salariale'!$Q10*0.65,4)*Basisbedragen!$I$7,2),ROUND(Basisbedragen!$D$36*Basisbedragen!$I$7,2)),ROUND(ROUND(Basisbedragen!$D$27*0.65,4)*Basisbedragen!$I$7,2))+Basisbedragen!$I$10) -> 63.29 | J15: =IF(MIN(MAX(ROUND(ROUND('Loonschijven_Tranches salariale'!$Q10*0.6,4)*Basisbedragen!$I$7,2),ROUND(Basisbedragen!$D$36*Basisbedragen!$I$7,2)),ROUND(ROUND(Basisbedragen!$D$28*0.6,4)*Basisbedragen!$I$7,2))<= Basisbedragen!$I$8,MIN(MAX(ROUND(ROUND('Loonschijven_Tranches salariale'!$Q10*0.6,4)*Basisbedragen!$I$2,2),ROUND(Basisbedragen!$D$36*Basisbedragen!$I$2,2)),ROUND(ROUND(Basisbedragen!$D$28*0.6,4)*Basisbedragen!$I$2,2)),MIN(MAX(ROUND(ROUND('Loonschijven_Tranches salariale'!$Q10*0.6,4)*Basisbedragen!$I$7,2),ROUND(Basisbedragen!$D$36*Basisbedragen!$I$7,2)),ROUND(ROUND(Basisbedragen!$D$28*0.6,4)*Basisbedragen!$I$7,2))+Basisbedragen!$I$10) -> 63.29 | K15: =MIN(MAX(ROUND(ROUND('Loonschijven_Tranches salariale'!$Q10*0.6,4)*Basisbedragen!$I$2,2),ROUND(Basisbedragen!$D$37*Basisbedragen!$I$2,2)),ROUND(ROUND(Basisbedragen!$D$29*0.6,4)*Basisbedragen!$I$2,2)) -> 57.53 | M15: =$K$12 -> 57.53 | O15: =IF(MIN(MAX(ROUND(ROUND('Loonschijven_Tranches salariale'!$Q10*0.65,4)*Basisbedragen!$I$7,2),ROUND(Basisbedragen!$D$38*Basisbedragen!$I$7,2)),ROUND(ROUND(Basisbedragen!$D$27*0.65,4)*Basisbedragen!$I$7,2))<= Basisbedragen!$I$8,MIN(MAX(ROUND(ROUND('Loonschijven_Tranches salariale'!$Q10*0.65,4)*Basisbedragen!$I$2,2),ROUND(Basisbedragen!$D$38*Basisbedragen!$I$2,2)),ROUND(ROUND(Basisbedragen!$D$27*0.65,4)*Basisbedragen!$I$2,2)),MIN(MAX(ROUND(ROUND('Loonschijven_Tranches salariale'!$Q10*0.65,4)*Basisbedragen!$I$7,2),ROUND(Basisbedragen!$D$38*Basisbedragen!$I$7,2)),ROUND(ROUND(Basisbedragen!$D$27*0.65,4)*Basisbedragen!$I$7,2))+Basisbedragen!$I$10) -> 60.92 | P15: =IF(MIN(MAX(ROUND(ROUND('Loonschijven_Tranches salariale'!$Q10*0.6,4)*Basisbedragen!$I$7,2),ROUND(Basisbedragen!$D$39*Basisbedragen!$I$7,2)),ROUND(ROUND(Basisbedragen!$D$28*0.6,4)*Basisbedragen!$I$7,2))<= Basisbedragen!$I$8,MIN(MAX(ROUND(ROUND('Loonschijven_Tranches salariale'!$Q10*0.6,4)*Basisbedragen!$I$2,2),ROUND(Basisbedragen!$D$39*Basisbedragen!$I$2,2)),ROUND(ROUND(Basisbedragen!$D$28*0.6,4)*Basisbedragen!$I$2,2)),MIN(MAX(ROUND(ROUND('Loonschijven_Tranches salariale'!$Q10*0.6,4)*Basisbedragen!$I$7,2),ROUND(Basisbedragen!$D$39*Basisbedragen!$I$7,2)),ROUND(ROUND(Basisbedragen!$D$28*0.6,4)*Basisbedragen!$I$7,2))+Basisbedragen!$I$10) -> 56.23 | Q15: =MIN(MAX(ROUND(ROUND('Loonschijven_Tranches salariale'!$Q10*0.6,4)*Basisbedragen!$I$2,2),ROUND(Basisbedragen!$D$40*Basisbedragen!$I$2,2)),ROUND(ROUND(Basisbedragen!$D$29*0.6,4)*Basisbedragen!$I$2,2)) -> 51.12 | S15: =$S$12 -> 42.37 | T15: =$T$12 -> 29.85
A16: =A15+1 -> 4 | C16: =IF(MIN(MAX(ROUND(ROUND('Loonschijven_Tranches salariale'!$Q11*0.65,4)*Basisbedragen!$I$7,2),ROUND(Basisbedragen!$D$34*Basisbedragen!$I$7,2)),ROUND(ROUND(Basisbedragen!$D$27*0.65,4)*Basisbedragen!$I$7,2))<= Basisbedragen!$I$8,MIN(MAX(ROUND(ROUND('Loonschijven_Tranches salariale'!$Q11*0.65,4)*Basisbedragen!$I$2,2),ROUND(Basisbedragen!$D$34*Basisbedragen!$I$2,2)),ROUND(ROUND(Basisbedragen!$D$27*0.65,4)*Basisbedragen!$I$2,2)),MIN(MAX(ROUND(ROUND('Loonschijven_Tranches salariale'!$Q11*0.65,4)*Basisbedragen!$I$7,2),ROUND(Basisbedragen!$D$34*Basisbedragen!$I$7,2)),ROUND(ROUND(Basisbedragen!$D$27*0.65,4)*Basisbedragen!$I$7,2))+Basisbedragen!$I$10) -> 78.09 | D16: =IF(MIN(MAX(ROUND(ROUND('Loonschijven_Tranches salariale'!$Q11*0.6,4)*Basisbedragen!$I$7,2),ROUND(Basisbedragen!$D$34*Basisbedragen!$I$7,2)),ROUND(ROUND(Basisbedragen!$D$28*0.6,4)*Basisbedragen!$I$7,2))<= Basisbedragen!$I$8,MIN(MAX(ROUND(ROUND('Loonschijven_Tranches salariale'!$Q11*0.6,4)*Basisbedragen!$I$2,2),ROUND(Basisbedragen!$D$34*Basisbedragen!$I$2,2)),ROUND(ROUND(Basisbedragen!$D$28*0.6,4)*Basisbedragen!$I$2,2)),MIN(MAX(ROUND(ROUND('Loonschijven_Tranches salariale'!$Q11*0.6,4)*Basisbedragen!$I$7,2),ROUND(Basisbedragen!$D$34*Basisbedragen!$I$7,2)),ROUND(ROUND(Basisbedragen!$D$28*0.6,4)*Basisbedragen!$I$7,2))+Basisbedragen!$I$10) -> 78.09 | E16: =MIN(MAX(ROUND(ROUND('Loonschijven_Tranches salariale'!$Q11*0.6,4)*Basisbedragen!$I$2,2),ROUND(Basisbedragen!$D$35*Basisbedragen!$I$2,2)),ROUND(ROUND(Basisbedragen!$D$29*0.6,4)*Basisbedragen!$I$2,2)) -> 70.99 | G16: =$E$12 -> 70.99 | I16: =IF(MIN(MAX(ROUND(ROUND('Loonschijven_Tranches salariale'!$Q11*0.65,4)*Basisbedragen!$I$7,2),ROUND(Basisbedragen!$D$36*Basisbedragen!$I$7,2)),ROUND(ROUND(Basisbedragen!$D$27*0.65,4)*Basisbedragen!$I$7,2))<= Basisbedragen!$I$8,MIN(MAX(ROUND(ROUND('Loonschijven_Tranches salariale'!$Q11*0.65,4)*Basisbedragen!$I$2,2),ROUND(Basisbedragen!$D$36*Basisbedragen!$I$2,2)),ROUND(ROUND(Basisbedragen!$D$27*0.65,4)*Basisbedragen!$I$2,2)),MIN(MAX(ROUND(ROUND('Loonschijven_Tranches salariale'!$Q11*0.65,4)*Basisbedragen!$I$7,2),ROUND(Basisbedragen!$D$36*Basisbedragen!$I$7,2)),ROUND(ROUND(Basisbedragen!$D$27*0.65,4)*Basisbedragen!$I$7,2))+Basisbedragen!$I$10) -> 63.29 | J16: =IF(MIN(MAX(ROUND(ROUND('Loonschijven_Tranches salariale'!$Q11*0.6,4)*Basisbedragen!$I$7,2),ROUND(Basisbedragen!$D$36*Basisbedragen!$I$7,2)),ROUND(ROUND(Basisbedragen!$D$28*0.6,4)*Basisbedragen!$I$7,2))<= Basisbedragen!$I$8,MIN(MAX(ROUND(ROUND('Loonschijven_Tranches salariale'!$Q11*0.6,4)*Basisbedragen!$I$2,2),ROUND(Basisbedragen!$D$36*Basisbedragen!$I$2,2)),ROUND(ROUND(Basisbedragen!$D$28*0.6,4)*Basisbedragen!$I$2,2)),MIN(MAX(ROUND(ROUND('Loonschijven_Tranches salariale'!$Q11*0.6,4)*Basisbedragen!$I$7,2),ROUND(Basisbedragen!$D$36*Basisbedragen!$I$7,2)),ROUND(ROUND(Basisbedragen!$D$28*0.6,4)*Basisbedragen!$I$7,2))+Basisbedragen!$I$10) -> 63.29 | K16: =MIN(MAX(ROUND(ROUND('Loonschijven_Tranches salariale'!$Q11*0.6,4)*Basisbedragen!$I$2,2),ROUND(Basisbedragen!$D$37*Basisbedragen!$I$2,2)),ROUND(ROUND(Basisbedragen!$D$29*0.6,4)*Basisbedragen!$I$2,2)) -> 57.53 | M16: =$K$12 -> 57.53 | O16: =IF(MIN(MAX(ROUND(ROUND('Loonschijven_Tranches salariale'!$Q11*0.65,4)*Basisbedragen!$I$7,2),ROUND(Basisbedragen!$D$38*Basisbedragen!$I$7,2)),ROUND(ROUND(Basisbedragen!$D$27*0.65,4)*Basisbedragen!$I$7,2))<= Basisbedragen!$I$8,MIN(MAX(ROUND(ROUND('Loonschijven_Tranches salariale'!$Q11*0.65,4)*Basisbedragen!$I$2,2),ROUND(Basisbedragen!$D$38*Basisbedragen!$I$2,2)),ROUND(ROUND(Basisbedragen!$D$27*0.65,4)*Basisbedragen!$I$2,2)),MIN(MAX(ROUND(ROUND('Loonschijven_Tranches salariale'!$Q11*0.65,4)*Basisbedragen!$I$7,2),ROUND(Basisbedragen!$D$38*Basisbedragen!$I$7,2)),ROUND(ROUND(Basisbedragen!$D$27*0.65,4)*Basisbedragen!$I$7,2))+Basisbedragen!$I$10) -> 60.92 | P16: =IF(MIN(MAX(ROUND(ROUND('Loonschijven_Tranches salariale'!$Q11*0.6,4)*Basisbedragen!$I$7,2),ROUND(Basisbedragen!$D$39*Basisbedragen!$I$7,2)),ROUND(ROUND(Basisbedragen!$D$28*0.6,4)*Basisbedragen!$I$7,2))<= Basisbedragen!$I$8,MIN(MAX(ROUND(ROUND('Loonschijven_Tranches salariale'!$Q11*0.6,4)*Basisbedragen!$I$2,2),ROUND(Basisbedragen!$D$39*Basisbedragen!$I$2,2)),ROUND(ROUND(Basisbedragen!$D$28*0.6,4)*Basisbedragen!$I$2,2)),MIN(MAX(ROUND(ROUND('Loonschijven_Tranches salariale'!$Q11*0.6,4)*Basisbedragen!$I$7,2),ROUND(Basisbedragen!$D$39*Basisbedragen!$I$7,2)),ROUND(ROUND(Basisbedragen!$D$28*0.6,4)*Basisbedragen!$I$7,2))+Basisbedragen!$I$10) -> 56.23 | Q16: =MIN(MAX(ROUND(ROUND('Loonschijven_Tranches salariale'!$Q11*0.6,4)*Basisbedragen!$I$2,2),ROUND(Basisbedragen!$D$40*Basisbedragen!$I$2,2)),ROUND(ROUND(Basisbedragen!$D$29*0.6,4)*Basisbedragen!$I$2,2)) -> 51.12 | S16: =$S$12 -> 42.37 | T16: =$T$12 -> 29.85
A17: =A16+1 -> 5 | C17: =IF(MIN(MAX(ROUND(ROUND('Loonschijven_Tranches salariale'!$Q12*0.65,4)*Basisbedragen!$I$7,2),ROUND(Basisbedragen!$D$34*Basisbedragen!$I$7,2)),ROUND(ROUND(Basisbedragen!$D$27*0.65,4)*Basisbedragen!$I$7,2))<= Basisbedragen!$I$8,MIN(MAX(ROUND(ROUND('Loonschijven_Tranches salariale'!$Q12*0.65,4)*Basisbedragen!$I$2,2),ROUND(Basisbedragen!$D$34*Basisbedragen!$I$2,2)),ROUND(ROUND(Basisbedragen!$D$27*0.65,4)*Basisbedragen!$I$2,2)),MIN(MAX(ROUND(ROUND('Loonschijven_Tranches salariale'!$Q12*0.65,4)*Basisbedragen!$I$7,2),ROUND(Basisbedragen!$D$34*Basisbedragen!$I$7,2)),ROUND(ROUND(Basisbedragen!$D$27*0.65,4)*Basisbedragen!$I$7,2))+Basisbedragen!$I$10) -> 78.09 | D17: =IF(MIN(MAX(ROUND(ROUND('Loonschijven_Tranches salariale'!$Q12*0.6,4)*Basisbedragen!$I$7,2),ROUND(Basisbedragen!$D$34*Basisbedragen!$I$7,2)),ROUND(ROUND(Basisbedragen!$D$28*0.6,4)*Basisbedragen!$I$7,2))<= Basisbedragen!$I$8,MIN(MAX(ROUND(ROUND('Loonschijven_Tranches salariale'!$Q12*0.6,4)*Basisbedragen!$I$2,2),ROUND(Basisbedragen!$D$34*Basisbedragen!$I$2,2)),ROUND(ROUND(Basisbedragen!$D$28*0.6,4)*Basisbedragen!$I$2,2)),MIN(MAX(ROUND(ROUND('Loonschijven_Tranches salariale'!$Q12*0.6,4)*Basisbedragen!$I$7,2),ROUND(Basisbedragen!$D$34*Basisbedragen!$I$7,2)),ROUND(ROUND(Basisbedragen!$D$28*0.6,4)*Basisbedragen!$I$7,2))+Basisbedragen!$I$10) -> 78.09 | E17: =MIN(MAX(ROUND(ROUND('Loonschijven_Tranches salariale'!$Q12*0.6,4)*Basisbedragen!$I$2,2),ROUND(Basisbedragen!$D$35*Basisbedragen!$I$2,2)),ROUND(ROUND(Basisbedragen!$D$29*0.6,4)*Basisbedragen!$I$2,2)) -> 70.99 | G17: =$E$12 -> 70.99 | I17: =IF(MIN(MAX(ROUND(ROUND('Loonschijven_Tranches salariale'!$Q12*0.65,4)*Basisbedragen!$I$7,2),ROUND(Basisbedragen!$D$36*Basisbedragen!$I$7,2)),ROUND(ROUND(Basisbedragen!$D$27*0.65,4)*Basisbedragen!$I$7,2))<= Basisbedragen!$I$8,MIN(MAX(ROUND(ROUND('Loonschijven_Tranches salariale'!$Q12*0.65,4)*Basisbedragen!$I$2,2),ROUND(Basisbedragen!$D$36*Basisbedragen!$I$2,2)),ROUND(ROUND(Basisbedragen!$D$27*0.65,4)*Basisbedragen!$I$2,2)),MIN(MAX(ROUND(ROUND('Loonschijven_Tranches salariale'!$Q12*0.65,4)*Basisbedragen!$I$7,2),ROUND(Basisbedragen!$D$36*Basisbedragen!$I$7,2)),ROUND(ROUND(Basisbedragen!$D$27*0.65,4)*Basisbedragen!$I$7,2))+Basisbedragen!$I$10) -> 63.29 | J17: =IF(MIN(MAX(ROUND(ROUND('Loonschijven_Tranches salariale'!$Q12*0.6,4)*Basisbedragen!$I$7,2),ROUND(Basisbedragen!$D$36*Basisbedragen!$I$7,2)),ROUND(ROUND(Basisbedragen!$D$28*0.6,4)*Basisbedragen!$I$7,2))<= Basisbedragen!$I$8,MIN(MAX(ROUND(ROUND('Loonschijven_Tranches salariale'!$Q12*0.6,4)*Basisbedragen!$I$2,2),ROUND(Basisbedragen!$D$36*Basisbedragen!$I$2,2)),ROUND(ROUND(Basisbedragen!$D$28*0.6,4)*Basisbedragen!$I$2,2)),MIN(MAX(ROUND(ROUND('Loonschijven_Tranches salariale'!$Q12*0.6,4)*Basisbedragen!$I$7,2),ROUND(Basisbedragen!$D$36*Basisbedragen!$I$7,2)),ROUND(ROUND(Basisbedragen!$D$28*0.6,4)*Basisbedragen!$I$7,2))+Basisbedragen!$I$10) -> 63.29 | K17: =MIN(MAX(ROUND(ROUND('Loonschijven_Tranches salariale'!$Q12*0.6,4)*Basisbedragen!$I$2,2),ROUND(Basisbedragen!$D$37*Basisbedragen!$I$2,2)),ROUND(ROUND(Basisbedragen!$D$29*0.6,4)*Basisbedragen!$I$2,2)) -> 57.53 | M17: =$K$12 -> 57.53 | O17: =IF(MIN(MAX(ROUND(ROUND('Loonschijven_Tranches salariale'!$Q12*0.65,4)*Basisbedragen!$I$7,2),ROUND(Basisbedragen!$D$38*Basisbedragen!$I$7,2)),ROUND(ROUND(Basisbedragen!$D$27*0.65,4)*Basisbedragen!$I$7,2))<= Basisbedragen!$I$8,MIN(MAX(ROUND(ROUND('Loonschijven_Tranches salariale'!$Q12*0.65,4)*Basisbedragen!$I$2,2),ROUND(Basisbedragen!$D$38*Basisbedragen!$I$2,2)),ROUND(ROUND(Basisbedragen!$D$27*0.65,4)*Basisbedragen!$I$2,2)),MIN(MAX(ROUND(ROUND('Loonschijven_Tranches salariale'!$Q12*0.65,4)*Basisbedragen!$I$7,2),ROUND(Basisbedragen!$D$38*Basisbedragen!$I$7,2)),ROUND(ROUND(Basisbedragen!$D$27*0.65,4)*Basisbedragen!$I$7,2))+Basisbedragen!$I$10) -> 60.92 | P17: =IF(MIN(MAX(ROUND(ROUND('Loonschijven_Tranches salariale'!$Q12*0.6,4)*Basisbedragen!$I$7,2),ROUND(Basisbedragen!$D$39*Basisbedragen!$I$7,2)),ROUND(ROUND(Basisbedragen!$D$28*0.6,4)*Basisbedragen!$I$7,2))<= Basisbedragen!$I$8,MIN(MAX(ROUND(ROUND('Loonschijven_Tranches salariale'!$Q12*0.6,4)*Basisbedragen!$I$2,2),ROUND(Basisbedragen!$D$39*Basisbedragen!$I$2,2)),ROUND(ROUND(Basisbedragen!$D$28*0.6,4)*Basisbedragen!$I$2,2)),MIN(MAX(ROUND(ROUND('Loonschijven_Tranches salariale'!$Q12*0.6,4)*Basisbedragen!$I$7,2),ROUND(Basisbedragen!$D$39*Basisbedragen!$I$7,2)),ROUND(ROUND(Basisbedragen!$D$28*0.6,4)*Basisbedragen!$I$7,2))+Basisbedragen!$I$10) -> 56.23 | Q17: =MIN(MAX(ROUND(ROUND('Loonschijven_Tranches salariale'!$Q12*0.6,4)*Basisbedragen!$I$2,2),ROUND(Basisbedragen!$D$40*Basisbedragen!$I$2,2)),ROUND(ROUND(Basisbedragen!$D$29*0.6,4)*Basisbedragen!$I$2,2)) -> 51.12 | S17: =$S$12 -> 42.37 | T17: =$T$12 -> 29.85
A18: =A17+1 -> 6 | C18: =IF(MIN(MAX(ROUND(ROUND('Loonschijven_Tranches salariale'!$Q13*0.65,4)*Basisbedragen!$I$7,2),ROUND(Basisbedragen!$D$34*Basisbedragen!$I$7,2)),ROUND(ROUND(Basisbedragen!$D$27*0.65,4)*Basisbedragen!$I$7,2))<= Basisbedragen!$I$8,MIN(MAX(ROUND(ROUND('Loonschijven_Tranches salariale'!$Q13*0.65,4)*Basisbedragen!$I$2,2),ROUND(Basisbedragen!$D$34*Basisbedragen!$I$2,2)),ROUND(ROUND(Basisbedragen!$D$27*0.65,4)*Basisbedragen!$I$2,2)),MIN(MAX(ROUND(ROUND('Loonschijven_Tranches salariale'!$Q13*0.65,4)*Basisbedragen!$I$7,2),ROUND(Basisbedragen!$D$34*Basisbedragen!$I$7,2)),ROUND(ROUND(Basisbedragen!$D$27*0.65,4)*Basisbedragen!$I$7,2))+Basisbedragen!$I$10) -> 78.09 | D18: =IF(MIN(MAX(ROUND(ROUND('Loonschijven_Tranches salariale'!$Q13*0.6,4)*Basisbedragen!$I$7,2),ROUND(Basisbedragen!$D$34*Basisbedragen!$I$7,2)),ROUND(ROUND(Basisbedragen!$D$28*0.6,4)*Basisbedragen!$I$7,2))<= Basisbedragen!$I$8,MIN(MAX(ROUND(ROUND('Loonschijven_Tranches salariale'!$Q13*0.6,4)*Basisbedragen!$I$2,2),ROUND(Basisbedragen!$D$34*Basisbedragen!$I$2,2)),ROUND(ROUND(Basisbedragen!$D$28*0.6,4)*Basisbedragen!$I$2,2)),MIN(MAX(ROUND(ROUND('Loonschijven_Tranches salariale'!$Q13*0.6,4)*Basisbedragen!$I$7,2),ROUND(Basisbedragen!$D$34*Basisbedragen!$I$7,2)),ROUND(ROUND(Basisbedragen!$D$28*0.6,4)*Basisbedragen!$I$7,2))+Basisbedragen!$I$10) -> 78.09 | E18: =MIN(MAX(ROUND(ROUND('Loonschijven_Tranches salariale'!$Q13*0.6,4)*Basisbedragen!$I$2,2),ROUND(Basisbedragen!$D$35*Basisbedragen!$I$2,2)),ROUND(ROUND(Basisbedragen!$D$29*0.6,4)*Basisbedragen!$I$2,2)) -> 70.99 | G18: =$E$12 -> 70.99 | I18: =IF(MIN(MAX(ROUND(ROUND('Loonschijven_Tranches salariale'!$Q13*0.65,4)*Basisbedragen!$I$7,2),ROUND(Basisbedragen!$D$36*Basisbedragen!$I$7,2)),ROUND(ROUND(Basisbedragen!$D$27*0.65,4)*Basisbedragen!$I$7,2))<= Basisbedragen!$I$8,MIN(MAX(ROUND(ROUND('Loonschijven_Tranches salariale'!$Q13*0.65,4)*Basisbedragen!$I$2,2),ROUND(Basisbedragen!$D$36*Basisbedragen!$I$2,2)),ROUND(ROUND(Basisbedragen!$D$27*0.65,4)*Basisbedragen!$I$2,2)),MIN(MAX(ROUND(ROUND('Loonschijven_Tranches salariale'!$Q13*0.65,4)*Basisbedragen!$I$7,2),ROUND(Basisbedragen!$D$36*Basisbedragen!$I$7,2)),ROUND(ROUND(Basisbedragen!$D$27*0.65,4)*Basisbedragen!$I$7,2))+Basisbedragen!$I$10) -> 63.29 | J18: =IF(MIN(MAX(ROUND(ROUND('Loonschijven_Tranches salariale'!$Q13*0.6,4)*Basisbedragen!$I$7,2),ROUND(Basisbedragen!$D$36*Basisbedragen!$I$7,2)),ROUND(ROUND(Basisbedragen!$D$28*0.6,4)*Basisbedragen!$I$7,2))<= Basisbedragen!$I$8,MIN(MAX(ROUND(ROUND('Loonschijven_Tranches salariale'!$Q13*0.6,4)*Basisbedragen!$I$2,2),ROUND(Basisbedragen!$D$36*Basisbedragen!$I$2,2)),ROUND(ROUND(Basisbedragen!$D$28*0.6,4)*Basisbedragen!$I$2,2)),MIN(MAX(ROUND(ROUND('Loonschijven_Tranches salariale'!$Q13*0.6,4)*Basisbedragen!$I$7,2),ROUND(Basisbedragen!$D$36*Basisbedragen!$I$7,2)),ROUND(ROUND(Basisbedragen!$D$28*0.6,4)*Basisbedragen!$I$7,2))+Basisbedragen!$I$10) -> 63.29 | K18: =MIN(MAX(ROUND(ROUND('Loonschijven_Tranches salariale'!$Q13*0.6,4)*Basisbedragen!$I$2,2),ROUND(Basisbedragen!$D$37*Basisbedragen!$I$2,2)),ROUND(ROUND(Basisbedragen!$D$29*0.6,4)*Basisbedragen!$I$2,2)) -> 57.53 | M18: =$K$12 -> 57.53 | O18: =IF(MIN(MAX(ROUND(ROUND('Loonschijven_Tranches salariale'!$Q13*0.65,4)*Basisbedragen!$I$7,2),ROUND(Basisbedragen!$D$38*Basisbedragen!$I$7,2)),ROUND(ROUND(Basisbedragen!$D$27*0.65,4)*Basisbedragen!$I$7,2))<= Basisbedragen!$I$8,MIN(MAX(ROUND(ROUND('Loonschijven_Tranches salariale'!$Q13*0.65,4)*Basisbedragen!$I$2,2),ROUND(Basisbedragen!$D$38*Basisbedragen!$I$2,2)),ROUND(ROUND(Basisbedragen!$D$27*0.65,4)*Basisbedragen!$I$2,2)),MIN(MAX(ROUND(ROUND('Loonschijven_Tranches salariale'!$Q13*0.65,4)*Basisbedragen!$I$7,2),ROUND(Basisbedragen!$D$38*Basisbedragen!$I$7,2)),ROUND(ROUND(Basisbedragen!$D$27*0.65,4)*Basisbedragen!$I$7,2))+Basisbedragen!$I$10) -> 60.92 | P18: =IF(MIN(MAX(ROUND(ROUND('Loonschijven_Tranches salariale'!$Q13*0.6,4)*Basisbedragen!$I$7,2),ROUND(Basisbedragen!$D$39*Basisbedragen!$I$7,2)),ROUND(ROUND(Basisbedragen!$D$28*0.6,4)*Basisbedragen!$I$7,2))<= Basisbedragen!$I$8,MIN(MAX(ROUND(ROUND('Loonschijven_Tranches salariale'!$Q13*0.6,4)*Basisbedragen!$I$2,2),ROUND(Basisbedragen!$D$39*Basisbedragen!$I$2,2)),ROUND(ROUND(Basisbedragen!$D$28*0.6,4)*Basisbedragen!$I$2,2)),MIN(MAX(ROUND(ROUND('Loonschijven_Tranches salariale'!$Q13*0.6,4)*Basisbedragen!$I$7,2),ROUND(Basisbedragen!$D$39*Basisbedragen!$I$7,2)),ROUND(ROUND(Basisbedragen!$D$28*0.6,4)*Basisbedragen!$I$7,2))+Basisbedragen!$I$10) -> 56.23 | Q18: =MIN(MAX(ROUND(ROUND('Loonschijven_Tranches salariale'!$Q13*0.6,4)*Basisbedragen!$I$2,2),ROUND(Basisbedragen!$D$40*Basisbedragen!$I$2,2)),ROUND(ROUND(Basisbedragen!$D$29*0.6,4)*Basisbedragen!$I$2,2)) -> 51.12 | S18: =$S$12 -> 42.37 | T18: =$T$12 -> 29.85
A19: =A18+1 -> 7 | C19: =IF(MIN(MAX(ROUND(ROUND('Loonschijven_Tranches salariale'!$Q14*0.65,4)*Basisbedragen!$I$7,2),ROUND(Basisbedragen!$D$34*Basisbedragen!$I$7,2)),ROUND(ROUND(Basisbedragen!$D$27*0.65,4)*Basisbedragen!$I$7,2))<= Basisbedragen!$I$8,MIN(MAX(ROUND(ROUND('Loonschijven_Tranches salariale'!$Q14*0.65,4)*Basisbedragen!$I$2,2),ROUND(Basisbedragen!$D$34*Basisbedragen!$I$2,2)),ROUND(ROUND(Basisbedragen!$D$27*0.65,4)*Basisbedragen!$I$2,2)),MIN(MAX(ROUND(ROUND('Loonschijven_Tranches salariale'!$Q14*0.65,4)*Basisbedragen!$I$7,2),ROUND(Basisbedragen!$D$34*Basisbedragen!$I$7,2)),ROUND(ROUND(Basisbedragen!$D$27*0.65,4)*Basisbedragen!$I$7,2))+Basisbedragen!$I$10) -> 78.09 | D19: =IF(MIN(MAX(ROUND(ROUND('Loonschijven_Tranches salariale'!$Q14*0.6,4)*Basisbedragen!$I$7,2),ROUND(Basisbedragen!$D$34*Basisbedragen!$I$7,2)),ROUND(ROUND(Basisbedragen!$D$28*0.6,4)*Basisbedragen!$I$7,2))<= Basisbedragen!$I$8,MIN(MAX(ROUND(ROUND('Loonschijven_Tranches salariale'!$Q14*0.6,4)*Basisbedragen!$I$2,2),ROUND(Basisbedragen!$D$34*Basisbedragen!$I$2,2)),ROUND(ROUND(Basisbedragen!$D$28*0.6,4)*Basisbedragen!$I$2,2)),MIN(MAX(ROUND(ROUND('Loonschijven_Tranches salariale'!$Q14*0.6,4)*Basisbedragen!$I$7,2),ROUND(Basisbedragen!$D$34*Basisbedragen!$I$7,2)),ROUND(ROUND(Basisbedragen!$D$28*0.6,4)*Basisbedragen!$I$7,2))+Basisbedragen!$I$10) -> 78.09 | E19: =MIN(MAX(ROUND(ROUND('Loonschijven_Tranches salariale'!$Q14*0.6,4)*Basisbedragen!$I$2,2),ROUND(Basisbedragen!$D$35*Basisbedragen!$I$2,2)),ROUND(ROUND(Basisbedragen!$D$29*0.6,4)*Basisbedragen!$I$2,2)) -> 70.99 | G19: =$E$12 -> 70.99 | I19: =IF(MIN(MAX(ROUND(ROUND('Loonschijven_Tranches salariale'!$Q14*0.65,4)*Basisbedragen!$I$7,2),ROUND(Basisbedragen!$D$36*Basisbedragen!$I$7,2)),ROUND(ROUND(Basisbedragen!$D$27*0.65,4)*Basisbedragen!$I$7,2))<= Basisbedragen!$I$8,MIN(MAX(ROUND(ROUND('Loonschijven_Tranches salariale'!$Q14*0.65,4)*Basisbedragen!$I$2,2),ROUND(Basisbedragen!$D$36*Basisbedragen!$I$2,2)),ROUND(ROUND(Basisbedragen!$D$27*0.65,4)*Basisbedragen!$I$2,2)),MIN(MAX(ROUND(ROUND('Loonschijven_Tranches salariale'!$Q14*0.65,4)*Basisbedragen!$I$7,2),ROUND(Basisbedragen!$D$36*Basisbedragen!$I$7,2)),ROUND(ROUND(Basisbedragen!$D$27*0.65,4)*Basisbedragen!$I$7,2))+Basisbedragen!$I$10) -> 63.29 | J19: =IF(MIN(MAX(ROUND(ROUND('Loonschijven_Tranches salariale'!$Q14*0.6,4)*Basisbedragen!$I$7,2),ROUND(Basisbedragen!$D$36*Basisbedragen!$I$7,2)),ROUND(ROUND(Basisbedragen!$D$28*0.6,4)*Basisbedragen!$I$7,2))<= Basisbedragen!$I$8,MIN(MAX(ROUND(ROUND('Loonschijven_Tranches salariale'!$Q14*0.6,4)*Basisbedragen!$I$2,2),ROUND(Basisbedragen!$D$36*Basisbedragen!$I$2,2)),ROUND(ROUND(Basisbedragen!$D$28*0.6,4)*Basisbedragen!$I$2,2)),MIN(MAX(ROUND(ROUND('Loonschijven_Tranches salariale'!$Q14*0.6,4)*Basisbedragen!$I$7,2),ROUND(Basisbedragen!$D$36*Basisbedragen!$I$7,2)),ROUND(ROUND(Basisbedragen!$D$28*0.6,4)*Basisbedragen!$I$7,2))+Basisbedragen!$I$10) -> 63.29 | K19: =MIN(MAX(ROUND(ROUND('Loonschijven_Tranches salariale'!$Q14*0.6,4)*Basisbedragen!$I$2,2),ROUND(Basisbedragen!$D$37*Basisbedragen!$I$2,2)),ROUND(ROUND(Basisbedragen!$D$29*0.6,4)*Basisbedragen!$I$2,2)) -> 57.53 | M19: =$K$12 -> 57.53 | O19: =IF(MIN(MAX(ROUND(ROUND('Loonschijven_Tranches salariale'!$Q14*0.65,4)*Basisbedragen!$I$7,2),ROUND(Basisbedragen!$D$38*Basisbedragen!$I$7,2)),ROUND(ROUND(Basisbedragen!$D$27*0.65,4)*Basisbedragen!$I$7,2))<= Basisbedragen!$I$8,MIN(MAX(ROUND(ROUND('Loonschijven_Tranches salariale'!$Q14*0.65,4)*Basisbedragen!$I$2,2),ROUND(Basisbedragen!$D$38*Basisbedragen!$I$2,2)),ROUND(ROUND(Basisbedragen!$D$27*0.65,4)*Basisbedragen!$I$2,2)),MIN(MAX(ROUND(ROUND('Loonschijven_Tranches salariale'!$Q14*0.65,4)*Basisbedragen!$I$7,2),ROUND(Basisbedragen!$D$38*Basisbedragen!$I$7,2)),ROUND(ROUND(Basisbedragen!$D$27*0.65,4)*Basisbedragen!$I$7,2))+Basisbedragen!$I$10) -> 60.92 | P19: =IF(MIN(MAX(ROUND(ROUND('Loonschijven_Tranches salariale'!$Q14*0.6,4)*Basisbedragen!$I$7,2),ROUND(Basisbedragen!$D$39*Basisbedragen!$I$7,2)),ROUND(ROUND(Basisbedragen!$D$28*0.6,4)*Basisbedragen!$I$7,2))<= Basisbedragen!$I$8,MIN(MAX(ROUND(ROUND('Loonschijven_Tranches salariale'!$Q14*0.6,4)*Basisbedragen!$I$2,2),ROUND(Basisbedragen!$D$39*Basisbedragen!$I$2,2)),ROUND(ROUND(Basisbedragen!$D$28*0.6,4)*Basisbedragen!$I$2,2)),MIN(MAX(ROUND(ROUND('Loonschijven_Tranches salariale'!$Q14*0.6,4)*Basisbedragen!$I$7,2),ROUND(Basisbedragen!$D$39*Basisbedragen!$I$7,2)),ROUND(ROUND(Basisbedragen!$D$28*0.6,4)*Basisbedragen!$I$7,2))+Basisbedragen!$I$10) -> 56.23 | Q19: =MIN(MAX(ROUND(ROUND('Loonschijven_Tranches salariale'!$Q14*0.6,4)*Basisbedragen!$I$2,2),ROUND(Basisbedragen!$D$40*Basisbedragen!$I$2,2)),ROUND(ROUND(Basisbedragen!$D$29*0.6,4)*Basisbedragen!$I$2,2)) -> 51.12 | S19: =$S$12 -> 42.37 | T19: =$T$12 -> 29.85
A20: =A19+1 -> 8 | C20: =IF(MIN(MAX(ROUND(ROUND('Loonschijven_Tranches salariale'!$Q15*0.65,4)*Basisbedragen!$I$7,2),ROUND(Basisbedragen!$D$34*Basisbedragen!$I$7,2)),ROUND(ROUND(Basisbedragen!$D$27*0.65,4)*Basisbedragen!$I$7,2))<= Basisbedragen!$I$8,MIN(MAX(ROUND(ROUND('Loonschijven_Tranches salariale'!$Q15*0.65,4)*Basisbedragen!$I$2,2),ROUND(Basisbedragen!$D$34*Basisbedragen!$I$2,2)),ROUND(ROUND(Basisbedragen!$D$27*0.65,4)*Basisbedragen!$I$2,2)),MIN(MAX(ROUND(ROUND('Loonschijven_Tranches salariale'!$Q15*0.65,4)*Basisbedragen!$I$7,2),ROUND(Basisbedragen!$D$34*Basisbedragen!$I$7,2)),ROUND(ROUND(Basisbedragen!$D$27*0.65,4)*Basisbedragen!$I$7,2))+Basisbedragen!$I$10) -> 78.09 | D20: =IF(MIN(MAX(ROUND(ROUND('Loonschijven_Tranches salariale'!$Q15*0.6,4)*Basisbedragen!$I$7,2),ROUND(Basisbedragen!$D$34*Basisbedragen!$I$7,2)),ROUND(ROUND(Basisbedragen!$D$28*0.6,4)*Basisbedragen!$I$7,2))<= Basisbedragen!$I$8,MIN(MAX(ROUND(ROUND('Loonschijven_Tranches salariale'!$Q15*0.6,4)*Basisbedragen!$I$2,2),ROUND(Basisbedragen!$D$34*Basisbedragen!$I$2,2)),ROUND(ROUND(Basisbedragen!$D$28*0.6,4)*Basisbedragen!$I$2,2)),MIN(MAX(ROUND(ROUND('Loonschijven_Tranches salariale'!$Q15*0.6,4)*Basisbedragen!$I$7,2),ROUND(Basisbedragen!$D$34*Basisbedragen!$I$7,2)),ROUND(ROUND(Basisbedragen!$D$28*0.6,4)*Basisbedragen!$I$7,2))+Basisbedragen!$I$10) -> 78.09 | E20: =MIN(MAX(ROUND(ROUND('Loonschijven_Tranches salariale'!$Q15*0.6,4)*Basisbedragen!$I$2,2),ROUND(Basisbedragen!$D$35*Basisbedragen!$I$2,2)),ROUND(ROUND(Basisbedragen!$D$29*0.6,4)*Basisbedragen!$I$2,2)) -> 70.99 | G20: =$E$12 -> 70.99 | I20: =IF(MIN(MAX(ROUND(ROUND('Loonschijven_Tranches salariale'!$Q15*0.65,4)*Basisbedragen!$I$7,2),ROUND(Basisbedragen!$D$36*Basisbedragen!$I$7,2)),ROUND(ROUND(Basisbedragen!$D$27*0.65,4)*Basisbedragen!$I$7,2))<= Basisbedragen!$I$8,MIN(MAX(ROUND(ROUND('Loonschijven_Tranches salariale'!$Q15*0.65,4)*Basisbedragen!$I$2,2),ROUND(Basisbedragen!$D$36*Basisbedragen!$I$2,2)),ROUND(ROUND(Basisbedragen!$D$27*0.65,4)*Basisbedragen!$I$2,2)),MIN(MAX(ROUND(ROUND('Loonschijven_Tranches salariale'!$Q15*0.65,4)*Basisbedragen!$I$7,2),ROUND(Basisbedragen!$D$36*Basisbedragen!$I$7,2)),ROUND(ROUND(Basisbedragen!$D$27*0.65,4)*Basisbedragen!$I$7,2))+Basisbedragen!$I$10) -> 63.29 | J20: =IF(MIN(MAX(ROUND(ROUND('Loonschijven_Tranches salariale'!$Q15*0.6,4)*Basisbedragen!$I$7,2),ROUND(Basisbedragen!$D$36*Basisbedragen!$I$7,2)),ROUND(ROUND(Basisbedragen!$D$28*0.6,4)*Basisbedragen!$I$7,2))<= Basisbedragen!$I$8,MIN(MAX(ROUND(ROUND('Loonschijven_Tranches salariale'!$Q15*0.6,4)*Basisbedragen!$I$2,2),ROUND(Basisbedragen!$D$36*Basisbedragen!$I$2,2)),ROUND(ROUND(Basisbedragen!$D$28*0.6,4)*Basisbedragen!$I$2,2)),MIN(MAX(ROUND(ROUND('Loonschijven_Tranches salariale'!$Q15*0.6,4)*Basisbedragen!$I$7,2),ROUND(Basisbedragen!$D$36*Basisbedragen!$I$7,2)),ROUND(ROUND(Basisbedragen!$D$28*0.6,4)*Basisbedragen!$I$7,2))+Basisbedragen!$I$10) -> 63.29 | K20: =MIN(MAX(ROUND(ROUND('Loonschijven_Tranches salariale'!$Q15*0.6,4)*Basisbedragen!$I$2,2),ROUND(Basisbedragen!$D$37*Basisbedragen!$I$2,2)),ROUND(ROUND(Basisbedragen!$D$29*0.6,4)*Basisbedragen!$I$2,2)) -> 57.53 | M20: =$K$12 -> 57.53 | O20: =IF(MIN(MAX(ROUND(ROUND('Loonschijven_Tranches salariale'!$Q15*0.65,4)*Basisbedragen!$I$7,2),ROUND(Basisbedragen!$D$38*Basisbedragen!$I$7,2)),ROUND(ROUND(Basisbedragen!$D$27*0.65,4)*Basisbedragen!$I$7,2))<= Basisbedragen!$I$8,MIN(MAX(ROUND(ROUND('Loonschijven_Tranches salariale'!$Q15*0.65,4)*Basisbedragen!$I$2,2),ROUND(Basisbedragen!$D$38*Basisbedragen!$I$2,2)),ROUND(ROUND(Basisbedragen!$D$27*0.65,4)*Basisbedragen!$I$2,2)),MIN(MAX(ROUND(ROUND('Loonschijven_Tranches salariale'!$Q15*0.65,4)*Basisbedragen!$I$7,2),ROUND(Basisbedragen!$D$38*Basisbedragen!$I$7,2)),ROUND(ROUND(Basisbedragen!$D$27*0.65,4)*Basisbedragen!$I$7,2))+Basisbedragen!$I$10) -> 60.92 | P20: =IF(MIN(MAX(ROUND(ROUND('Loonschijven_Tranches salariale'!$Q15*0.6,4)*Basisbedragen!$I$7,2),ROUND(Basisbedragen!$D$39*Basisbedragen!$I$7,2)),ROUND(ROUND(Basisbedragen!$D$28*0.6,4)*Basisbedragen!$I$7,2))<= Basisbedragen!$I$8,MIN(MAX(ROUND(ROUND('Loonschijven_Tranches salariale'!$Q15*0.6,4)*Basisbedragen!$I$2,2),ROUND(Basisbedragen!$D$39*Basisbedragen!$I$2,2)),ROUND(ROUND(Basisbedragen!$D$28*0.6,4)*Basisbedragen!$I$2,2)),MIN(MAX(ROUND(ROUND('Loonschijven_Tranches salariale'!$Q15*0.6,4)*Basisbedragen!$I$7,2),ROUND(Basisbedragen!$D$39*Basisbedragen!$I$7,2)),ROUND(ROUND(Basisbedragen!$D$28*0.6,4)*Basisbedragen!$I$7,2))+Basisbedragen!$I$10) -> 56.23 | Q20: =MIN(MAX(ROUND(ROUND('Loonschijven_Tranches salariale'!$Q15*0.6,4)*Basisbedragen!$I$2,2),ROUND(Basisbedragen!$D$40*Basisbedragen!$I$2,2)),ROUND(ROUND(Basisbedragen!$D$29*0.6,4)*Basisbedragen!$I$2,2)) -> 51.12 | S20: =$S$12 -> 42.37 | T20: =$T$12 -> 29.85
A21: =A20+1 -> 9 | C21: =IF(MIN(MAX(ROUND(ROUND('Loonschijven_Tranches salariale'!$Q16*0.65,4)*Basisbedragen!$I$7,2),ROUND(Basisbedragen!$D$34*Basisbedragen!$I$7,2)),ROUND(ROUND(Basisbedragen!$D$27*0.65,4)*Basisbedragen!$I$7,2))<= Basisbedragen!$I$8,MIN(MAX(ROUND(ROUND('Loonschijven_Tranches salariale'!$Q16*0.65,4)*Basisbedragen!$I$2,2),ROUND(Basisbedragen!$D$34*Basisbedragen!$I$2,2)),ROUND(ROUND(Basisbedragen!$D$27*0.65,4)*Basisbedragen!$I$2,2)),MIN(MAX(ROUND(ROUND('Loonschijven_Tranches salariale'!$Q16*0.65,4)*Basisbedragen!$I$7,2),ROUND(Basisbedragen!$D$34*Basisbedragen!$I$7,2)),ROUND(ROUND(Basisbedragen!$D$27*0.65,4)*Basisbedragen!$I$7,2))+Basisbedragen!$I$10) -> 78.09 | D21: =IF(MIN(MAX(ROUND(ROUND('Loonschijven_Tranches salariale'!$Q16*0.6,4)*Basisbedragen!$I$7,2),ROUND(Basisbedragen!$D$34*Basisbedragen!$I$7,2)),ROUND(ROUND(Basisbedragen!$D$28*0.6,4)*Basisbedragen!$I$7,2))<= Basisbedragen!$I$8,MIN(MAX(ROUND(ROUND('Loonschijven_Tranches salariale'!$Q16*0.6,4)*Basisbedragen!$I$2,2),ROUND(Basisbedragen!$D$34*Basisbedragen!$I$2,2)),ROUND(ROUND(Basisbedragen!$D$28*0.6,4)*Basisbedragen!$I$2,2)),MIN(MAX(ROUND(ROUND('Loonschijven_Tranches salariale'!$Q16*0.6,4)*Basisbedragen!$I$7,2),ROUND(Basisbedragen!$D$34*Basisbedragen!$I$7,2)),ROUND(ROUND(Basisbedragen!$D$28*0.6,4)*Basisbedragen!$I$7,2))+Basisbedragen!$I$10) -> 78.09 | E21: =MIN(MAX(ROUND(ROUND('Loonschijven_Tranches salariale'!$Q16*0.6,4)*Basisbedragen!$I$2,2),ROUND(Basisbedragen!$D$35*Basisbedragen!$I$2,2)),ROUND(ROUND(Basisbedragen!$D$29*0.6,4)*Basisbedragen!$I$2,2)) -> 70.99 | G21: =$E$12 -> 70.99 | I21: =IF(MIN(MAX(ROUND(ROUND('Loonschijven_Tranches salariale'!$Q16*0.65,4)*Basisbedragen!$I$7,2),ROUND(Basisbedragen!$D$36*Basisbedragen!$I$7,2)),ROUND(ROUND(Basisbedragen!$D$27*0.65,4)*Basisbedragen!$I$7,2))<= Basisbedragen!$I$8,MIN(MAX(ROUND(ROUND('Loonschijven_Tranches salariale'!$Q16*0.65,4)*Basisbedragen!$I$2,2),ROUND(Basisbedragen!$D$36*Basisbedragen!$I$2,2)),ROUND(ROUND(Basisbedragen!$D$27*0.65,4)*Basisbedragen!$I$2,2)),MIN(MAX(ROUND(ROUND('Loonschijven_Tranches salariale'!$Q16*0.65,4)*Basisbedragen!$I$7,2),ROUND(Basisbedragen!$D$36*Basisbedragen!$I$7,2)),ROUND(ROUND(Basisbedragen!$D$27*0.65,4)*Basisbedragen!$I$7,2))+Basisbedragen!$I$10) -> 63.29 | J21: =IF(MIN(MAX(ROUND(ROUND('Loonschijven_Tranches salariale'!$Q16*0.6,4)*Basisbedragen!$I$7,2),ROUND(Basisbedragen!$D$36*Basisbedragen!$I$7,2)),ROUND(ROUND(Basisbedragen!$D$28*0.6,4)*Basisbedragen!$I$7,2))<= Basisbedragen!$I$8,MIN(MAX(ROUND(ROUND('Loonschijven_Tranches salariale'!$Q16*0.6,4)*Basisbedragen!$I$2,2),ROUND(Basisbedragen!$D$36*Basisbedragen!$I$2,2)),ROUND(ROUND(Basisbedragen!$D$28*0.6,4)*Basisbedragen!$I$2,2)),MIN(MAX(ROUND(ROUND('Loonschijven_Tranches salariale'!$Q16*0.6,4)*Basisbedragen!$I$7,2),ROUND(Basisbedragen!$D$36*Basisbedragen!$I$7,2)),ROUND(ROUND(Basisbedragen!$D$28*0.6,4)*Basisbedragen!$I$7,2))+Basisbedragen!$I$10) -> 63.29 | K21: =MIN(MAX(ROUND(ROUND('Loonschijven_Tranches salariale'!$Q16*0.6,4)*Basisbedragen!$I$2,2),ROUND(Basisbedragen!$D$37*Basisbedragen!$I$2,2)),ROUND(ROUND(Basisbedragen!$D$29*0.6,4)*Basisbedragen!$I$2,2)) -> 57.53 | M21: =$K$12 -> 57.53 | O21: =IF(MIN(MAX(ROUND(ROUND('Loonschijven_Tranches salariale'!$Q16*0.65,4)*Basisbedragen!$I$7,2),ROUND(Basisbedragen!$D$38*Basisbedragen!$I$7,2)),ROUND(ROUND(Basisbedragen!$D$27*0.65,4)*Basisbedragen!$I$7,2))<= Basisbedragen!$I$8,MIN(MAX(ROUND(ROUND('Loonschijven_Tranches salariale'!$Q16*0.65,4)*Basisbedragen!$I$2,2),ROUND(Basisbedragen!$D$38*Basisbedragen!$I$2,2)),ROUND(ROUND(Basisbedragen!$D$27*0.65,4)*Basisbedragen!$I$2,2)),MIN(MAX(ROUND(ROUND('Loonschijven_Tranches salariale'!$Q16*0.65,4)*Basisbedragen!$I$7,2),ROUND(Basisbedragen!$D$38*Basisbedragen!$I$7,2)),ROUND(ROUND(Basisbedragen!$D$27*0.65,4)*Basisbedragen!$I$7,2))+Basisbedragen!$I$10) -> 60.92 | P21: =IF(MIN(MAX(ROUND(ROUND('Loonschijven_Tranches salariale'!$Q16*0.6,4)*Basisbedragen!$I$7,2),ROUND(Basisbedragen!$D$39*Basisbedragen!$I$7,2)),ROUND(ROUND(Basisbedragen!$D$28*0.6,4)*Basisbedragen!$I$7,2))<= Basisbedragen!$I$8,MIN(MAX(ROUND(ROUND('Loonschijven_Tranches salariale'!$Q16*0.6,4)*Basisbedragen!$I$2,2),ROUND(Basisbedragen!$D$39*Basisbedragen!$I$2,2)),ROUND(ROUND(Basisbedragen!$D$28*0.6,4)*Basisbedragen!$I$2,2)),MIN(MAX(ROUND(ROUND('Loonschijven_Tranches salariale'!$Q16*0.6,4)*Basisbedragen!$I$7,2),ROUND(Basisbedragen!$D$39*Basisbedragen!$I$7,2)),ROUND(ROUND(Basisbedragen!$D$28*0.6,4)*Basisbedragen!$I$7,2))+Basisbedragen!$I$10) -> 56.23 | Q21: =MIN(MAX(ROUND(ROUND('Loonschijven_Tranches salariale'!$Q16*0.6,4)*Basisbedragen!$I$2,2),ROUND(Basisbedragen!$D$40*Basisbedragen!$I$2,2)),ROUND(ROUND(Basisbedragen!$D$29*0.6,4)*Basisbedragen!$I$2,2)) -> 51.12 | S21: =$S$12 -> 42.37 | T21: =$T$12 -> 29.85
A22: =A21+1 -> 10 | C22: =IF(MIN(MAX(ROUND(ROUND('Loonschijven_Tranches salariale'!$Q17*0.65,4)*Basisbedragen!$I$7,2),ROUND(Basisbedragen!$D$34*Basisbedragen!$I$7,2)),ROUND(ROUND(Basisbedragen!$D$27*0.65,4)*Basisbedragen!$I$7,2))<= Basisbedragen!$I$8,MIN(MAX(ROUND(ROUND('Loonschijven_Tranches salariale'!$Q17*0.65,4)*Basisbedragen!$I$2,2),ROUND(Basisbedragen!$D$34*Basisbedragen!$I$2,2)),ROUND(ROUND(Basisbedragen!$D$27*0.65,4)*Basisbedragen!$I$2,2)),MIN(MAX(ROUND(ROUND('Loonschijven_Tranches salariale'!$Q17*0.65,4)*Basisbedragen!$I$7,2),ROUND(Basisbedragen!$D$34*Basisbedragen!$I$7,2)),ROUND(ROUND(Basisbedragen!$D$27*0.65,4)*Basisbedragen!$I$7,2))+Basisbedragen!$I$10) -> 78.09 | D22: =IF(MIN(MAX(ROUND(ROUND('Loonschijven_Tranches salariale'!$Q17*0.6,4)*Basisbedragen!$I$7,2),ROUND(Basisbedragen!$D$34*Basisbedragen!$I$7,2)),ROUND(ROUND(Basisbedragen!$D$28*0.6,4)*Basisbedragen!$I$7,2))<= Basisbedragen!$I$8,MIN(MAX(ROUND(ROUND('Loonschijven_Tranches salariale'!$Q17*0.6,4)*Basisbedragen!$I$2,2),ROUND(Basisbedragen!$D$34*Basisbedragen!$I$2,2)),ROUND(ROUND(Basisbedragen!$D$28*0.6,4)*Basisbedragen!$I$2,2)),MIN(MAX(ROUND(ROUND('Loonschijven_Tranches salariale'!$Q17*0.6,4)*Basisbedragen!$I$7,2),ROUND(Basisbedragen!$D$34*Basisbedragen!$I$7,2)),ROUND(ROUND(Basisbedragen!$D$28*0.6,4)*Basisbedragen!$I$7,2))+Basisbedragen!$I$10) -> 78.09 | E22: =MIN(MAX(ROUND(ROUND('Loonschijven_Tranches salariale'!$Q17*0.6,4)*Basisbedragen!$I$2,2),ROUND(Basisbedragen!$D$35*Basisbedragen!$I$2,2)),ROUND(ROUND(Basisbedragen!$D$29*0.6,4)*Basisbedragen!$I$2,2)) -> 70.99 | G22: =$E$12 -> 70.99 | I22: =IF(MIN(MAX(ROUND(ROUND('Loonschijven_Tranches salariale'!$Q17*0.65,4)*Basisbedragen!$I$7,2),ROUND(Basisbedragen!$D$36*Basisbedragen!$I$7,2)),ROUND(ROUND(Basisbedragen!$D$27*0.65,4)*Basisbedragen!$I$7,2))<= Basisbedragen!$I$8,MIN(MAX(ROUND(ROUND('Loonschijven_Tranches salariale'!$Q17*0.65,4)*Basisbedragen!$I$2,2),ROUND(Basisbedragen!$D$36*Basisbedragen!$I$2,2)),ROUND(ROUND(Basisbedragen!$D$27*0.65,4)*Basisbedragen!$I$2,2)),MIN(MAX(ROUND(ROUND('Loonschijven_Tranches salariale'!$Q17*0.65,4)*Basisbedragen!$I$7,2),ROUND(Basisbedragen!$D$36*Basisbedragen!$I$7,2)),ROUND(ROUND(Basisbedragen!$D$27*0.65,4)*Basisbedragen!$I$7,2))+Basisbedragen!$I$10) -> 63.29 | J22: =IF(MIN(MAX(ROUND(ROUND('Loonschijven_Tranches salariale'!$Q17*0.6,4)*Basisbedragen!$I$7,2),ROUND(Basisbedragen!$D$36*Basisbedragen!$I$7,2)),ROUND(ROUND(Basisbedragen!$D$28*0.6,4)*Basisbedragen!$I$7,2))<= Basisbedragen!$I$8,MIN(MAX(ROUND(ROUND('Loonschijven_Tranches salariale'!$Q17*0.6,4)*Basisbedragen!$I$2,2),ROUND(Basisbedragen!$D$36*Basisbedragen!$I$2,2)),ROUND(ROUND(Basisbedragen!$D$28*0.6,4)*Basisbedragen!$I$2,2)),MIN(MAX(ROUND(ROUND('Loonschijven_Tranches salariale'!$Q17*0.6,4)*Basisbedragen!$I$7,2),ROUND(Basisbedragen!$D$36*Basisbedragen!$I$7,2)),ROUND(ROUND(Basisbedragen!$D$28*0.6,4)*Basisbedragen!$I$7,2))+Basisbedragen!$I$10) -> 63.29 | K22: =MIN(MAX(ROUND(ROUND('Loonschijven_Tranches salariale'!$Q17*0.6,4)*Basisbedragen!$I$2,2),ROUND(Basisbedragen!$D$37*Basisbedragen!$I$2,2)),ROUND(ROUND(Basisbedragen!$D$29*0.6,4)*Basisbedragen!$I$2,2)) -> 57.53 | M22: =$K$12 -> 57.53 | O22: =IF(MIN(MAX(ROUND(ROUND('Loonschijven_Tranches salariale'!$Q17*0.65,4)*Basisbedragen!$I$7,2),ROUND(Basisbedragen!$D$38*Basisbedragen!$I$7,2)),ROUND(ROUND(Basisbedragen!$D$27*0.65,4)*Basisbedragen!$I$7,2))<= Basisbedragen!$I$8,MIN(MAX(ROUND(ROUND('Loonschijven_Tranches salariale'!$Q17*0.65,4)*Basisbedragen!$I$2,2),ROUND(Basisbedragen!$D$38*Basisbedragen!$I$2,2)),ROUND(ROUND(Basisbedragen!$D$27*0.65,4)*Basisbedragen!$I$2,2)),MIN(MAX(ROUND(ROUND('Loonschijven_Tranches salariale'!$Q17*0.65,4)*Basisbedragen!$I$7,2),ROUND(Basisbedragen!$D$38*Basisbedragen!$I$7,2)),ROUND(ROUND(Basisbedragen!$D$27*0.65,4)*Basisbedragen!$I$7,2))+Basisbedragen!$I$10) -> 60.92 | P22: =IF(MIN(MAX(ROUND(ROUND('Loonschijven_Tranches salariale'!$Q17*0.6,4)*Basisbedragen!$I$7,2),ROUND(Basisbedragen!$D$39*Basisbedragen!$I$7,2)),ROUND(ROUND(Basisbedragen!$D$28*0.6,4)*Basisbedragen!$I$7,2))<= Basisbedragen!$I$8,MIN(MAX(ROUND(ROUND('Loonschijven_Tranches salariale'!$Q17*0.6,4)*Basisbedragen!$I$2,2),ROUND(Basisbedragen!$D$39*Basisbedragen!$I$2,2)),ROUND(ROUND(Basisbedragen!$D$28*0.6,4)*Basisbedragen!$I$2,2)),MIN(MAX(ROUND(ROUND('Loonschijven_Tranches salariale'!$Q17*0.6,4)*Basisbedragen!$I$7,2),ROUND(Basisbedragen!$D$39*Basisbedragen!$I$7,2)),ROUND(ROUND(Basisbedragen!$D$28*0.6,4)*Basisbedragen!$I$7,2))+Basisbedragen!$I$10) -> 56.23 | Q22: =MIN(MAX(ROUND(ROUND('Loonschijven_Tranches salariale'!$Q17*0.6,4)*Basisbedragen!$I$2,2),ROUND(Basisbedragen!$D$40*Basisbedragen!$I$2,2)),ROUND(ROUND(Basisbedragen!$D$29*0.6,4)*Basisbedragen!$I$2,2)) -> 51.12 | S22: =$S$12 -> 42.37 | T22: =$T$12 -> 29.85
A23: =A22+1 -> 11 | C23: =IF(MIN(MAX(ROUND(ROUND('Loonschijven_Tranches salariale'!$Q18*0.65,4)*Basisbedragen!$I$7,2),ROUND(Basisbedragen!$D$34*Basisbedragen!$I$7,2)),ROUND(ROUND(Basisbedragen!$D$27*0.65,4)*Basisbedragen!$I$7,2))<= Basisbedragen!$I$8,MIN(MAX(ROUND(ROUND('Loonschijven_Tranches salariale'!$Q18*0.65,4)*Basisbedragen!$I$2,2),ROUND(Basisbedragen!$D$34*Basisbedragen!$I$2,2)),ROUND(ROUND(Basisbedragen!$D$27*0.65,4)*Basisbedragen!$I$2,2)),MIN(MAX(ROUND(ROUND('Loonschijven_Tranches salariale'!$Q18*0.65,4)*Basisbedragen!$I$7,2),ROUND(Basisbedragen!$D$34*Basisbedragen!$I$7,2)),ROUND(ROUND(Basisbedragen!$D$27*0.65,4)*Basisbedragen!$I$7,2))+Basisbedragen!$I$10) -> 78.09 | D23: =IF(MIN(MAX(ROUND(ROUND('Loonschijven_Tranches salariale'!$Q18*0.6,4)*Basisbedragen!$I$7,2),ROUND(Basisbedragen!$D$34*Basisbedragen!$I$7,2)),ROUND(ROUND(Basisbedragen!$D$28*0.6,4)*Basisbedragen!$I$7,2))<= Basisbedragen!$I$8,MIN(MAX(ROUND(ROUND('Loonschijven_Tranches salariale'!$Q18*0.6,4)*Basisbedragen!$I$2,2),ROUND(Basisbedragen!$D$34*Basisbedragen!$I$2,2)),ROUND(ROUND(Basisbedragen!$D$28*0.6,4)*Basisbedragen!$I$2,2)),MIN(MAX(ROUND(ROUND('Loonschijven_Tranches salariale'!$Q18*0.6,4)*Basisbedragen!$I$7,2),ROUND(Basisbedragen!$D$34*Basisbedragen!$I$7,2)),ROUND(ROUND(Basisbedragen!$D$28*0.6,4)*Basisbedragen!$I$7,2))+Basisbedragen!$I$10) -> 78.09 | E23: =MIN(MAX(ROUND(ROUND('Loonschijven_Tranches salariale'!$Q18*0.6,4)*Basisbedragen!$I$2,2),ROUND(Basisbedragen!$D$35*Basisbedragen!$I$2,2)),ROUND(ROUND(Basisbedragen!$D$29*0.6,4)*Basisbedragen!$I$2,2)) -> 70.99 | G23: =$E$12 -> 70.99 | I23: =IF(MIN(MAX(ROUND(ROUND('Loonschijven_Tranches salariale'!$Q18*0.65,4)*Basisbedragen!$I$7,2),ROUND(Basisbedragen!$D$36*Basisbedragen!$I$7,2)),ROUND(ROUND(Basisbedragen!$D$27*0.65,4)*Basisbedragen!$I$7,2))<= Basisbedragen!$I$8,MIN(MAX(ROUND(ROUND('Loonschijven_Tranches salariale'!$Q18*0.65,4)*Basisbedragen!$I$2,2),ROUND(Basisbedragen!$D$36*Basisbedragen!$I$2,2)),ROUND(ROUND(Basisbedragen!$D$27*0.65,4)*Basisbedragen!$I$2,2)),MIN(MAX(ROUND(ROUND('Loonschijven_Tranches salariale'!$Q18*0.65,4)*Basisbedragen!$I$7,2),ROUND(Basisbedragen!$D$36*Basisbedragen!$I$7,2)),ROUND(ROUND(Basisbedragen!$D$27*0.65,4)*Basisbedragen!$I$7,2))+Basisbedragen!$I$10) -> 63.29 | J23: =IF(MIN(MAX(ROUND(ROUND('Loonschijven_Tranches salariale'!$Q18*0.6,4)*Basisbedragen!$I$7,2),ROUND(Basisbedragen!$D$36*Basisbedragen!$I$7,2)),ROUND(ROUND(Basisbedragen!$D$28*0.6,4)*Basisbedragen!$I$7,2))<= Basisbedragen!$I$8,MIN(MAX(ROUND(ROUND('Loonschijven_Tranches salariale'!$Q18*0.6,4)*Basisbedragen!$I$2,2),ROUND(Basisbedragen!$D$36*Basisbedragen!$I$2,2)),ROUND(ROUND(Basisbedragen!$D$28*0.6,4)*Basisbedragen!$I$2,2)),MIN(MAX(ROUND(ROUND('Loonschijven_Tranches salariale'!$Q18*0.6,4)*Basisbedragen!$I$7,2),ROUND(Basisbedragen!$D$36*Basisbedragen!$I$7,2)),ROUND(ROUND(Basisbedragen!$D$28*0.6,4)*Basisbedragen!$I$7,2))+Basisbedragen!$I$10) -> 63.29 | K23: =MIN(MAX(ROUND(ROUND('Loonschijven_Tranches salariale'!$Q18*0.6,4)*Basisbedragen!$I$2,2),ROUND(Basisbedragen!$D$37*Basisbedragen!$I$2,2)),ROUND(ROUND(Basisbedragen!$D$29*0.6,4)*Basisbedragen!$I$2,2)) -> 57.53 | M23: =$K$12 -> 57.53 | O23: =IF(MIN(MAX(ROUND(ROUND('Loonschijven_Tranches salariale'!$Q18*0.65,4)*Basisbedragen!$I$7,2),ROUND(Basisbedragen!$D$38*Basisbedragen!$I$7,2)),ROUND(ROUND(Basisbedragen!$D$27*0.65,4)*Basisbedragen!$I$7,2))<= Basisbedragen!$I$8,MIN(MAX(ROUND(ROUND('Loonschijven_Tranches salariale'!$Q18*0.65,4)*Basisbedragen!$I$2,2),ROUND(Basisbedragen!$D$38*Basisbedragen!$I$2,2)),ROUND(ROUND(Basisbedragen!$D$27*0.65,4)*Basisbedragen!$I$2,2)),MIN(MAX(ROUND(ROUND('Loonschijven_Tranches salariale'!$Q18*0.65,4)*Basisbedragen!$I$7,2),ROUND(Basisbedragen!$D$38*Basisbedragen!$I$7,2)),ROUND(ROUND(Basisbedragen!$D$27*0.65,4)*Basisbedragen!$I$7,2))+Basisbedragen!$I$10) -> 60.92 | P23: =IF(MIN(MAX(ROUND(ROUND('Loonschijven_Tranches salariale'!$Q18*0.6,4)*Basisbedragen!$I$7,2),ROUND(Basisbedragen!$D$39*Basisbedragen!$I$7,2)),ROUND(ROUND(Basisbedragen!$D$28*0.6,4)*Basisbedragen!$I$7,2))<= Basisbedragen!$I$8,MIN(MAX(ROUND(ROUND('Loonschijven_Tranches salariale'!$Q18*0.6,4)*Basisbedragen!$I$2,2),ROUND(Basisbedragen!$D$39*Basisbedragen!$I$2,2)),ROUND(ROUND(Basisbedragen!$D$28*0.6,4)*Basisbedragen!$I$2,2)),MIN(MAX(ROUND(ROUND('Loonschijven_Tranches salariale'!$Q18*0.6,4)*Basisbedragen!$I$7,2),ROUND(Basisbedragen!$D$39*Basisbedragen!$I$7,2)),ROUND(ROUND(Basisbedragen!$D$28*0.6,4)*Basisbedragen!$I$7,2))+Basisbedragen!$I$10) -> 56.23 | Q23: =MIN(MAX(ROUND(ROUND('Loonschijven_Tranches salariale'!$Q18*0.6,4)*Basisbedragen!$I$2,2),ROUND(Basisbedragen!$D$40*Basisbedragen!$I$2,2)),ROUND(ROUND(Basisbedragen!$D$29*0.6,4)*Basisbedragen!$I$2,2)) -> 51.12 | S23: =$S$12 -> 42.37 | T23: =$T$12 -> 29.85
A24: =A23+1 -> 12 | C24: =IF(MIN(MAX(ROUND(ROUND('Loonschijven_Tranches salariale'!$Q19*0.65,4)*Basisbedragen!$I$7,2),ROUND(Basisbedragen!$D$34*Basisbedragen!$I$7,2)),ROUND(ROUND(Basisbedragen!$D$27*0.65,4)*Basisbedragen!$I$7,2))<= Basisbedragen!$I$8,MIN(MAX(ROUND(ROUND('Loonschijven_Tranches salariale'!$Q19*0.65,4)*Basisbedragen!$I$2,2),ROUND(Basisbedragen!$D$34*Basisbedragen!$I$2,2)),ROUND(ROUND(Basisbedragen!$D$27*0.65,4)*Basisbedragen!$I$2,2)),MIN(MAX(ROUND(ROUND('Loonschijven_Tranches salariale'!$Q19*0.65,4)*Basisbedragen!$I$7,2),ROUND(Basisbedragen!$D$34*Basisbedragen!$I$7,2)),ROUND(ROUND(Basisbedragen!$D$27*0.65,4)*Basisbedragen!$I$7,2))+Basisbedragen!$I$10) -> 78.09 | D24: =IF(MIN(MAX(ROUND(ROUND('Loonschijven_Tranches salariale'!$Q19*0.6,4)*Basisbedragen!$I$7,2),ROUND(Basisbedragen!$D$34*Basisbedragen!$I$7,2)),ROUND(ROUND(Basisbedragen!$D$28*0.6,4)*Basisbedragen!$I$7,2))<= Basisbedragen!$I$8,MIN(MAX(ROUND(ROUND('Loonschijven_Tranches salariale'!$Q19*0.6,4)*Basisbedragen!$I$2,2),ROUND(Basisbedragen!$D$34*Basisbedragen!$I$2,2)),ROUND(ROUND(Basisbedragen!$D$28*0.6,4)*Basisbedragen!$I$2,2)),MIN(MAX(ROUND(ROUND('Loonschijven_Tranches salariale'!$Q19*0.6,4)*Basisbedragen!$I$7,2),ROUND(Basisbedragen!$D$34*Basisbedragen!$I$7,2)),ROUND(ROUND(Basisbedragen!$D$28*0.6,4)*Basisbedragen!$I$7,2))+Basisbedragen!$I$10) -> 78.09 | E24: =MIN(MAX(ROUND(ROUND('Loonschijven_Tranches salariale'!$Q19*0.6,4)*Basisbedragen!$I$2,2),ROUND(Basisbedragen!$D$35*Basisbedragen!$I$2,2)),ROUND(ROUND(Basisbedragen!$D$29*0.6,4)*Basisbedragen!$I$2,2)) -> 70.99 | G24: =$E$12 -> 70.99 | I24: =IF(MIN(MAX(ROUND(ROUND('Loonschijven_Tranches salariale'!$Q19*0.65,4)*Basisbedragen!$I$7,2),ROUND(Basisbedragen!$D$36*Basisbedragen!$I$7,2)),ROUND(ROUND(Basisbedragen!$D$27*0.65,4)*Basisbedragen!$I$7,2))<= Basisbedragen!$I$8,MIN(MAX(ROUND(ROUND('Loonschijven_Tranches salariale'!$Q19*0.65,4)*Basisbedragen!$I$2,2),ROUND(Basisbedragen!$D$36*Basisbedragen!$I$2,2)),ROUND(ROUND(Basisbedragen!$D$27*0.65,4)*Basisbedragen!$I$2,2)),MIN(MAX(ROUND(ROUND('Loonschijven_Tranches salariale'!$Q19*0.65,4)*Basisbedragen!$I$7,2),ROUND(Basisbedragen!$D$36*Basisbedragen!$I$7,2)),ROUND(ROUND(Basisbedragen!$D$27*0.65,4)*Basisbedragen!$I$7,2))+Basisbedragen!$I$10) -> 63.29 | J24: =IF(MIN(MAX(ROUND(ROUND('Loonschijven_Tranches salariale'!$Q19*0.6,4)*Basisbedragen!$I$7,2),ROUND(Basisbedragen!$D$36*Basisbedragen!$I$7,2)),ROUND(ROUND(Basisbedragen!$D$28*0.6,4)*Basisbedragen!$I$7,2))<= Basisbedragen!$I$8,MIN(MAX(ROUND(ROUND('Loonschijven_Tranches salariale'!$Q19*0.6,4)*Basisbedragen!$I$2,2),ROUND(Basisbedragen!$D$36*Basisbedragen!$I$2,2)),ROUND(ROUND(Basisbedragen!$D$28*0.6,4)*Basisbedragen!$I$2,2)),MIN(MAX(ROUND(ROUND('Loonschijven_Tranches salariale'!$Q19*0.6,4)*Basisbedragen!$I$7,2),ROUND(Basisbedragen!$D$36*Basisbedragen!$I$7,2)),ROUND(ROUND(Basisbedragen!$D$28*0.6,4)*Basisbedragen!$I$7,2))+Basisbedragen!$I$10) -> 63.29 | K24: =MIN(MAX(ROUND(ROUND('Loonschijven_Tranches salariale'!$Q19*0.6,4)*Basisbedragen!$I$2,2),ROUND(Basisbedragen!$D$37*Basisbedragen!$I$2,2)),ROUND(ROUND(Basisbedragen!$D$29*0.6,4)*Basisbedragen!$I$2,2)) -> 57.53 | M24: =$K$12 -> 57.53 | O24: =IF(MIN(MAX(ROUND(ROUND('Loonschijven_Tranches salariale'!$Q19*0.65,4)*Basisbedragen!$I$7,2),ROUND(Basisbedragen!$D$38*Basisbedragen!$I$7,2)),ROUND(ROUND(Basisbedragen!$D$27*0.65,4)*Basisbedragen!$I$7,2))<= Basisbedragen!$I$8,MIN(MAX(ROUND(ROUND('Loonschijven_Tranches salariale'!$Q19*0.65,4)*Basisbedragen!$I$2,2),ROUND(Basisbedragen!$D$38*Basisbedragen!$I$2,2)),ROUND(ROUND(Basisbedragen!$D$27*0.65,4)*Basisbedragen!$I$2,2)),MIN(MAX(ROUND(ROUND('Loonschijven_Tranches salariale'!$Q19*0.65,4)*Basisbedragen!$I$7,2),ROUND(Basisbedragen!$D$38*Basisbedragen!$I$7,2)),ROUND(ROUND(Basisbedragen!$D$27*0.65,4)*Basisbedragen!$I$7,2))+Basisbedragen!$I$10) -> 60.92 | P24: =IF(MIN(MAX(ROUND(ROUND('Loonschijven_Tranches salariale'!$Q19*0.6,4)*Basisbedragen!$I$7,2),ROUND(Basisbedragen!$D$39*Basisbedragen!$I$7,2)),ROUND(ROUND(Basisbedragen!$D$28*0.6,4)*Basisbedragen!$I$7,2))<= Basisbedragen!$I$8,MIN(MAX(ROUND(ROUND('Loonschijven_Tranches salariale'!$Q19*0.6,4)*Basisbedragen!$I$2,2),ROUND(Basisbedragen!$D$39*Basisbedragen!$I$2,2)),ROUND(ROUND(Basisbedragen!$D$28*0.6,4)*Basisbedragen!$I$2,2)),MIN(MAX(ROUND(ROUND('Loonschijven_Tranches salariale'!$Q19*0.6,4)*Basisbedragen!$I$7,2),ROUND(Basisbedragen!$D$39*Basisbedragen!$I$7,2)),ROUND(ROUND(Basisbedragen!$D$28*0.6,4)*Basisbedragen!$I$7,2))+Basisbedragen!$I$10) -> 56.23 | Q24: =MIN(MAX(ROUND(ROUND('Loonschijven_Tranches salariale'!$Q19*0.6,4)*Basisbedragen!$I$2,2),ROUND(Basisbedragen!$D$40*Basisbedragen!$I$2,2)),ROUND(ROUND(Basisbedragen!$D$29*0.6,4)*Basisbedragen!$I$2,2)) -> 51.12 | S24: =$S$12 -> 42.37 | T24: =$T$12 -> 29.85
A25: =A24+1 -> 13 | C25: =IF(MIN(MAX(ROUND(ROUND('Loonschijven_Tranches salariale'!$Q20*0.65,4)*Basisbedragen!$I$7,2),ROUND(Basisbedragen!$D$34*Basisbedragen!$I$7,2)),ROUND(ROUND(Basisbedragen!$D$27*0.65,4)*Basisbedragen!$I$7,2))<= Basisbedragen!$I$8,MIN(MAX(ROUND(ROUND('Loonschijven_Tranches salariale'!$Q20*0.65,4)*Basisbedragen!$I$2,2),ROUND(Basisbedragen!$D$34*Basisbedragen!$I$2,2)),ROUND(ROUND(Basisbedragen!$D$27*0.65,4)*Basisbedragen!$I$2,2)),MIN(MAX(ROUND(ROUND('Loonschijven_Tranches salariale'!$Q20*0.65,4)*Basisbedragen!$I$7,2),ROUND(Basisbedragen!$D$34*Basisbedragen!$I$7,2)),ROUND(ROUND(Basisbedragen!$D$27*0.65,4)*Basisbedragen!$I$7,2))+Basisbedragen!$I$10) -> 78.09 | D25: =IF(MIN(MAX(ROUND(ROUND('Loonschijven_Tranches salariale'!$Q20*0.6,4)*Basisbedragen!$I$7,2),ROUND(Basisbedragen!$D$34*Basisbedragen!$I$7,2)),ROUND(ROUND(Basisbedragen!$D$28*0.6,4)*Basisbedragen!$I$7,2))<= Basisbedragen!$I$8,MIN(MAX(ROUND(ROUND('Loonschijven_Tranches salariale'!$Q20*0.6,4)*Basisbedragen!$I$2,2),ROUND(Basisbedragen!$D$34*Basisbedragen!$I$2,2)),ROUND(ROUND(Basisbedragen!$D$28*0.6,4)*Basisbedragen!$I$2,2)),MIN(MAX(ROUND(ROUND('Loonschijven_Tranches salariale'!$Q20*0.6,4)*Basisbedragen!$I$7,2),ROUND(Basisbedragen!$D$34*Basisbedragen!$I$7,2)),ROUND(ROUND(Basisbedragen!$D$28*0.6,4)*Basisbedragen!$I$7,2))+Basisbedragen!$I$10) -> 78.09 | E25: =MIN(MAX(ROUND(ROUND('Loonschijven_Tranches salariale'!$Q20*0.6,4)*Basisbedragen!$I$2,2),ROUND(Basisbedragen!$D$35*Basisbedragen!$I$2,2)),ROUND(ROUND(Basisbedragen!$D$29*0.6,4)*Basisbedragen!$I$2,2)) -> 70.99 | G25: =$E$12 -> 70.99 | I25: =IF(MIN(MAX(ROUND(ROUND('Loonschijven_Tranches salariale'!$Q20*0.65,4)*Basisbedragen!$I$7,2),ROUND(Basisbedragen!$D$36*Basisbedragen!$I$7,2)),ROUND(ROUND(Basisbedragen!$D$27*0.65,4)*Basisbedragen!$I$7,2))<= Basisbedragen!$I$8,MIN(MAX(ROUND(ROUND('Loonschijven_Tranches salariale'!$Q20*0.65,4)*Basisbedragen!$I$2,2),ROUND(Basisbedragen!$D$36*Basisbedragen!$I$2,2)),ROUND(ROUND(Basisbedragen!$D$27*0.65,4)*Basisbedragen!$I$2,2)),MIN(MAX(ROUND(ROUND('Loonschijven_Tranches salariale'!$Q20*0.65,4)*Basisbedragen!$I$7,2),ROUND(Basisbedragen!$D$36*Basisbedragen!$I$7,2)),ROUND(ROUND(Basisbedragen!$D$27*0.65,4)*Basisbedragen!$I$7,2))+Basisbedragen!$I$10) -> 63.29 | J25: =IF(MIN(MAX(ROUND(ROUND('Loonschijven_Tranches salariale'!$Q20*0.6,4)*Basisbedragen!$I$7,2),ROUND(Basisbedragen!$D$36*Basisbedragen!$I$7,2)),ROUND(ROUND(Basisbedragen!$D$28*0.6,4)*Basisbedragen!$I$7,2))<= Basisbedragen!$I$8,MIN(MAX(ROUND(ROUND('Loonschijven_Tranches salariale'!$Q20*0.6,4)*Basisbedragen!$I$2,2),ROUND(Basisbedragen!$D$36*Basisbedragen!$I$2,2)),ROUND(ROUND(Basisbedragen!$D$28*0.6,4)*Basisbedragen!$I$2,2)),MIN(MAX(ROUND(ROUND('Loonschijven_Tranches salariale'!$Q20*0.6,4)*Basisbedragen!$I$7,2),ROUND(Basisbedragen!$D$36*Basisbedragen!$I$7,2)),ROUND(ROUND(Basisbedragen!$D$28*0.6,4)*Basisbedragen!$I$7,2))+Basisbedragen!$I$10) -> 63.29 | K25: =MIN(MAX(ROUND(ROUND('Loonschijven_Tranches salariale'!$Q20*0.6,4)*Basisbedragen!$I$2,2),ROUND(Basisbedragen!$D$37*Basisbedragen!$I$2,2)),ROUND(ROUND(Basisbedragen!$D$29*0.6,4)*Basisbedragen!$I$2,2)) -> 57.53 | M25: =$K$12 -> 57.53 | O25: =IF(MIN(MAX(ROUND(ROUND('Loonschijven_Tranches salariale'!$Q20*0.65,4)*Basisbedragen!$I$7,2),ROUND(Basisbedragen!$D$38*Basisbedragen!$I$7,2)),ROUND(ROUND(Basisbedragen!$D$27*0.65,4)*Basisbedragen!$I$7,2))<= Basisbedragen!$I$8,MIN(MAX(ROUND(ROUND('Loonschijven_Tranches salariale'!$Q20*0.65,4)*Basisbedragen!$I$2,2),ROUND(Basisbedragen!$D$38*Basisbedragen!$I$2,2)),ROUND(ROUND(Basisbedragen!$D$27*0.65,4)*Basisbedragen!$I$2,2)),MIN(MAX(ROUND(ROUND('Loonschijven_Tranches salariale'!$Q20*0.65,4)*Basisbedragen!$I$7,2),ROUND(Basisbedragen!$D$38*Basisbedragen!$I$7,2)),ROUND(ROUND(Basisbedragen!$D$27*0.65,4)*Basisbedragen!$I$7,2))+Basisbedragen!$I$10) -> 60.92 | P25: =IF(MIN(MAX(ROUND(ROUND('Loonschijven_Tranches salariale'!$Q20*0.6,4)*Basisbedragen!$I$7,2),ROUND(Basisbedragen!$D$39*Basisbedragen!$I$7,2)),ROUND(ROUND(Basisbedragen!$D$28*0.6,4)*Basisbedragen!$I$7,2))<= Basisbedragen!$I$8,MIN(MAX(ROUND(ROUND('Loonschijven_Tranches salariale'!$Q20*0.6,4)*Basisbedragen!$I$2,2),ROUND(Basisbedragen!$D$39*Basisbedragen!$I$2,2)),ROUND(ROUND(Basisbedragen!$D$28*0.6,4)*Basisbedragen!$I$2,2)),MIN(MAX(ROUND(ROUND('Loonschijven_Tranches salariale'!$Q20*0.6,4)*Basisbedragen!$I$7,2),ROUND(Basisbedragen!$D$39*Basisbedragen!$I$7,2)),ROUND(ROUND(Basisbedragen!$D$28*0.6,4)*Basisbedragen!$I$7,2))+Basisbedragen!$I$10) -> 56.23 | Q25: =MIN(MAX(ROUND(ROUND('Loonschijven_Tranches salariale'!$Q20*0.6,4)*Basisbedragen!$I$2,2),ROUND(Basisbedragen!$D$40*Basisbedragen!$I$2,2)),ROUND(ROUND(Basisbedragen!$D$29*0.6,4)*Basisbedragen!$I$2,2)) -> 51.12 | S25: =$S$12 -> 42.37 | T25: =$T$12 -> 29.85
... A111: =A110+1 -> 99 | C111: =IF(MIN(MAX(ROUND(ROUND('Loonschijven_Tranches salariale'!$Q106*0.65,4)*Basisbedragen!$I$7,2),ROUND(Basisbedragen!$D$34*Basisbedragen!$I$7,2)),ROUND(ROUND(Basisbedragen!$D$27*0.65,4)*Basisbedragen!$I$7,2))<= Basisbedragen!$I$8,MIN(MAX(ROUND(ROUND('Loonschijven_Tranches salariale'!$Q106*0.65,4)*Basisbedragen!$I$2,2),ROUND(Basisbedragen!$D$34*Basisbedragen!$I$2,2)),ROUND(ROUND(Basisbedragen!$D$27*0.65,4)*Basisbedragen!$I$2,2)),MIN(MAX(ROUND(ROUND('Loonschijven_Tranches salariale'!$Q106*0.65,4)*Basisbedragen!$I$7,2),ROUND(Basisbedragen!$D$34*Basisbedragen!$I$7,2)),ROUND(ROUND(Basisbedragen!$D$27*0.65,4)*Basisbedragen!$I$7,2))+Basisbedragen!$I$10) -> 108.19 | D111: =IF(MIN(MAX(ROUND(ROUND('Loonschijven_Tranches salariale'!$Q106*0.6,4)*Basisbedragen!$I$7,2),ROUND(Basisbedragen!$D$34*Basisbedragen!$I$7,2)),ROUND(ROUND(Basisbedragen!$D$28*0.6,4)*Basisbedragen!$I$7,2))<= Basisbedragen!$I$8,MIN(MAX(ROUND(ROUND('Loonschijven_Tranches salariale'!$Q106*0.6,4)*Basisbedragen!$I$2,2),ROUND(Basisbedragen!$D$34*Basisbedragen!$I$2,2)),ROUND(ROUND(Basisbedragen!$D$28*0.6,4)*Basisbedragen!$I$2,2)),MIN(MAX(ROUND(ROUND('Loonschijven_Tranches salariale'!$Q106*0.6,4)*Basisbedragen!$I$7,2),ROUND(Basisbedragen!$D$34*Basisbedragen!$I$7,2)),ROUND(ROUND(Basisbedragen!$D$28*0.6,4)*Basisbedragen!$I$7,2))+Basisbedragen!$I$10) -> 94.1 | E111: =MIN(MAX(ROUND(ROUND('Loonschijven_Tranches salariale'!$Q106*0.6,4)*Basisbedragen!$I$2,2),ROUND(Basisbedragen!$D$35*Basisbedragen!$I$2,2)),ROUND(ROUND(Basisbedragen!$D$29*0.6,4)*Basisbedragen!$I$2,2)) -> 76.81 | G111: =$E$12 -> 70.99 | I111: =IF(MIN(MAX(ROUND(ROUND('Loonschijven_Tranches salariale'!$Q106*0.65,4)*Basisbedragen!$I$7,2),ROUND(Basisbedragen!$D$36*Basisbedragen!$I$7,2)),ROUND(ROUND(Basisbedragen!$D$27*0.65,4)*Basisbedragen!$I$7,2))<= Basisbedragen!$I$8,MIN(MAX(ROUND(ROUND('Loonschijven_Tranches salariale'!$Q106*0.65,4)*Basisbedragen!$I$2,2),ROUND(Basisbedragen!$D$36*Basisbedragen!$I$2,2)),ROUND(ROUND(Basisbedragen!$D$27*0.65,4)*Basisbedragen!$I$2,2)),MIN(MAX(ROUND(ROUND('Loonschijven_Tranches salariale'!$Q106*0.65,4)*Basisbedragen!$I$7,2),ROUND(Basisbedragen!$D$36*Basisbedragen!$I$7,2)),ROUND(ROUND(Basisbedragen!$D$27*0.65,4)*Basisbedragen!$I$7,2))+Basisbedragen!$I$10) -> 108.19 | J111: =IF(MIN(MAX(ROUND(ROUND('Loonschijven_Tranches salariale'!$Q106*0.6,4)*Basisbedragen!$I$7,2),ROUND(Basisbedragen!$D$36*Basisbedragen!$I$7,2)),ROUND(ROUND(Basisbedragen!$D$28*0.6,4)*Basisbedragen!$I$7,2))<= Basisbedragen!$I$8,MIN(MAX(ROUND(ROUND('Loonschijven_Tranches salariale'!$Q106*0.6,4)*Basisbedragen!$I$2,2),ROUND(Basisbedragen!$D$36*Basisbedragen!$I$2,2)),ROUND(ROUND(Basisbedragen!$D$28*0.6,4)*Basisbedragen!$I$2,2)),MIN(MAX(ROUND(ROUND('Loonschijven_Tranches salariale'!$Q106*0.6,4)*Basisbedragen!$I$7,2),ROUND(Basisbedragen!$D$36*Basisbedragen!$I$7,2)),ROUND(ROUND(Basisbedragen!$D$28*0.6,4)*Basisbedragen!$I$7,2))+Basisbedragen!$I$10) -> 94.1 | K111: =MIN(MAX(ROUND(ROUND('Loonschijven_Tranches salariale'!$Q106*0.6,4)*Basisbedragen!$I$2,2),ROUND(Basisbedragen!$D$37*Basisbedragen!$I$2,2)),ROUND(ROUND(Basisbedragen!$D$29*0.6,4)*Basisbedragen!$I$2,2)) -> 76.81 | M111: =$K$12 -> 57.53 | O111: =IF(MIN(MAX(ROUND(ROUND('Loonschijven_Tranches salariale'!$Q106*0.65,4)*Basisbedragen!$I$7,2),ROUND(Basisbedragen!$D$38*Basisbedragen!$I$7,2)),ROUND(ROUND(Basisbedragen!$D$27*0.65,4)*Basisbedragen!$I$7,2))<= Basisbedragen!$I$8,MIN(MAX(ROUND(ROUND('Loonschijven_Tranches salariale'!$Q106*0.65,4)*Basisbedragen!$I$2,2),ROUND(Basisbedragen!$D$38*Basisbedragen!$I$2,2)),ROUND(ROUND(Basisbedragen!$D$27*0.65,4)*Basisbedragen!$I$2,2)),MIN(MAX(ROUND(ROUND('Loonschijven_Tranches salariale'!$Q106*0.65,4)*Basisbedragen!$I$7,2),ROUND(Basisbedragen!$D$38*Basisbedragen!$I$7,2)),ROUND(ROUND(Basisbedragen!$D$27*0.65,4)*Basisbedragen!$I$7,2))+Basisbedragen!$I$10) -> 108.19 | P111: =IF(MIN(MAX(ROUND(ROUND('Loonschijven_Tranches salariale'!$Q106*0.6,4)*Basisbedragen!$I$7,2),ROUND(Basisbedragen!$D$39*Basisbedragen!$I$7,2)),ROUND(ROUND(Basisbedragen!$D$28*0.6,4)*Basisbedragen!$I$7,2))<= Basisbedragen!$I$8,MIN(MAX(ROUND(ROUND('Loonschijven_Tranches salariale'!$Q106*0.6,4)*Basisbedragen!$I$2,2),ROUND(Basisbedragen!$D$39*Basisbedragen!$I$2,2)),ROUND(ROUND(Basisbedragen!$D$28*0.6,4)*Basisbedragen!$I$2,2)),MIN(MAX(ROUND(ROUND('Loonschijven_Tranches salariale'!$Q106*0.6,4)*Basisbedragen!$I$7,2),ROUND(Basisbedragen!$D$39*Basisbedragen!$I$7,2)),ROUND(ROUND(Basisbedragen!$D$28*0.6,4)*Basisbedragen!$I$7,2))+Basisbedragen!$I$10) -> 94.1 | Q111: =MIN(MAX(ROUND(ROUND('Loonschijven_Tranches salariale'!$Q106*0.6,4)*Basisbedragen!$I$2,2),ROUND(Basisbedragen!$D$40*Basisbedragen!$I$2,2)),ROUND(ROUND(Basisbedragen!$D$29*0.6,4)*Basisbedragen!$I$2,2)) -> 76.81 | S111: =$S$12 -> 42.37 | T111: =$T$12 -> 29.85

Sheet A_N_B_half_demi
A1: Geldig/valable | C1: Volledige werkloosheidsuitkeringen - dagbedrag van de halve uitkering | U1: Multiplicat(o)(eu)r | W1: =Basisbedragen!$I$2 -> 1.8114
A2: 46266 | C2: Allocations de chômage complet - montant journalier de la demi allocation
C4: Werknemers met gezinslast Travailleurs ayant charge de famille | I4: Alleenwonenden Isolés | O4: Samenwonenden Cohabitants
C6: 1e periode | G6: 2e per | I6: 1e periode | M6: 2e per | O6: 1e periode | S6: 2e per | T6: 2ème pér
D7: 1ère période | G7: 2ème pér | J7: 1ère période | M7: 2ème pér | P7: 1ère période | S7: BV+ / PP+ | T7: BV- / PP-
A9: Code | C9: AA1 | D9: AA2 | E9: AA3 | G9: AB AX | I9: NA1 | J9: NA2 | K9: NA3 | M9: NB NX | O9: BA1 | P9: BA2 | Q9: BA3 | S9: BX | T9: BB
O10: 0.65 | P10: 0.6 | Q10: 0.6
C11: 0.65 | D11: 0.6 | E11: 0.6 | I11: 0.65 | J11: 0.6 | K11: 0.6 | O11: 0.65 | P11: 0.6 | Q11: 0.6
A12: MIN | C12: =ROUND(A_N_B_vol_plein!C12/2,2) -> 39.05 | D12: =ROUND(A_N_B_vol_plein!D12/2,2) -> 39.05 | E12: =ROUND(A_N_B_vol_plein!E12/2,2) -> 35.5 | F12: =ROUND(A_N_B_vol_plein!F12/2,2) -> 0 | G12: =E12 -> 35.5 | H12: =ROUND(A_N_B_vol_plein!H12/2,2) -> 0 | I12: =ROUND(A_N_B_vol_plein!I12/2,2) -> 31.65 | J12: =ROUND(A_N_B_vol_plein!J12/2,2) -> 31.65 | K12: =ROUND(A_N_B_vol_plein!K12/2,2) -> 28.77 | L12: =ROUND(A_N_B_vol_plein!L12/2,2) -> 0 | M12: =K12 -> 28.77 | N12: =ROUND(A_N_B_vol_plein!N12/2,2) -> 0 | O12: =ROUND(A_N_B_vol_plein!O12/2,2) -> 30.46 | P12: =ROUND(A_N_B_vol_plein!P12/2,2) -> 28.12 | Q12: =ROUND(A_N_B_vol_plein!Q12/2,2) -> 25.56 | R12: =ROUND(A_N_B_vol_plein!R12/2,2) -> 0 | S12: =ROUND(A_N_B_vol_plein!S12/2,2) -> 21.19 | T12: =ROUND(A_N_B_vol_plein!T12/2,2) -> 14.93
A13: 1 | C13: =ROUND(MIN(MAX(ROUND(ROUND('Loonschijven_Tranches salariale'!$Q8*0.65,4)*Basisbedragen!$I$2,2),ROUND(Basisbedragen!$D$34*Basisbedragen!$I$2,2)),ROUND(ROUND(Basisbedragen!$D$27*0.65,4)*Basisbedragen!$I$2,2))/2,2) -> 39.05 | D13: =ROUND(MIN(MAX(ROUND(ROUND('Loonschijven_Tranches salariale'!$Q8*0.6,4)*Basisbedragen!$I$2,2),ROUND(Basisbedragen!$D$34*Basisbedragen!$I$2,2)),ROUND(ROUND(Basisbedragen!$D$28*0.6,4)*Basisbedragen!$I$2,2))/2,2) -> 39.05 | E13: =ROUND(A_N_B_vol_plein!E13/2,2) -> 35.5 | F13: =ROUND(A_N_B_vol_plein!F13/2,2) -> 0 | G13: =ROUND(A_N_B_vol_plein!G13/2,2) -> 35.5 | H13: =ROUND(A_N_B_vol_plein!H13/2,2) -> 0 | I13: =ROUND(MIN(MAX(ROUND(ROUND('Loonschijven_Tranches salariale'!$Q8*0.65,4)*Basisbedragen!$I$2,2),ROUND(Basisbedragen!$D$36*Basisbedragen!$I$2,2)),ROUND(ROUND(Basisbedragen!$D$27*0.65,4)*Basisbedragen!$I$2,2))/2,2) -> 31.65 | J13: =ROUND(MIN(MAX(ROUND(ROUND('Loonschijven_Tranches salariale'!$Q8*0.6,4)*Basisbedragen!$I$2,2),ROUND(Basisbedragen!$D$36*Basisbedragen!$I$2,2)),ROUND(ROUND(Basisbedragen!$D$28*0.6,4)*Basisbedragen!$I$2,2))/2,2) -> 31.65 | K13: =ROUND(A_N_B_vol_plein!K13/2,2) -> 28.77 | L13: =ROUND(A_N_B_vol_plein!L13/2,2) -> 0 | M13: =ROUND(A_N_B_vol_plein!M13/2,2) -> 28.77 | N13: =ROUND(A_N_B_vol_plein!N13/2,2) -> 0 | O13: =ROUND(MIN(MAX(ROUND(ROUND('Loonschijven_Tranches salariale'!$Q8*0.65,4)*Basisbedragen!$I$2,2),ROUND(Basisbedragen!$D$38*Basisbedragen!$I$2,2)),ROUND(ROUND(Basisbedragen!$D$27*0.65,4)*Basisbedragen!$I$2,2))/2,2) -> 30.46 | P13: =ROUND(MIN(MAX(ROUND(ROUND('Loonschijven_Tranches salariale'!$Q8*0.6,4)*Basisbedragen!$I$2,2),ROUND(Basisbedragen!$D$39*Basisbedragen!$I$2,2)),ROUND(ROUND(Basisbedragen!$D$28*0.6,4)*Basisbedragen!$I$2,2))/2,2) -> 28.12 | Q13: =ROUND(A_N_B_vol_plein!Q13/2,2) -> 25.56 | R13: =ROUND(A_N_B_vol_plein!R13/2,2) -> 0 | S13: =ROUND(A_N_B_vol_plein!S13/2,2) -> 21.19 | T13: =ROUND(A_N_B_vol_plein!T13/2,2) -> 14.93
A14: =A13+1 -> 2 | C14: =ROUND(MIN(MAX(ROUND(ROUND('Loonschijven_Tranches salariale'!$Q9*0.65,4)*Basisbedragen!$I$2,2),ROUND(Basisbedragen!$D$34*Basisbedragen!$I$2,2)),ROUND(ROUND(Basisbedragen!$D$27*0.65,4)*Basisbedragen!$I$2,2))/2,2) -> 39.05 | D14: =ROUND(MIN(MAX(ROUND(ROUND('Loonschijven_Tranches salariale'!$Q9*0.6,4)*Basisbedragen!$I$2,2),ROUND(Basisbedragen!$D$34*Basisbedragen!$I$2,2)),ROUND(ROUND(Basisbedragen!$D$28*0.6,4)*Basisbedragen!$I$2,2))/2,2) -> 39.05 | E14: =ROUND(A_N_B_vol_plein!E14/2,2) -> 35.5 | F14: =ROUND(A_N_B_vol_plein!F14/2,2) -> 0 | G14: =ROUND(A_N_B_vol_plein!G14/2,2) -> 35.5 | H14: =ROUND(A_N_B_vol_plein!H14/2,2) -> 0 | I14: =ROUND(MIN(MAX(ROUND(ROUND('Loonschijven_Tranches salariale'!$Q9*0.65,4)*Basisbedragen!$I$2,2),ROUND(Basisbedragen!$D$36*Basisbedragen!$I$2,2)),ROUND(ROUND(Basisbedragen!$D$27*0.65,4)*Basisbedragen!$I$2,2))/2,2) -> 31.65 | J14: =ROUND(MIN(MAX(ROUND(ROUND('Loonschijven_Tranches salariale'!$Q9*0.6,4)*Basisbedragen!$I$2,2),ROUND(Basisbedragen!$D$36*Basisbedragen!$I$2,2)),ROUND(ROUND(Basisbedragen!$D$28*0.6,4)*Basisbedragen!$I$2,2))/2,2) -> 31.65 | K14: =ROUND(A_N_B_vol_plein!K14/2,2) -> 28.77 | L14: =ROUND(A_N_B_vol_plein!L14/2,2) -> 0 | M14: =ROUND(A_N_B_vol_plein!M14/2,2) -> 28.77 | N14: =ROUND(A_N_B_vol_plein!N14/2,2) -> 0 | O14: =ROUND(MIN(MAX(ROUND(ROUND('Loonschijven_Tranches salariale'!$Q9*0.65,4)*Basisbedragen!$I$2,2),ROUND(Basisbedragen!$D$38*Basisbedragen!$I$2,2)),ROUND(ROUND(Basisbedragen!$D$27*0.65,4)*Basisbedragen!$I$2,2))/2,2) -> 30.46 | P14: =ROUND(MIN(MAX(ROUND(ROUND('Loonschijven_Tranches salariale'!$Q9*0.6,4)*Basisbedragen!$I$2,2),ROUND(Basisbedragen!$D$39*Basisbedragen!$I$2,2)),ROUND(ROUND(Basisbedragen!$D$28*0.6,4)*Basisbedragen!$I$2,2))/2,2) -> 28.12 | Q14: =ROUND(A_N_B_vol_plein!Q14/2,2) -> 25.56 | R14: =ROUND(A_N_B_vol_plein!R14/2,2) -> 0 | S14: =ROUND(A_N_B_vol_plein!S14/2,2) -> 21.19 | T14: =ROUND(A_N_B_vol_plein!T14/2,2) -> 14.93
A15: =A14+1 -> 3 | C15: =ROUND(MIN(MAX(ROUND(ROUND('Loonschijven_Tranches salariale'!$Q10*0.65,4)*Basisbedragen!$I$2,2),ROUND(Basisbedragen!$D$34*Basisbedragen!$I$2,2)),ROUND(ROUND(Basisbedragen!$D$27*0.65,4)*Basisbedragen!$I$2,2))/2,2) -> 39.05 | D15: =ROUND(MIN(MAX(ROUND(ROUND('Loonschijven_Tranches salariale'!$Q10*0.6,4)*Basisbedragen!$I$2,2),ROUND(Basisbedragen!$D$34*Basisbedragen!$I$2,2)),ROUND(ROUND(Basisbedragen!$D$28*0.6,4)*Basisbedragen!$I$2,2))/2,2) -> 39.05 | E15: =ROUND(A_N_B_vol_plein!E15/2,2) -> 35.5 | F15: =ROUND(A_N_B_vol_plein!F15/2,2) -> 0 | G15: =ROUND(A_N_B_vol_plein!G15/2,2) -> 35.5 | H15: =ROUND(A_N_B_vol_plein!H15/2,2) -> 0 | I15: =ROUND(MIN(MAX(ROUND(ROUND('Loonschijven_Tranches salariale'!$Q10*0.65,4)*Basisbedragen!$I$2,2),ROUND(Basisbedragen!$D$36*Basisbedragen!$I$2,2)),ROUND(ROUND(Basisbedragen!$D$27*0.65,4)*Basisbedragen!$I$2,2))/2,2) -> 31.65 | J15: =ROUND(MIN(MAX(ROUND(ROUND('Loonschijven_Tranches salariale'!$Q10*0.6,4)*Basisbedragen!$I$2,2),ROUND(Basisbedragen!$D$36*Basisbedragen!$I$2,2)),ROUND(ROUND(Basisbedragen!$D$28*0.6,4)*Basisbedragen!$I$2,2))/2,2) -> 31.65 | K15: =ROUND(A_N_B_vol_plein!K15/2,2) -> 28.77 | L15: =ROUND(A_N_B_vol_plein!L15/2,2) -> 0 | M15: =ROUND(A_N_B_vol_plein!M15/2,2) -> 28.77 | N15: =ROUND(A_N_B_vol_plein!N15/2,2) -> 0 | O15: =ROUND(MIN(MAX(ROUND(ROUND('Loonschijven_Tranches salariale'!$Q10*0.65,4)*Basisbedragen!$I$2,2),ROUND(Basisbedragen!$D$38*Basisbedragen!$I$2,2)),ROUND(ROUND(Basisbedragen!$D$27*0.65,4)*Basisbedragen!$I$2,2))/2,2) -> 30.46 | P15: =ROUND(MIN(MAX(ROUND(ROUND('Loonschijven_Tranches salariale'!$Q10*0.6,4)*Basisbedragen!$I$2,2),ROUND(Basisbedragen!$D$39*Basisbedragen!$I$2,2)),ROUND(ROUND(Basisbedragen!$D$28*0.6,4)*Basisbedragen!$I$2,2))/2,2) -> 28.12 | Q15: =ROUND(A_N_B_vol_plein!Q15/2,2) -> 25.56 | R15: =ROUND(A_N_B_vol_plein!R15/2,2) -> 0 | S15: =ROUND(A_N_B_vol_plein!S15/2,2) -> 21.19 | T15: =ROUND(A_N_B_vol_plein!T15/2,2) -> 14.93
A16: =A15+1 -> 4 | C16: =ROUND(MIN(MAX(ROUND(ROUND('Loonschijven_Tranches salariale'!$Q11*0.65,4)*Basisbedragen!$I$2,2),ROUND(Basisbedragen!$D$34*Basisbedragen!$I$2,2)),ROUND(ROUND(Basisbedragen!$D$27*0.65,4)*Basisbedragen!$I$2,2))/2,2) -> 39.05 | D16: =ROUND(MIN(MAX(ROUND(ROUND('Loonschijven_Tranches salariale'!$Q11*0.6,4)*Basisbedragen!$I$2,2),ROUND(Basisbedragen!$D$34*Basisbedragen!$I$2,2)),ROUND(ROUND(Basisbedragen!$D$28*0.6,4)*Basisbedragen!$I$2,2))/2,2) -> 39.05 | E16: =ROUND(A_N_B_vol_plein!E16/2,2) -> 35.5 | F16: =ROUND(A_N_B_vol_plein!F16/2,2) -> 0 | G16: =ROUND(A_N_B_vol_plein!G16/2,2) -> 35.5 | H16: =ROUND(A_N_B_vol_plein!H16/2,2) -> 0 | I16: =ROUND(MIN(MAX(ROUND(ROUND('Loonschijven_Tranches salariale'!$Q11*0.65,4)*Basisbedragen!$I$2,2),ROUND(Basisbedragen!$D$36*Basisbedragen!$I$2,2)),ROUND(ROUND(Basisbedragen!$D$27*0.65,4)*Basisbedragen!$I$2,2))/2,2) -> 31.65 | J16: =ROUND(MIN(MAX(ROUND(ROUND('Loonschijven_Tranches salariale'!$Q11*0.6,4)*Basisbedragen!$I$2,2),ROUND(Basisbedragen!$D$36*Basisbedragen!$I$2,2)),ROUND(ROUND(Basisbedragen!$D$28*0.6,4)*Basisbedragen!$I$2,2))/2,2) -> 31.65 | K16: =ROUND(A_N_B_vol_plein!K16/2,2) -> 28.77 | L16: =ROUND(A_N_B_vol_plein!L16/2,2) -> 0 | M16: =ROUND(A_N_B_vol_plein!M16/2,2) -> 28.77 | N16: =ROUND(A_N_B_vol_plein!N16/2,2) -> 0 | O16: =ROUND(MIN(MAX(ROUND(ROUND('Loonschijven_Tranches salariale'!$Q11*0.65,4)*Basisbedragen!$I$2,2),ROUND(Basisbedragen!$D$38*Basisbedragen!$I$2,2)),ROUND(ROUND(Basisbedragen!$D$27*0.65,4)*Basisbedragen!$I$2,2))/2,2) -> 30.46 | P16: =ROUND(MIN(MAX(ROUND(ROUND('Loonschijven_Tranches salariale'!$Q11*0.6,4)*Basisbedragen!$I$2,2),ROUND(Basisbedragen!$D$39*Basisbedragen!$I$2,2)),ROUND(ROUND(Basisbedragen!$D$28*0.6,4)*Basisbedragen!$I$2,2))/2,2) -> 28.12 | Q16: =ROUND(A_N_B_vol_plein!Q16/2,2) -> 25.56 | R16: =ROUND(A_N_B_vol_plein!R16/2,2) -> 0 | S16: =ROUND(A_N_B_vol_plein!S16/2,2) -> 21.19 | T16: =ROUND(A_N_B_vol_plein!T16/2,2) -> 14.93
A17: =A16+1 -> 5 | C17: =ROUND(MIN(MAX(ROUND(ROUND('Loonschijven_Tranches salariale'!$Q12*0.65,4)*Basisbedragen!$I$2,2),ROUND(Basisbedragen!$D$34*Basisbedragen!$I$2,2)),ROUND(ROUND(Basisbedragen!$D$27*0.65,4)*Basisbedragen!$I$2,2))/2,2) -> 39.05 | D17: =ROUND(MIN(MAX(ROUND(ROUND('Loonschijven_Tranches salariale'!$Q12*0.6,4)*Basisbedragen!$I$2,2),ROUND(Basisbedragen!$D$34*Basisbedragen!$I$2,2)),ROUND(ROUND(Basisbedragen!$D$28*0.6,4)*Basisbedragen!$I$2,2))/2,2) -> 39.05 | E17: =ROUND(A_N_B_vol_plein!E17/2,2) -> 35.5 | F17: =ROUND(A_N_B_vol_plein!F17/2,2) -> 0 | G17: =ROUND(A_N_B_vol_plein!G17/2,2) -> 35.5 | H17: =ROUND(A_N_B_vol_plein!H17/2,2) -> 0 | I17: =ROUND(MIN(MAX(ROUND(ROUND('Loonschijven_Tranches salariale'!$Q12*0.65,4)*Basisbedragen!$I$2,2),ROUND(Basisbedragen!$D$36*Basisbedragen!$I$2,2)),ROUND(ROUND(Basisbedragen!$D$27*0.65,4)*Basisbedragen!$I$2,2))/2,2) -> 31.65 | J17: =ROUND(MIN(MAX(ROUND(ROUND('Loonschijven_Tranches salariale'!$Q12*0.6,4)*Basisbedragen!$I$2,2),ROUND(Basisbedragen!$D$36*Basisbedragen!$I$2,2)),ROUND(ROUND(Basisbedragen!$D$28*0.6,4)*Basisbedragen!$I$2,2))/2,2) -> 31.65 | K17: =ROUND(A_N_B_vol_plein!K17/2,2) -> 28.77 | L17: =ROUND(A_N_B_vol_plein!L17/2,2) -> 0 | M17: =ROUND(A_N_B_vol_plein!M17/2,2) -> 28.77 | N17: =ROUND(A_N_B_vol_plein!N17/2,2) -> 0 | O17: =ROUND(MIN(MAX(ROUND(ROUND('Loonschijven_Tranches salariale'!$Q12*0.65,4)*Basisbedragen!$I$2,2),ROUND(Basisbedragen!$D$38*Basisbedragen!$I$2,2)),ROUND(ROUND(Basisbedragen!$D$27*0.65,4)*Basisbedragen!$I$2,2))/2,2) -> 30.46 | P17: =ROUND(MIN(MAX(ROUND(ROUND('Loonschijven_Tranches salariale'!$Q12*0.6,4)*Basisbedragen!$I$2,2),ROUND(Basisbedragen!$D$39*Basisbedragen!$I$2,2)),ROUND(ROUND(Basisbedragen!$D$28*0.6,4)*Basisbedragen!$I$2,2))/2,2) -> 28.12 | Q17: =ROUND(A_N_B_vol_plein!Q17/2,2) -> 25.56 | R17: =ROUND(A_N_B_vol_plein!R17/2,2) -> 0 | S17: =ROUND(A_N_B_vol_plein!S17/2,2) -> 21.19 | T17: =ROUND(A_N_B_vol_plein!T17/2,2) -> 14.93
A18: =A17+1 -> 6 | C18: =ROUND(MIN(MAX(ROUND(ROUND('Loonschijven_Tranches salariale'!$Q13*0.65,4)*Basisbedragen!$I$2,2),ROUND(Basisbedragen!$D$34*Basisbedragen!$I$2,2)),ROUND(ROUND(Basisbedragen!$D$27*0.65,4)*Basisbedragen!$I$2,2))/2,2) -> 39.05 | D18: =ROUND(MIN(MAX(ROUND(ROUND('Loonschijven_Tranches salariale'!$Q13*0.6,4)*Basisbedragen!$I$2,2),ROUND(Basisbedragen!$D$34*Basisbedragen!$I$2,2)),ROUND(ROUND(Basisbedragen!$D$28*0.6,4)*Basisbedragen!$I$2,2))/2,2) -> 39.05 | E18: =ROUND(A_N_B_vol_plein!E18/2,2) -> 35.5 | F18: =ROUND(A_N_B_vol_plein!F18/2,2) -> 0 | G18: =ROUND(A_N_B_vol_plein!G18/2,2) -> 35.5 | H18: =ROUND(A_N_B_vol_plein!H18/2,2) -> 0 | I18: =ROUND(MIN(MAX(ROUND(ROUND('Loonschijven_Tranches salariale'!$Q13*0.65,4)*Basisbedragen!$I$2,2),ROUND(Basisbedragen!$D$36*Basisbedragen!$I$2,2)),ROUND(ROUND(Basisbedragen!$D$27*0.65,4)*Basisbedragen!$I$2,2))/2,2) -> 31.65 | J18: =ROUND(MIN(MAX(ROUND(ROUND('Loonschijven_Tranches salariale'!$Q13*0.6,4)*Basisbedragen!$I$2,2),ROUND(Basisbedragen!$D$36*Basisbedragen!$I$2,2)),ROUND(ROUND(Basisbedragen!$D$28*0.6,4)*Basisbedragen!$I$2,2))/2,2) -> 31.65 | K18: =ROUND(A_N_B_vol_plein!K18/2,2) -> 28.77 | L18: =ROUND(A_N_B_vol_plein!L18/2,2) -> 0 | M18: =ROUND(A_N_B_vol_plein!M18/2,2) -> 28.77 | N18: =ROUND(A_N_B_vol_plein!N18/2,2) -> 0 | O18: =ROUND(MIN(MAX(ROUND(ROUND('Loonschijven_Tranches salariale'!$Q13*0.65,4)*Basisbedragen!$I$2,2),ROUND(Basisbedragen!$D$38*Basisbedragen!$I$2,2)),ROUND(ROUND(Basisbedragen!$D$27*0.65,4)*Basisbedragen!$I$2,2))/2,2) -> 30.46 | P18: =ROUND(MIN(MAX(ROUND(ROUND('Loonschijven_Tranches salariale'!$Q13*0.6,4)*Basisbedragen!$I$2,2),ROUND(Basisbedragen!$D$39*Basisbedragen!$I$2,2)),ROUND(ROUND(Basisbedragen!$D$28*0.6,4)*Basisbedragen!$I$2,2))/2,2) -> 28.12 | Q18: =ROUND(A_N_B_vol_plein!Q18/2,2) -> 25.56 | R18: =ROUND(A_N_B_vol_plein!R18/2,2) -> 0 | S18: =ROUND(A_N_B_vol_plein!S18/2,2) -> 21.19 | T18: =ROUND(A_N_B_vol_plein!T18/2,2) -> 14.93
A19: =A18+1 -> 7 | C19: =ROUND(MIN(MAX(ROUND(ROUND('Loonschijven_Tranches salariale'!$Q14*0.65,4)*Basisbedragen!$I$2,2),ROUND(Basisbedragen!$D$34*Basisbedragen!$I$2,2)),ROUND(ROUND(Basisbedragen!$D$27*0.65,4)*Basisbedragen!$I$2,2))/2,2) -> 39.05 | D19: =ROUND(MIN(MAX(ROUND(ROUND('Loonschijven_Tranches salariale'!$Q14*0.6,4)*Basisbedragen!$I$2,2),ROUND(Basisbedragen!$D$34*Basisbedragen!$I$2,2)),ROUND(ROUND(Basisbedragen!$D$28*0.6,4)*Basisbedragen!$I$2,2))/2,2) -> 39.05 | E19: =ROUND(A_N_B_vol_plein!E19/2,2) -> 35.5 | F19: =ROUND(A_N_B_vol_plein!F19/2,2) -> 0 | G19: =ROUND(A_N_B_vol_plein!G19/2,2) -> 35.5 | H19: =ROUND(A_N_B_vol_plein!H19/2,2) -> 0 | I19: =ROUND(MIN(MAX(ROUND(ROUND('Loonschijven_Tranches salariale'!$Q14*0.65,4)*Basisbedragen!$I$2,2),ROUND(Basisbedragen!$D$36*Basisbedragen!$I$2,2)),ROUND(ROUND(Basisbedragen!$D$27*0.65,4)*Basisbedragen!$I$2,2))/2,2) -> 31.65 | J19: =ROUND(MIN(MAX(ROUND(ROUND('Loonschijven_Tranches salariale'!$Q14*0.6,4)*Basisbedragen!$I$2,2),ROUND(Basisbedragen!$D$36*Basisbedragen!$I$2,2)),ROUND(ROUND(Basisbedragen!$D$28*0.6,4)*Basisbedragen!$I$2,2))/2,2) -> 31.65 | K19: =ROUND(A_N_B_vol_plein!K19/2,2) -> 28.77 | L19: =ROUND(A_N_B_vol_plein!L19/2,2) -> 0 | M19: =ROUND(A_N_B_vol_plein!M19/2,2) -> 28.77 | N19: =ROUND(A_N_B_vol_plein!N19/2,2) -> 0 | O19: =ROUND(MIN(MAX(ROUND(ROUND('Loonschijven_Tranches salariale'!$Q14*0.65,4)*Basisbedragen!$I$2,2),ROUND(Basisbedragen!$D$38*Basisbedragen!$I$2,2)),ROUND(ROUND(Basisbedragen!$D$27*0.65,4)*Basisbedragen!$I$2,2))/2,2) -> 30.46 | P19: =ROUND(MIN(MAX(ROUND(ROUND('Loonschijven_Tranches salariale'!$Q14*0.6,4)*Basisbedragen!$I$2,2),ROUND(Basisbedragen!$D$39*Basisbedragen!$I$2,2)),ROUND(ROUND(Basisbedragen!$D$28*0.6,4)*Basisbedragen!$I$2,2))/2,2) -> 28.12 | Q19: =ROUND(A_N_B_vol_plein!Q19/2,2) -> 25.56 | R19: =ROUND(A_N_B_vol_plein!R19/2,2) -> 0 | S19: =ROUND(A_N_B_vol_plein!S19/2,2) -> 21.19 | T19: =ROUND(A_N_B_vol_plein!T19/2,2) -> 14.93
A20: =A19+1 -> 8 | C20: =ROUND(MIN(MAX(ROUND(ROUND('Loonschijven_Tranches salariale'!$Q15*0.65,4)*Basisbedragen!$I$2,2),ROUND(Basisbedragen!$D$34*Basisbedragen!$I$2,2)),ROUND(ROUND(Basisbedragen!$D$27*0.65,4)*Basisbedragen!$I$2,2))/2,2) -> 39.05 | D20: =ROUND(MIN(MAX(ROUND(ROUND('Loonschijven_Tranches salariale'!$Q15*0.6,4)*Basisbedragen!$I$2,2),ROUND(Basisbedragen!$D$34*Basisbedragen!$I$2,2)),ROUND(ROUND(Basisbedragen!$D$28*0.6,4)*Basisbedragen!$I$2,2))/2,2) -> 39.05 | E20: =ROUND(A_N_B_vol_plein!E20/2,2) -> 35.5 | F20: =ROUND(A_N_B_vol_plein!F20/2,2) -> 0 | G20: =ROUND(A_N_B_vol_plein!G20/2,2) -> 35.5 | H20: =ROUND(A_N_B_vol_plein!H20/2,2) -> 0 | I20: =ROUND(MIN(MAX(ROUND(ROUND('Loonschijven_Tranches salariale'!$Q15*0.65,4)*Basisbedragen!$I$2,2),ROUND(Basisbedragen!$D$36*Basisbedragen!$I$2,2)),ROUND(ROUND(Basisbedragen!$D$27*0.65,4)*Basisbedragen!$I$2,2))/2,2) -> 31.65 | J20: =ROUND(MIN(MAX(ROUND(ROUND('Loonschijven_Tranches salariale'!$Q15*0.6,4)*Basisbedragen!$I$2,2),ROUND(Basisbedragen!$D$36*Basisbedragen!$I$2,2)),ROUND(ROUND(Basisbedragen!$D$28*0.6,4)*Basisbedragen!$I$2,2))/2,2) -> 31.65 | K20: =ROUND(A_N_B_vol_plein!K20/2,2) -> 28.77 | L20: =ROUND(A_N_B_vol_plein!L20/2,2) -> 0 | M20: =ROUND(A_N_B_vol_plein!M20/2,2) -> 28.77 | N20: =ROUND(A_N_B_vol_plein!N20/2,2) -> 0 | O20: =ROUND(MIN(MAX(ROUND(ROUND('Loonschijven_Tranches salariale'!$Q15*0.65,4)*Basisbedragen!$I$2,2),ROUND(Basisbedragen!$D$38*Basisbedragen!$I$2,2)),ROUND(ROUND(Basisbedragen!$D$27*0.65,4)*Basisbedragen!$I$2,2))/2,2) -> 30.46 | P20: =ROUND(MIN(MAX(ROUND(ROUND('Loonschijven_Tranches salariale'!$Q15*0.6,4)*Basisbedragen!$I$2,2),ROUND(Basisbedragen!$D$39*Basisbedragen!$I$2,2)),ROUND(ROUND(Basisbedragen!$D$28*0.6,4)*Basisbedragen!$I$2,2))/2,2) -> 28.12 | Q20: =ROUND(A_N_B_vol_plein!Q20/2,2) -> 25.56 | R20: =ROUND(A_N_B_vol_plein!R20/2,2) -> 0 | S20: =ROUND(A_N_B_vol_plein!S20/2,2) -> 21.19 | T20: =ROUND(A_N_B_vol_plein!T20/2,2) -> 14.93
A21: =A20+1 -> 9 | C21: =ROUND(MIN(MAX(ROUND(ROUND('Loonschijven_Tranches salariale'!$Q16*0.65,4)*Basisbedragen!$I$2,2),ROUND(Basisbedragen!$D$34*Basisbedragen!$I$2,2)),ROUND(ROUND(Basisbedragen!$D$27*0.65,4)*Basisbedragen!$I$2,2))/2,2) -> 39.05 | D21: =ROUND(MIN(MAX(ROUND(ROUND('Loonschijven_Tranches salariale'!$Q16*0.6,4)*Basisbedragen!$I$2,2),ROUND(Basisbedragen!$D$34*Basisbedragen!$I$2,2)),ROUND(ROUND(Basisbedragen!$D$28*0.6,4)*Basisbedragen!$I$2,2))/2,2) -> 39.05 | E21: =ROUND(A_N_B_vol_plein!E21/2,2) -> 35.5 | F21: =ROUND(A_N_B_vol_plein!F21/2,2) -> 0 | G21: =ROUND(A_N_B_vol_plein!G21/2,2) -> 35.5 | H21: =ROUND(A_N_B_vol_plein!H21/2,2) -> 0 | I21: =ROUND(MIN(MAX(ROUND(ROUND('Loonschijven_Tranches salariale'!$Q16*0.65,4)*Basisbedragen!$I$2,2),ROUND(Basisbedragen!$D$36*Basisbedragen!$I$2,2)),ROUND(ROUND(Basisbedragen!$D$27*0.65,4)*Basisbedragen!$I$2,2))/2,2) -> 31.65 | J21: =ROUND(MIN(MAX(ROUND(ROUND('Loonschijven_Tranches salariale'!$Q16*0.6,4)*Basisbedragen!$I$2,2),ROUND(Basisbedragen!$D$36*Basisbedragen!$I$2,2)),ROUND(ROUND(Basisbedragen!$D$28*0.6,4)*Basisbedragen!$I$2,2))/2,2) -> 31.65 | K21: =ROUND(A_N_B_vol_plein!K21/2,2) -> 28.77 | L21: =ROUND(A_N_B_vol_plein!L21/2,2) -> 0 | M21: =ROUND(A_N_B_vol_plein!M21/2,2) -> 28.77 | N21: =ROUND(A_N_B_vol_plein!N21/2,2) -> 0 | O21: =ROUND(MIN(MAX(ROUND(ROUND('Loonschijven_Tranches salariale'!$Q16*0.65,4)*Basisbedragen!$I$2,2),ROUND(Basisbedragen!$D$38*Basisbedragen!$I$2,2)),ROUND(ROUND(Basisbedragen!$D$27*0.65,4)*Basisbedragen!$I$2,2))/2,2) -> 30.46 | P21: =ROUND(MIN(MAX(ROUND(ROUND('Loonschijven_Tranches salariale'!$Q16*0.6,4)*Basisbedragen!$I$2,2),ROUND(Basisbedragen!$D$39*Basisbedragen!$I$2,2)),ROUND(ROUND(Basisbedragen!$D$28*0.6,4)*Basisbedragen!$I$2,2))/2,2) -> 28.12 | Q21: =ROUND(A_N_B_vol_plein!Q21/2,2) -> 25.56 | R21: =ROUND(A_N_B_vol_plein!R21/2,2) -> 0 | S21: =ROUND(A_N_B_vol_plein!S21/2,2) -> 21.19 | T21: =ROUND(A_N_B_vol_plein!T21/2,2) -> 14.93
A22: =A21+1 -> 10 | C22: =ROUND(MIN(MAX(ROUND(ROUND('Loonschijven_Tranches salariale'!$Q17*0.65,4)*Basisbedragen!$I$2,2),ROUND(Basisbedragen!$D$34*Basisbedragen!$I$2,2)),ROUND(ROUND(Basisbedragen!$D$27*0.65,4)*Basisbedragen!$I$2,2))/2,2) -> 39.05 | D22: =ROUND(MIN(MAX(ROUND(ROUND('Loonschijven_Tranches salariale'!$Q17*0.6,4)*Basisbedragen!$I$2,2),ROUND(Basisbedragen!$D$34*Basisbedragen!$I$2,2)),ROUND(ROUND(Basisbedragen!$D$28*0.6,4)*Basisbedragen!$I$2,2))/2,2) -> 39.05 | E22: =ROUND(A_N_B_vol_plein!E22/2,2) -> 35.5 | F22: =ROUND(A_N_B_vol_plein!F22/2,2) -> 0 | G22: =ROUND(A_N_B_vol_plein!G22/2,2) -> 35.5 | H22: =ROUND(A_N_B_vol_plein!H22/2,2) -> 0 | I22: =ROUND(MIN(MAX(ROUND(ROUND('Loonschijven_Tranches salariale'!$Q17*0.65,4)*Basisbedragen!$I$2,2),ROUND(Basisbedragen!$D$36*Basisbedragen!$I$2,2)),ROUND(ROUND(Basisbedragen!$D$27*0.65,4)*Basisbedragen!$I$2,2))/2,2) -> 31.65 | J22: =ROUND(MIN(MAX(ROUND(ROUND('Loonschijven_Tranches salariale'!$Q17*0.6,4)*Basisbedragen!$I$2,2),ROUND(Basisbedragen!$D$36*Basisbedragen!$I$2,2)),ROUND(ROUND(Basisbedragen!$D$28*0.6,4)*Basisbedragen!$I$2,2))/2,2) -> 31.65 | K22: =ROUND(A_N_B_vol_plein!K22/2,2) -> 28.77 | L22: =ROUND(A_N_B_vol_plein!L22/2,2) -> 0 | M22: =ROUND(A_N_B_vol_plein!M22/2,2) -> 28.77 | N22: =ROUND(A_N_B_vol_plein!N22/2,2) -> 0 | O22: =ROUND(MIN(MAX(ROUND(ROUND('Loonschijven_Tranches salariale'!$Q17*0.65,4)*Basisbedragen!$I$2,2),ROUND(Basisbedragen!$D$38*Basisbedragen!$I$2,2)),ROUND(ROUND(Basisbedragen!$D$27*0.65,4)*Basisbedragen!$I$2,2))/2,2) -> 30.46 | P22: =ROUND(MIN(MAX(ROUND(ROUND('Loonschijven_Tranches salariale'!$Q17*0.6,4)*Basisbedragen!$I$2,2),ROUND(Basisbedragen!$D$39*Basisbedragen!$I$2,2)),ROUND(ROUND(Basisbedragen!$D$28*0.6,4)*Basisbedragen!$I$2,2))/2,2) -> 28.12 | Q22: =ROUND(A_N_B_vol_plein!Q22/2,2) -> 25.56 | R22: =ROUND(A_N_B_vol_plein!R22/2,2) -> 0 | S22: =ROUND(A_N_B_vol_plein!S22/2,2) -> 21.19 | T22: =ROUND(A_N_B_vol_plein!T22/2,2) -> 14.93
A23: =A22+1 -> 11 | C23: =ROUND(MIN(MAX(ROUND(ROUND('Loonschijven_Tranches salariale'!$Q18*0.65,4)*Basisbedragen!$I$2,2),ROUND(Basisbedragen!$D$34*Basisbedragen!$I$2,2)),ROUND(ROUND(Basisbedragen!$D$27*0.65,4)*Basisbedragen!$I$2,2))/2,2) -> 39.05 | D23: =ROUND(MIN(MAX(ROUND(ROUND('Loonschijven_Tranches salariale'!$Q18*0.6,4)*Basisbedragen!$I$2,2),ROUND(Basisbedragen!$D$34*Basisbedragen!$I$2,2)),ROUND(ROUND(Basisbedragen!$D$28*0.6,4)*Basisbedragen!$I$2,2))/2,2) -> 39.05 | E23: =ROUND(A_N_B_vol_plein!E23/2,2) -> 35.5 | F23: =ROUND(A_N_B_vol_plein!F23/2,2) -> 0 | G23: =ROUND(A_N_B_vol_plein!G23/2,2) -> 35.5 | H23: =ROUND(A_N_B_vol_plein!H23/2,2) -> 0 | I23: =ROUND(MIN(MAX(ROUND(ROUND('Loonschijven_Tranches salariale'!$Q18*0.65,4)*Basisbedragen!$I$2,2),ROUND(Basisbedragen!$D$36*Basisbedragen!$I$2,2)),ROUND(ROUND(Basisbedragen!$D$27*0.65,4)*Basisbedragen!$I$2,2))/2,2) -> 31.65 | J23: =ROUND(MIN(MAX(ROUND(ROUND('Loonschijven_Tranches salariale'!$Q18*0.6,4)*Basisbedragen!$I$2,2),ROUND(Basisbedragen!$D$36*Basisbedragen!$I$2,2)),ROUND(ROUND(Basisbedragen!$D$28*0.6,4)*Basisbedragen!$I$2,2))/2,2) -> 31.65 | K23: =ROUND(A_N_B_vol_plein!K23/2,2) -> 28.77 | L23: =ROUND(A_N_B_vol_plein!L23/2,2) -> 0 | M23: =ROUND(A_N_B_vol_plein!M23/2,2) -> 28.77 | N23: =ROUND(A_N_B_vol_plein!N23/2,2) -> 0 | O23: =ROUND(MIN(MAX(ROUND(ROUND('Loonschijven_Tranches salariale'!$Q18*0.65,4)*Basisbedragen!$I$2,2),ROUND(Basisbedragen!$D$38*Basisbedragen!$I$2,2)),ROUND(ROUND(Basisbedragen!$D$27*0.65,4)*Basisbedragen!$I$2,2))/2,2) -> 30.46 | P23: =ROUND(MIN(MAX(ROUND(ROUND('Loonschijven_Tranches salariale'!$Q18*0.6,4)*Basisbedragen!$I$2,2),ROUND(Basisbedragen!$D$39*Basisbedragen!$I$2,2)),ROUND(ROUND(Basisbedragen!$D$28*0.6,4)*Basisbedragen!$I$2,2))/2,2) -> 28.12 | Q23: =ROUND(A_N_B_vol_plein!Q23/2,2) -> 25.56 | R23: =ROUND(A_N_B_vol_plein!R23/2,2) -> 0 | S23: =ROUND(A_N_B_vol_plein!S23/2,2) -> 21.19 | T23: =ROUND(A_N_B_vol_plein!T23/2,2) -> 14.93
A24: =A23+1 -> 12 | C24: =ROUND(MIN(MAX(ROUND(ROUND('Loonschijven_Tranches salariale'!$Q19*0.65,4)*Basisbedragen!$I$2,2),ROUND(Basisbedragen!$D$34*Basisbedragen!$I$2,2)),ROUND(ROUND(Basisbedragen!$D$27*0.65,4)*Basisbedragen!$I$2,2))/2,2) -> 39.05 | D24: =ROUND(MIN(MAX(ROUND(ROUND('Loonschijven_Tranches salariale'!$Q19*0.6,4)*Basisbedragen!$I$2,2),ROUND(Basisbedragen!$D$34*Basisbedragen!$I$2,2)),ROUND(ROUND(Basisbedragen!$D$28*0.6,4)*Basisbedragen!$I$2,2))/2,2) -> 39.05 | E24: =ROUND(A_N_B_vol_plein!E24/2,2) -> 35.5 | F24: =ROUND(A_N_B_vol_plein!F24/2,2) -> 0 | G24: =ROUND(A_N_B_vol_plein!G24/2,2) -> 35.5 | H24: =ROUND(A_N_B_vol_plein!H24/2,2) -> 0 | I24: =ROUND(MIN(MAX(ROUND(ROUND('Loonschijven_Tranches salariale'!$Q19*0.65,4)*Basisbedragen!$I$2,2),ROUND(Basisbedragen!$D$36*Basisbedragen!$I$2,2)),ROUND(ROUND(Basisbedragen!$D$27*0.65,4)*Basisbedragen!$I$2,2))/2,2) -> 31.65 | J24: =ROUND(MIN(MAX(ROUND(ROUND('Loonschijven_Tranches salariale'!$Q19*0.6,4)*Basisbedragen!$I$2,2),ROUND(Basisbedragen!$D$36*Basisbedragen!$I$2,2)),ROUND(ROUND(Basisbedragen!$D$28*0.6,4)*Basisbedragen!$I$2,2))/2,2) -> 31.65 | K24: =ROUND(A_N_B_vol_plein!K24/2,2) -> 28.77 | L24: =ROUND(A_N_B_vol_plein!L24/2,2) -> 0 | M24: =ROUND(A_N_B_vol_plein!M24/2,2) -> 28.77 | N24: =ROUND(A_N_B_vol_plein!N24/2,2) -> 0 | O24: =ROUND(MIN(MAX(ROUND(ROUND('Loonschijven_Tranches salariale'!$Q19*0.65,4)*Basisbedragen!$I$2,2),ROUND(Basisbedragen!$D$38*Basisbedragen!$I$2,2)),ROUND(ROUND(Basisbedragen!$D$27*0.65,4)*Basisbedragen!$I$2,2))/2,2) -> 30.46 | P24: =ROUND(MIN(MAX(ROUND(ROUND('Loonschijven_Tranches salariale'!$Q19*0.6,4)*Basisbedragen!$I$2,2),ROUND(Basisbedragen!$D$39*Basisbedragen!$I$2,2)),ROUND(ROUND(Basisbedragen!$D$28*0.6,4)*Basisbedragen!$I$2,2))/2,2) -> 28.12 | Q24: =ROUND(A_N_B_vol_plein!Q24/2,2) -> 25.56 | R24: =ROUND(A_N_B_vol_plein!R24/2,2) -> 0 | S24: =ROUND(A_N_B_vol_plein!S24/2,2) -> 21.19 | T24: =ROUND(A_N_B_vol_plein!T24/2,2) -> 14.93
A25: =A24+1 -> 13 | C25: =ROUND(MIN(MAX(ROUND(ROUND('Loonschijven_Tranches salariale'!$Q20*0.65,4)*Basisbedragen!$I$2,2),ROUND(Basisbedragen!$D$34*Basisbedragen!$I$2,2)),ROUND(ROUND(Basisbedragen!$D$27*0.65,4)*Basisbedragen!$I$2,2))/2,2) -> 39.05 | D25: =ROUND(MIN(MAX(ROUND(ROUND('Loonschijven_Tranches salariale'!$Q20*0.6,4)*Basisbedragen!$I$2,2),ROUND(Basisbedragen!$D$34*Basisbedragen!$I$2,2)),ROUND(ROUND(Basisbedragen!$D$28*0.6,4)*Basisbedragen!$I$2,2))/2,2) -> 39.05 | E25: =ROUND(A_N_B_vol_plein!E25/2,2) -> 35.5 | F25: =ROUND(A_N_B_vol_plein!F25/2,2) -> 0 | G25: =ROUND(A_N_B_vol_plein!G25/2,2) -> 35.5 | H25: =ROUND(A_N_B_vol_plein!H25/2,2) -> 0 | I25: =ROUND(MIN(MAX(ROUND(ROUND('Loonschijven_Tranches salariale'!$Q20*0.65,4)*Basisbedragen!$I$2,2),ROUND(Basisbedragen!$D$36*Basisbedragen!$I$2,2)),ROUND(ROUND(Basisbedragen!$D$27*0.65,4)*Basisbedragen!$I$2,2))/2,2) -> 31.65 | J25: =ROUND(MIN(MAX(ROUND(ROUND('Loonschijven_Tranches salariale'!$Q20*0.6,4)*Basisbedragen!$I$2,2),ROUND(Basisbedragen!$D$36*Basisbedragen!$I$2,2)),ROUND(ROUND(Basisbedragen!$D$28*0.6,4)*Basisbedragen!$I$2,2))/2,2) -> 31.65 | K25: =ROUND(A_N_B_vol_plein!K25/2,2) -> 28.77 | L25: =ROUND(A_N_B_vol_plein!L25/2,2) -> 0 | M25: =ROUND(A_N_B_vol_plein!M25/2,2) -> 28.77 | N25: =ROUND(A_N_B_vol_plein!N25/2,2) -> 0 | O25: =ROUND(MIN(MAX(ROUND(ROUND('Loonschijven_Tranches salariale'!$Q20*0.65,4)*Basisbedragen!$I$2,2),ROUND(Basisbedragen!$D$38*Basisbedragen!$I$2,2)),ROUND(ROUND(Basisbedragen!$D$27*0.65,4)*Basisbedragen!$I$2,2))/2,2) -> 30.46 | P25: =ROUND(MIN(MAX(ROUND(ROUND('Loonschijven_Tranches salariale'!$Q20*0.6,4)*Basisbedragen!$I$2,2),ROUND(Basisbedragen!$D$39*Basisbedragen!$I$2,2)),ROUND(ROUND(Basisbedragen!$D$28*0.6,4)*Basisbedragen!$I$2,2))/2,2) -> 28.12 | Q25: =ROUND(A_N_B_vol_plein!Q25/2,2) -> 25.56 | R25: =ROUND(A_N_B_vol_plein!R25/2,2) -> 0 | S25: =ROUND(A_N_B_vol_plein!S25/2,2) -> 21.19 | T25: =ROUND(A_N_B_vol_plein!T25/2,2) -> 14.93
... A111: =A110+1 -> 99 | C111: =ROUND(MIN(MAX(ROUND(ROUND('Loonschijven_Tranches salariale'!$Q106*0.65,4)*Basisbedragen!$I$2,2),ROUND(Basisbedragen!$D$34*Basisbedragen!$I$2,2)),ROUND(ROUND(Basisbedragen!$D$27*0.65,4)*Basisbedragen!$I$2,2))/2,2) -> 54.4 | D111: =ROUND(MIN(MAX(ROUND(ROUND('Loonschijven_Tranches salariale'!$Q106*0.6,4)*Basisbedragen!$I$2,2),ROUND(Basisbedragen!$D$34*Basisbedragen!$I$2,2)),ROUND(ROUND(Basisbedragen!$D$28*0.6,4)*Basisbedragen!$I$2,2))/2,2) -> 47.21 | E111: =ROUND(A_N_B_vol_plein!E111/2,2) -> 38.41 | F111: =ROUND(A_N_B_vol_plein!F111/2,2) -> 0 | G111: =ROUND(A_N_B_vol_plein!G111/2,2) -> 35.5 | H111: =ROUND(A_N_B_vol_plein!H111/2,2) -> 0 | I111: =ROUND(MIN(MAX(ROUND(ROUND('Loonschijven_Tranches salariale'!$Q106*0.65,4)*Basisbedragen!$I$2,2),ROUND(Basisbedragen!$D$36*Basisbedragen!$I$2,2)),ROUND(ROUND(Basisbedragen!$D$27*0.65,4)*Basisbedragen!$I$2,2))/2,2) -> 54.4 | J111: =ROUND(MIN(MAX(ROUND(ROUND('Loonschijven_Tranches salariale'!$Q106*0.6,4)*Basisbedragen!$I$2,2),ROUND(Basisbedragen!$D$36*Basisbedragen!$I$2,2)),ROUND(ROUND(Basisbedragen!$D$28*0.6,4)*Basisbedragen!$I$2,2))/2,2) -> 47.21 | K111: =ROUND(A_N_B_vol_plein!K111/2,2) -> 38.41 | L111: =ROUND(A_N_B_vol_plein!L111/2,2) -> 0 | M111: =ROUND(A_N_B_vol_plein!M111/2,2) -> 28.77 | N111: =ROUND(A_N_B_vol_plein!N111/2,2) -> 0 | O111: =ROUND(MIN(MAX(ROUND(ROUND('Loonschijven_Tranches salariale'!$Q106*0.65,4)*Basisbedragen!$I$2,2),ROUND(Basisbedragen!$D$38*Basisbedragen!$I$2,2)),ROUND(ROUND(Basisbedragen!$D$27*0.65,4)*Basisbedragen!$I$2,2))/2,2) -> 54.4 | P111: =ROUND(MIN(MAX(ROUND(ROUND('Loonschijven_Tranches salariale'!$Q106*0.6,4)*Basisbedragen!$I$2,2),ROUND(Basisbedragen!$D$39*Basisbedragen!$I$2,2)),ROUND(ROUND(Basisbedragen!$D$28*0.6,4)*Basisbedragen!$I$2,2))/2,2) -> 47.21 | Q111: =ROUND(A_N_B_vol_plein!Q111/2,2) -> 38.41 | R111: =ROUND(A_N_B_vol_plein!R111/2,2) -> 0 | S111: =ROUND(A_N_B_vol_plein!S111/2,2) -> 21.19 | T111: =ROUND(A_N_B_vol_plein!T111/2,2) -> 14.93

Sheet TW-CT_JS
A1: Geldig/valable | B1: Tijdelijke werkloosheidsuitkeringen - dagbedrag van de uitkering | U1: Multiplicat(o)(eu)r | X1: =Basisbedragen!$I$2 -> 1.8114
A2: 46266 | B2: Allocations de chômage temporaire - montant journalier de l'allocation
B4: Volle uitkering Allocation entière | L4: Halve uitkering Demi allocation
A5: Code | B5: A0 N0 B0 | D5: A0 N0 B0 | F5: A0H | H5: A0H | J5: J/S | L5: A0 N0 B0 | N5: A0 N0 B0 | P5: A0H | R5: A0H | T5: J/S
B6: 0.65 | D6: 0.6 | F6: 0.65 | H6: 0.6 | J6: 0.65 | L6: 0.65 | N6: 0.6 | P6: 0.65 | R6: 0.6 | T6: 0.65
A7: MIN | B7: =ROUND(Basisbedragen!$D$48*$X$1,2) -> 70.14 | C7: =ROUND(Basisbedragen!$D$48*$X$1,2) -> 70.14 | D7: =ROUND(Basisbedragen!$D$49*$X$1,2) -> 64.74 | F7: =ROUND(B7*1.2,2) -> 84.17 | H7: =ROUND(D7*1.2,2) -> 77.69 | J7: =ROUND(Basisbedragen!$D$73*$X$1,2) -> 56.48 | L7: =ROUND(B7/2,2) -> 35.07 | M7: =ROUND(C7/2,2) -> 35.07 | N7: =ROUND(D7/2,2) -> 32.37 | P7: =ROUND(L8*1.2,2) -> 42.08 | R7: =ROUND(N8*1.2,2) -> 38.84 | T7: =ROUND(J7/2,2) -> 28.24
A8: 1 | B8: =IF(MIN(MAX(ROUND(ROUND('Loonschijven_Tranches salariale'!$Q8*0.65,4)*Basisbedragen!$I$7,2),ROUND(Basisbedragen!$D$48*Basisbedragen!$I$7,2)),ROUND(ROUND(Basisbedragen!$D$30*0.65,4)*Basisbedragen!$I$7,2))<= Basisbedragen!$I$8,MIN(MAX(ROUND(ROUND('Loonschijven_Tranches salariale'!$Q8*0.65,4)*Basisbedragen!$I$2,2),ROUND(Basisbedragen!$D$48*Basisbedragen!$I$2,2)),ROUND(ROUND(Basisbedragen!$D$30*0.65,4)*Basisbedragen!$I$2,2)),MIN(MAX(ROUND(ROUND('Loonschijven_Tranches salariale'!$Q8*0.65,4)*Basisbedragen!$I$7,2),ROUND(Basisbedragen!$D$48*Basisbedragen!$I$7,2)),ROUND(ROUND(Basisbedragen!$D$30*0.65,4)*Basisbedragen!$I$7,2))+Basisbedragen!$I$10) -> 70.14 | D8: =IF(MIN(MAX(ROUND(ROUND('Loonschijven_Tranches salariale'!$Q8*0.6,4)*Basisbedragen!$I$7,2),ROUND(Basisbedragen!$D$49*Basisbedragen!$I$7,2)),ROUND(ROUND(Basisbedragen!$D$30*0.6,4)*Basisbedragen!$I$7,2))<= Basisbedragen!$I$8,MIN(MAX(ROUND(ROUND('Loonschijven_Tranches salariale'!$Q8*0.6,4)*Basisbedragen!$I$2,2),ROUND(Basisbedragen!$D$49*Basisbedragen!$I$2,2)),ROUND(ROUND(Basisbedragen!$D$30*0.6,4)*Basisbedragen!$I$2,2)),MIN(MAX(ROUND(ROUND('Loonschijven_Tranches salariale'!$Q8*0.6,4)*Basisbedragen!$I$7,2),ROUND(Basisbedragen!$D$49*Basisbedragen!$I$7,2)),ROUND(ROUND(Basisbedragen!$D$30*0.6,4)*Basisbedragen!$I$7,2))+Basisbedragen!$I$10) -> 64.74 | F8: =ROUND(B8*1.2,2) -> 84.17 | H8: =ROUND(D8*1.2,2) -> 77.69 | J8: =MIN(MAX(ROUND(ROUND('Loonschijven_Tranches salariale'!$Q8*0.65,4)*Basisbedragen!$I$2,2),ROUND(Basisbedragen!$D$73*Basisbedragen!$I$2,2)),ROUND(ROUND(Basisbedragen!$D$31*0.65,4)*Basisbedragen!$I$2,2)) -> 56.48 | L8: =ROUND(MIN(MAX(ROUND(ROUND('Loonschijven_Tranches salariale'!$Q8*0.65,4)*Basisbedragen!$I$2,2),ROUND(Basisbedragen!$D$48*Basisbedragen!$I$2,2)),ROUND(ROUND(Basisbedragen!$D$30*0.65,4)*Basisbedragen!$I$2,2))/2,2) -> 35.07 | M8: =ROUND(C8/2,2) -> 0 | N8: =ROUND(MIN(MAX(ROUND(ROUND('Loonschijven_Tranches salariale'!$Q8*0.6,4)*Basisbedragen!$I$2,2),ROUND(Basisbedragen!$D$49*Basisbedragen!$I$2,2)),ROUND(ROUND(Basisbedragen!$D$30*0.6,4)*Basisbedragen!$I$2,2))/2,2) -> 32.37 | P8: =ROUND(L8*1.2,2) -> 42.08 | R8: =ROUND(N8*1.2,2) -> 38.84 | T8: =ROUND(J8/2,2) -> 28.24
A9: =A8+1 -> 2 | B9: =IF(MIN(MAX(ROUND(ROUND('Loonschijven_Tranches salariale'!$Q9*0.65,4)*Basisbedragen!$I$7,2),ROUND(Basisbedragen!$D$48*Basisbedragen!$I$7,2)),ROUND(ROUND(Basisbedragen!$D$30*0.65,4)*Basisbedragen!$I$7,2))<= Basisbedragen!$I$8,MIN(MAX(ROUND(ROUND('Loonschijven_Tranches salariale'!$Q9*0.65,4)*Basisbedragen!$I$2,2),ROUND(Basisbedragen!$D$48*Basisbedragen!$I$2,2)),ROUND(ROUND(Basisbedragen!$D$30*0.65,4)*Basisbedragen!$I$2,2)),MIN(MAX(ROUND(ROUND('Loonschijven_Tranches salariale'!$Q9*0.65,4)*Basisbedragen!$I$7,2),ROUND(Basisbedragen!$D$48*Basisbedragen!$I$7,2)),ROUND(ROUND(Basisbedragen!$D$30*0.65,4)*Basisbedragen!$I$7,2))+Basisbedragen!$I$10) -> 70.14 | D9: =IF(MIN(MAX(ROUND(ROUND('Loonschijven_Tranches salariale'!$Q9*0.6,4)*Basisbedragen!$I$7,2),ROUND(Basisbedragen!$D$49*Basisbedragen!$I$7,2)),ROUND(ROUND(Basisbedragen!$D$30*0.6,4)*Basisbedragen!$I$7,2))<= Basisbedragen!$I$8,MIN(MAX(ROUND(ROUND('Loonschijven_Tranches salariale'!$Q9*0.6,4)*Basisbedragen!$I$2,2),ROUND(Basisbedragen!$D$49*Basisbedragen!$I$2,2)),ROUND(ROUND(Basisbedragen!$D$30*0.6,4)*Basisbedragen!$I$2,2)),MIN(MAX(ROUND(ROUND('Loonschijven_Tranches salariale'!$Q9*0.6,4)*Basisbedragen!$I$7,2),ROUND(Basisbedragen!$D$49*Basisbedragen!$I$7,2)),ROUND(ROUND(Basisbedragen!$D$30*0.6,4)*Basisbedragen!$I$7,2))+Basisbedragen!$I$10) -> 64.74 | F9: =ROUND(B9*1.2,2) -> 84.17 | H9: =ROUND(D9*1.2,2) -> 77.69 | J9: =MIN(MAX(ROUND(ROUND('Loonschijven_Tranches salariale'!$Q9*0.65,4)*Basisbedragen!$I$2,2),ROUND(Basisbedragen!$D$73*Basisbedragen!$I$2,2)),ROUND(ROUND(Basisbedragen!$D$31*0.65,4)*Basisbedragen!$I$2,2)) -> 56.48 | L9: =ROUND(MIN(MAX(ROUND(ROUND('Loonschijven_Tranches salariale'!$Q9*0.65,4)*Basisbedragen!$I$2,2),ROUND(Basisbedragen!$D$48*Basisbedragen!$I$2,2)),ROUND(ROUND(Basisbedragen!$D$30*0.65,4)*Basisbedragen!$I$2,2))/2,2) -> 35.07 | N9: =ROUND(MIN(MAX(ROUND(ROUND('Loonschijven_Tranches salariale'!$Q9*0.6,4)*Basisbedragen!$I$2,2),ROUND(Basisbedragen!$D$49*Basisbedragen!$I$2,2)),ROUND(ROUND(Basisbedragen!$D$30*0.6,4)*Basisbedragen!$I$2,2))/2,2) -> 32.37 | P9: =ROUND(L9*1.2,2) -> 42.08 | R9: =ROUND(N9*1.2,2) -> 38.84 | T9: =ROUND(J9/2,2) -> 28.24
A10: =A9+1 -> 3 | B10: =IF(MIN(MAX(ROUND(ROUND('Loonschijven_Tranches salariale'!$Q10*0.65,4)*Basisbedragen!$I$7,2),ROUND(Basisbedragen!$D$48*Basisbedragen!$I$7,2)),ROUND(ROUND(Basisbedragen!$D$30*0.65,4)*Basisbedragen!$I$7,2))<= Basisbedragen!$I$8,MIN(MAX(ROUND(ROUND('Loonschijven_Tranches salariale'!$Q10*0.65,4)*Basisbedragen!$I$2,2),ROUND(Basisbedragen!$D$48*Basisbedragen!$I$2,2)),ROUND(ROUND(Basisbedragen!$D$30*0.65,4)*Basisbedragen!$I$2,2)),MIN(MAX(ROUND(ROUND('Loonschijven_Tranches salariale'!$Q10*0.65,4)*Basisbedragen!$I$7,2),ROUND(Basisbedragen!$D$48*Basisbedragen!$I$7,2)),ROUND(ROUND(Basisbedragen!$D$30*0.65,4)*Basisbedragen!$I$7,2))+Basisbedragen!$I$10) -> 70.14 | D10: =IF(MIN(MAX(ROUND(ROUND('Loonschijven_Tranches salariale'!$Q10*0.6,4)*Basisbedragen!$I$7,2),ROUND(Basisbedragen!$D$49*Basisbedragen!$I$7,2)),ROUND(ROUND(Basisbedragen!$D$30*0.6,4)*Basisbedragen!$I$7,2))<= Basisbedragen!$I$8,MIN(MAX(ROUND(ROUND('Loonschijven_Tranches salariale'!$Q10*0.6,4)*Basisbedragen!$I$2,2),ROUND(Basisbedragen!$D$49*Basisbedragen!$I$2,2)),ROUND(ROUND(Basisbedragen!$D$30*0.6,4)*Basisbedragen!$I$2,2)),MIN(MAX(ROUND(ROUND('Loonschijven_Tranches salariale'!$Q10*0.6,4)*Basisbedragen!$I$7,2),ROUND(Basisbedragen!$D$49*Basisbedragen!$I$7,2)),ROUND(ROUND(Basisbedragen!$D$30*0.6,4)*Basisbedragen!$I$7,2))+Basisbedragen!$I$10) -> 64.74 | F10: =ROUND(B10*1.2,2) -> 84.17 | H10: =ROUND(D10*1.2,2) -> 77.69 | J10: =MIN(MAX(ROUND(ROUND('Loonschijven_Tranches salariale'!$Q10*0.65,4)*Basisbedragen!$I$2,2),ROUND(Basisbedragen!$D$73*Basisbedragen!$I$2,2)),ROUND(ROUND(Basisbedragen!$D$31*0.65,4)*Basisbedragen!$I$2,2)) -> 56.48 | L10: =ROUND(MIN(MAX(ROUND(ROUND('Loonschijven_Tranches salariale'!$Q10*0.65,4)*Basisbedragen!$I$2,2),ROUND(Basisbedragen!$D$48*Basisbedragen!$I$2,2)),ROUND(ROUND(Basisbedragen!$D$30*0.65,4)*Basisbedragen!$I$2,2))/2,2) -> 35.07 | N10: =ROUND(MIN(MAX(ROUND(ROUND('Loonschijven_Tranches salariale'!$Q10*0.6,4)*Basisbedragen!$I$2,2),ROUND(Basisbedragen!$D$49*Basisbedragen!$I$2,2)),ROUND(ROUND(Basisbedragen!$D$30*0.6,4)*Basisbedragen!$I$2,2))/2,2) -> 32.37 | P10: =ROUND(L10*1.2,2) -> 42.08 | R10: =ROUND(N10*1.2,2) -> 38.84 | T10: =ROUND(J10/2,2) -> 28.24
A11: =A10+1 -> 4 | B11: =IF(MIN(MAX(ROUND(ROUND('Loonschijven_Tranches salariale'!$Q11*0.65,4)*Basisbedragen!$I$7,2),ROUND(Basisbedragen!$D$48*Basisbedragen!$I$7,2)),ROUND(ROUND(Basisbedragen!$D$30*0.65,4)*Basisbedragen!$I$7,2))<= Basisbedragen!$I$8,MIN(MAX(ROUND(ROUND('Loonschijven_Tranches salariale'!$Q11*0.65,4)*Basisbedragen!$I$2,2),ROUND(Basisbedragen!$D$48*Basisbedragen!$I$2,2)),ROUND(ROUND(Basisbedragen!$D$30*0.65,4)*Basisbedragen!$I$2,2)),MIN(MAX(ROUND(ROUND('Loonschijven_Tranches salariale'!$Q11*0.65,4)*Basisbedragen!$I$7,2),ROUND(Basisbedragen!$D$48*Basisbedragen!$I$7,2)),ROUND(ROUND(Basisbedragen!$D$30*0.65,4)*Basisbedragen!$I$7,2))+Basisbedragen!$I$10) -> 70.14 | D11: =IF(MIN(MAX(ROUND(ROUND('Loonschijven_Tranches salariale'!$Q11*0.6,4)*Basisbedragen!$I$7,2),ROUND(Basisbedragen!$D$49*Basisbedragen!$I$7,2)),ROUND(ROUND(Basisbedragen!$D$30*0.6,4)*Basisbedragen!$I$7,2))<= Basisbedragen!$I$8,MIN(MAX(ROUND(ROUND('Loonschijven_Tranches salariale'!$Q11*0.6,4)*Basisbedragen!$I$2,2),ROUND(Basisbedragen!$D$49*Basisbedragen!$I$2,2)),ROUND(ROUND(Basisbedragen!$D$30*0.6,4)*Basisbedragen!$I$2,2)),MIN(MAX(ROUND(ROUND('Loonschijven_Tranches salariale'!$Q11*0.6,4)*Basisbedragen!$I$7,2),ROUND(Basisbedragen!$D$49*Basisbedragen!$I$7,2)),ROUND(ROUND(Basisbedragen!$D$30*0.6,4)*Basisbedragen!$I$7,2))+Basisbedragen!$I$10) -> 64.74 | F11: =ROUND(B11*1.2,2) -> 84.17 | H11: =ROUND(D11*1.2,2) -> 77.69 | J11: =MIN(MAX(ROUND(ROUND('Loonschijven_Tranches salariale'!$Q11*0.65,4)*Basisbedragen!$I$2,2),ROUND(Basisbedragen!$D$73*Basisbedragen!$I$2,2)),ROUND(ROUND(Basisbedragen!$D$31*0.65,4)*Basisbedragen!$I$2,2)) -> 56.48 | L11: =ROUND(MIN(MAX(ROUND(ROUND('Loonschijven_Tranches salariale'!$Q11*0.65,4)*Basisbedragen!$I$2,2),ROUND(Basisbedragen!$D$48*Basisbedragen!$I$2,2)),ROUND(ROUND(Basisbedragen!$D$30*0.65,4)*Basisbedragen!$I$2,2))/2,2) -> 35.07 | N11: =ROUND(MIN(MAX(ROUND(ROUND('Loonschijven_Tranches salariale'!$Q11*0.6,4)*Basisbedragen!$I$2,2),ROUND(Basisbedragen!$D$49*Basisbedragen!$I$2,2)),ROUND(ROUND(Basisbedragen!$D$30*0.6,4)*Basisbedragen!$I$2,2))/2,2) -> 32.37 | P11: =ROUND(L11*1.2,2) -> 42.08 | R11: =ROUND(N11*1.2,2) -> 38.84 | T11: =ROUND(J11/2,2) -> 28.24
A12: =A11+1 -> 5 | B12: =IF(MIN(MAX(ROUND(ROUND('Loonschijven_Tranches salariale'!$Q12*0.65,4)*Basisbedragen!$I$7,2),ROUND(Basisbedragen!$D$48*Basisbedragen!$I$7,2)),ROUND(ROUND(Basisbedragen!$D$30*0.65,4)*Basisbedragen!$I$7,2))<= Basisbedragen!$I$8,MIN(MAX(ROUND(ROUND('Loonschijven_Tranches salariale'!$Q12*0.65,4)*Basisbedragen!$I$2,2),ROUND(Basisbedragen!$D$48*Basisbedragen!$I$2,2)),ROUND(ROUND(Basisbedragen!$D$30*0.65,4)*Basisbedragen!$I$2,2)),MIN(MAX(ROUND(ROUND('Loonschijven_Tranches salariale'!$Q12*0.65,4)*Basisbedragen!$I$7,2),ROUND(Basisbedragen!$D$48*Basisbedragen!$I$7,2)),ROUND(ROUND(Basisbedragen!$D$30*0.65,4)*Basisbedragen!$I$7,2))+Basisbedragen!$I$10) -> 70.14 | D12: =IF(MIN(MAX(ROUND(ROUND('Loonschijven_Tranches salariale'!$Q12*0.6,4)*Basisbedragen!$I$7,2),ROUND(Basisbedragen!$D$49*Basisbedragen!$I$7,2)),ROUND(ROUND(Basisbedragen!$D$30*0.6,4)*Basisbedragen!$I$7,2))<= Basisbedragen!$I$8,MIN(MAX(ROUND(ROUND('Loonschijven_Tranches salariale'!$Q12*0.6,4)*Basisbedragen!$I$2,2),ROUND(Basisbedragen!$D$49*Basisbedragen!$I$2,2)),ROUND(ROUND(Basisbedragen!$D$30*0.6,4)*Basisbedragen!$I$2,2)),MIN(MAX(ROUND(ROUND('Loonschijven_Tranches salariale'!$Q12*0.6,4)*Basisbedragen!$I$7,2),ROUND(Basisbedragen!$D$49*Basisbedragen!$I$7,2)),ROUND(ROUND(Basisbedragen!$D$30*0.6,4)*Basisbedragen!$I$7,2))+Basisbedragen!$I$10) -> 64.74 | F12: =ROUND(B12*1.2,2) -> 84.17 | H12: =ROUND(D12*1.2,2) -> 77.69 | J12: =MIN(MAX(ROUND(ROUND('Loonschijven_Tranches salariale'!$Q12*0.65,4)*Basisbedragen!$I$2,2),ROUND(Basisbedragen!$D$73*Basisbedragen!$I$2,2)),ROUND(ROUND(Basisbedragen!$D$31*0.65,4)*Basisbedragen!$I$2,2)) -> 56.48 | L12: =ROUND(MIN(MAX(ROUND(ROUND('Loonschijven_Tranches salariale'!$Q12*0.65,4)*Basisbedragen!$I$2,2),ROUND(Basisbedragen!$D$48*Basisbedragen!$I$2,2)),ROUND(ROUND(Basisbedragen!$D$30*0.65,4)*Basisbedragen!$I$2,2))/2,2) -> 35.07 | N12: =ROUND(MIN(MAX(ROUND(ROUND('Loonschijven_Tranches salariale'!$Q12*0.6,4)*Basisbedragen!$I$2,2),ROUND(Basisbedragen!$D$49*Basisbedragen!$I$2,2)),ROUND(ROUND(Basisbedragen!$D$30*0.6,4)*Basisbedragen!$I$2,2))/2,2) -> 32.37 | P12: =ROUND(L12*1.2,2) -> 42.08 | R12: =ROUND(N12*1.2,2) -> 38.84 | T12: =ROUND(J12/2,2) -> 28.24
A13: =A12+1 -> 6 | B13: =IF(MIN(MAX(ROUND(ROUND('Loonschijven_Tranches salariale'!$Q13*0.65,4)*Basisbedragen!$I$7,2),ROUND(Basisbedragen!$D$48*Basisbedragen!$I$7,2)),ROUND(ROUND(Basisbedragen!$D$30*0.65,4)*Basisbedragen!$I$7,2))<= Basisbedragen!$I$8,MIN(MAX(ROUND(ROUND('Loonschijven_Tranches salariale'!$Q13*0.65,4)*Basisbedragen!$I$2,2),ROUND(Basisbedragen!$D$48*Basisbedragen!$I$2,2)),ROUND(ROUND(Basisbedragen!$D$30*0.65,4)*Basisbedragen!$I$2,2)),MIN(MAX(ROUND(ROUND('Loonschijven_Tranches salariale'!$Q13*0.65,4)*Basisbedragen!$I$7,2),ROUND(Basisbedragen!$D$48*Basisbedragen!$I$7,2)),ROUND(ROUND(Basisbedragen!$D$30*0.65,4)*Basisbedragen!$I$7,2))+Basisbedragen!$I$10) -> 70.14 | D13: =IF(MIN(MAX(ROUND(ROUND('Loonschijven_Tranches salariale'!$Q13*0.6,4)*Basisbedragen!$I$7,2),ROUND(Basisbedragen!$D$49*Basisbedragen!$I$7,2)),ROUND(ROUND(Basisbedragen!$D$30*0.6,4)*Basisbedragen!$I$7,2))<= Basisbedragen!$I$8,MIN(MAX(ROUND(ROUND('Loonschijven_Tranches salariale'!$Q13*0.6,4)*Basisbedragen!$I$2,2),ROUND(Basisbedragen!$D$49*Basisbedragen!$I$2,2)),ROUND(ROUND(Basisbedragen!$D$30*0.6,4)*Basisbedragen!$I$2,2)),MIN(MAX(ROUND(ROUND('Loonschijven_Tranches salariale'!$Q13*0.6,4)*Basisbedragen!$I$7,2),ROUND(Basisbedragen!$D$49*Basisbedragen!$I$7,2)),ROUND(ROUND(Basisbedragen!$D$30*0.6,4)*Basisbedragen!$I$7,2))+Basisbedragen!$I$10) -> 64.74 | F13: =ROUND(B13*1.2,2) -> 84.17 | H13: =ROUND(D13*1.2,2) -> 77.69 | J13: =MIN(MAX(ROUND(ROUND('Loonschijven_Tranches salariale'!$Q13*0.65,4)*Basisbedragen!$I$2,2),ROUND(Basisbedragen!$D$73*Basisbedragen!$I$2,2)),ROUND(ROUND(Basisbedragen!$D$31*0.65,4)*Basisbedragen!$I$2,2)) -> 56.48 | L13: =ROUND(MIN(MAX(ROUND(ROUND('Loonschijven_Tranches salariale'!$Q13*0.65,4)*Basisbedragen!$I$2,2),ROUND(Basisbedragen!$D$48*Basisbedragen!$I$2,2)),ROUND(ROUND(Basisbedragen!$D$30*0.65,4)*Basisbedragen!$I$2,2))/2,2) -> 35.07 | N13: =ROUND(MIN(MAX(ROUND(ROUND('Loonschijven_Tranches salariale'!$Q13*0.6,4)*Basisbedragen!$I$2,2),ROUND(Basisbedragen!$D$49*Basisbedragen!$I$2,2)),ROUND(ROUND(Basisbedragen!$D$30*0.6,4)*Basisbedragen!$I$2,2))/2,2) -> 32.37 | P13: =ROUND(L13*1.2,2) -> 42.08 | R13: =ROUND(N13*1.2,2) -> 38.84 | T13: =ROUND(J13/2,2) -> 28.24
A14: =A13+1 -> 7 | B14: =IF(MIN(MAX(ROUND(ROUND('Loonschijven_Tranches salariale'!$Q14*0.65,4)*Basisbedragen!$I$7,2),ROUND(Basisbedragen!$D$48*Basisbedragen!$I$7,2)),ROUND(ROUND(Basisbedragen!$D$30*0.65,4)*Basisbedragen!$I$7,2))<= Basisbedragen!$I$8,MIN(MAX(ROUND(ROUND('Loonschijven_Tranches salariale'!$Q14*0.65,4)*Basisbedragen!$I$2,2),ROUND(Basisbedragen!$D$48*Basisbedragen!$I$2,2)),ROUND(ROUND(Basisbedragen!$D$30*0.65,4)*Basisbedragen!$I$2,2)),MIN(MAX(ROUND(ROUND('Loonschijven_Tranches salariale'!$Q14*0.65,4)*Basisbedragen!$I$7,2),ROUND(Basisbedragen!$D$48*Basisbedragen!$I$7,2)),ROUND(ROUND(Basisbedragen!$D$30*0.65,4)*Basisbedragen!$I$7,2))+Basisbedragen!$I$10) -> 70.14 | D14: =IF(MIN(MAX(ROUND(ROUND('Loonschijven_Tranches salariale'!$Q14*0.6,4)*Basisbedragen!$I$7,2),ROUND(Basisbedragen!$D$49*Basisbedragen!$I$7,2)),ROUND(ROUND(Basisbedragen!$D$30*0.6,4)*Basisbedragen!$I$7,2))<= Basisbedragen!$I$8,MIN(MAX(ROUND(ROUND('Loonschijven_Tranches salariale'!$Q14*0.6,4)*Basisbedragen!$I$2,2),ROUND(Basisbedragen!$D$49*Basisbedragen!$I$2,2)),ROUND(ROUND(Basisbedragen!$D$30*0.6,4)*Basisbedragen!$I$2,2)),MIN(MAX(ROUND(ROUND('Loonschijven_Tranches salariale'!$Q14*0.6,4)*Basisbedragen!$I$7,2),ROUND(Basisbedragen!$D$49*Basisbedragen!$I$7,2)),ROUND(ROUND(Basisbedragen!$D$30*0.6,4)*Basisbedragen!$I$7,2))+Basisbedragen!$I$10) -> 64.74 | F14: =ROUND(B14*1.2,2) -> 84.17 | H14: =ROUND(D14*1.2,2) -> 77.69 | J14: =MIN(MAX(ROUND(ROUND('Loonschijven_Tranches salariale'!$Q14*0.65,4)*Basisbedragen!$I$2,2),ROUND(Basisbedragen!$D$73*Basisbedragen!$I$2,2)),ROUND(ROUND(Basisbedragen!$D$31*0.65,4)*Basisbedragen!$I$2,2)) -> 56.48 | L14: =ROUND(MIN(MAX(ROUND(ROUND('Loonschijven_Tranches salariale'!$Q14*0.65,4)*Basisbedragen!$I$2,2),ROUND(Basisbedragen!$D$48*Basisbedragen!$I$2,2)),ROUND(ROUND(Basisbedragen!$D$30*0.65,4)*Basisbedragen!$I$2,2))/2,2) -> 35.07 | N14: =ROUND(MIN(MAX(ROUND(ROUND('Loonschijven_Tranches salariale'!$Q14*0.6,4)*Basisbedragen!$I$2,2),ROUND(Basisbedragen!$D$49*Basisbedragen!$I$2,2)),ROUND(ROUND(Basisbedragen!$D$30*0.6,4)*Basisbedragen!$I$2,2))/2,2) -> 32.37 | P14: =ROUND(L14*1.2,2) -> 42.08 | R14: =ROUND(N14*1.2,2) -> 38.84 | T14: =ROUND(J14/2,2) -> 28.24
A15: =A14+1 -> 8 | B15: =IF(MIN(MAX(ROUND(ROUND('Loonschijven_Tranches salariale'!$Q15*0.65,4)*Basisbedragen!$I$7,2),ROUND(Basisbedragen!$D$48*Basisbedragen!$I$7,2)),ROUND(ROUND(Basisbedragen!$D$30*0.65,4)*Basisbedragen!$I$7,2))<= Basisbedragen!$I$8,MIN(MAX(ROUND(ROUND('Loonschijven_Tranches salariale'!$Q15*0.65,4)*Basisbedragen!$I$2,2),ROUND(Basisbedragen!$D$48*Basisbedragen!$I$2,2)),ROUND(ROUND(Basisbedragen!$D$30*0.65,4)*Basisbedragen!$I$2,2)),MIN(MAX(ROUND(ROUND('Loonschijven_Tranches salariale'!$Q15*0.65,4)*Basisbedragen!$I$7,2),ROUND(Basisbedragen!$D$48*Basisbedragen!$I$7,2)),ROUND(ROUND(Basisbedragen!$D$30*0.65,4)*Basisbedragen!$I$7,2))+Basisbedragen!$I$10) -> 70.14 | D15: =IF(MIN(MAX(ROUND(ROUND('Loonschijven_Tranches salariale'!$Q15*0.6,4)*Basisbedragen!$I$7,2),ROUND(Basisbedragen!$D$49*Basisbedragen!$I$7,2)),ROUND(ROUND(Basisbedragen!$D$30*0.6,4)*Basisbedragen!$I$7,2))<= Basisbedragen!$I$8,MIN(MAX(ROUND(ROUND('Loonschijven_Tranches salariale'!$Q15*0.6,4)*Basisbedragen!$I$2,2),ROUND(Basisbedragen!$D$49*Basisbedragen!$I$2,2)),ROUND(ROUND(Basisbedragen!$D$30*0.6,4)*Basisbedragen!$I$2,2)),MIN(MAX(ROUND(ROUND('Loonschijven_Tranches salariale'!$Q15*0.6,4)*Basisbedragen!$I$7,2),ROUND(Basisbedragen!$D$49*Basisbedragen!$I$7,2)),ROUND(ROUND(Basisbedragen!$D$30*0.6,4)*Basisbedragen!$I$7,2))+Basisbedragen!$I$10) -> 64.74 | F15: =ROUND(B15*1.2,2) -> 84.17 | H15: =ROUND(D15*1.2,2) -> 77.69 | J15: =MIN(MAX(ROUND(ROUND('Loonschijven_Tranches salariale'!$Q15*0.65,4)*Basisbedragen!$I$2,2),ROUND(Basisbedragen!$D$73*Basisbedragen!$I$2,2)),ROUND(ROUND(Basisbedragen!$D$31*0.65,4)*Basisbedragen!$I$2,2)) -> 56.48 | L15: =ROUND(MIN(MAX(ROUND(ROUND('Loonschijven_Tranches salariale'!$Q15*0.65,4)*Basisbedragen!$I$2,2),ROUND(Basisbedragen!$D$48*Basisbedragen!$I$2,2)),ROUND(ROUND(Basisbedragen!$D$30*0.65,4)*Basisbedragen!$I$2,2))/2,2) -> 35.07 | N15: =ROUND(MIN(MAX(ROUND(ROUND('Loonschijven_Tranches salariale'!$Q15*0.6,4)*Basisbedragen!$I$2,2),ROUND(Basisbedragen!$D$49*Basisbedragen!$I$2,2)),ROUND(ROUND(Basisbedragen!$D$30*0.6,4)*Basisbedragen!$I$2,2))/2,2) -> 32.37 | P15: =ROUND(L15*1.2,2) -> 42.08 | R15: =ROUND(N15*1.2,2) -> 38.84 | T15: =ROUND(J15/2,2) -> 28.24
A16: =A15+1 -> 9 | B16: =IF(MIN(MAX(ROUND(ROUND('Loonschijven_Tranches salariale'!$Q16*0.65,4)*Basisbedragen!$I$7,2),ROUND(Basisbedragen!$D$48*Basisbedragen!$I$7,2)),ROUND(ROUND(Basisbedragen!$D$30*0.65,4)*Basisbedragen!$I$7,2))<= Basisbedragen!$I$8,MIN(MAX(ROUND(ROUND('Loonschijven_Tranches salariale'!$Q16*0.65,4)*Basisbedragen!$I$2,2),ROUND(Basisbedragen!$D$48*Basisbedragen!$I$2,2)),ROUND(ROUND(Basisbedragen!$D$30*0.65,4)*Basisbedragen!$I$2,2)),MIN(MAX(ROUND(ROUND('Loonschijven_Tranches salariale'!$Q16*0.65,4)*Basisbedragen!$I$7,2),ROUND(Basisbedragen!$D$48*Basisbedragen!$I$7,2)),ROUND(ROUND(Basisbedragen!$D$30*0.65,4)*Basisbedragen!$I$7,2))+Basisbedragen!$I$10) -> 70.14 | D16: =IF(MIN(MAX(ROUND(ROUND('Loonschijven_Tranches salariale'!$Q16*0.6,4)*Basisbedragen!$I$7,2),ROUND(Basisbedragen!$D$49*Basisbedragen!$I$7,2)),ROUND(ROUND(Basisbedragen!$D$30*0.6,4)*Basisbedragen!$I$7,2))<= Basisbedragen!$I$8,MIN(MAX(ROUND(ROUND('Loonschijven_Tranches salariale'!$Q16*0.6,4)*Basisbedragen!$I$2,2),ROUND(Basisbedragen!$D$49*Basisbedragen!$I$2,2)),ROUND(ROUND(Basisbedragen!$D$30*0.6,4)*Basisbedragen!$I$2,2)),MIN(MAX(ROUND(ROUND('Loonschijven_Tranches salariale'!$Q16*0.6,4)*Basisbedragen!$I$7,2),ROUND(Basisbedragen!$D$49*Basisbedragen!$I$7,2)),ROUND(ROUND(Basisbedragen!$D$30*0.6,4)*Basisbedragen!$I$7,2))+Basisbedragen!$I$10) -> 64.74 | F16: =ROUND(B16*1.2,2) -> 84.17 | H16: =ROUND(D16*1.2,2) -> 77.69 | J16: =MIN(MAX(ROUND(ROUND('Loonschijven_Tranches salariale'!$Q16*0.65,4)*Basisbedragen!$I$2,2),ROUND(Basisbedragen!$D$73*Basisbedragen!$I$2,2)),ROUND(ROUND(Basisbedragen!$D$31*0.65,4)*Basisbedragen!$I$2,2)) -> 56.48 | L16: =ROUND(MIN(MAX(ROUND(ROUND('Loonschijven_Tranches salariale'!$Q16*0.65,4)*Basisbedragen!$I$2,2),ROUND(Basisbedragen!$D$48*Basisbedragen!$I$2,2)),ROUND(ROUND(Basisbedragen!$D$30*0.65,4)*Basisbedragen!$I$2,2))/2,2) -> 35.07 | N16: =ROUND(MIN(MAX(ROUND(ROUND('Loonschijven_Tranches salariale'!$Q16*0.6,4)*Basisbedragen!$I$2,2),ROUND(Basisbedragen!$D$49*Basisbedragen!$I$2,2)),ROUND(ROUND(Basisbedragen!$D$30*0.6,4)*Basisbedragen!$I$2,2))/2,2) -> 32.37 | P16: =ROUND(L16*1.2,2) -> 42.08 | R16: =ROUND(N16*1.2,2) -> 38.84 | T16: =ROUND(J16/2,2) -> 28.24
A17: =A16+1 -> 10 | B17: =IF(MIN(MAX(ROUND(ROUND('Loonschijven_Tranches salariale'!$Q17*0.65,4)*Basisbedragen!$I$7,2),ROUND(Basisbedragen!$D$48*Basisbedragen!$I$7,2)),ROUND(ROUND(Basisbedragen!$D$30*0.65,4)*Basisbedragen!$I$7,2))<= Basisbedragen!$I$8,MIN(MAX(ROUND(ROUND('Loonschijven_Tranches salariale'!$Q17*0.65,4)*Basisbedragen!$I$2,2),ROUND(Basisbedragen!$D$48*Basisbedragen!$I$2,2)),ROUND(ROUND(Basisbedragen!$D$30*0.65,4)*Basisbedragen!$I$2,2)),MIN(MAX(ROUND(ROUND('Loonschijven_Tranches salariale'!$Q17*0.65,4)*Basisbedragen!$I$7,2),ROUND(Basisbedragen!$D$48*Basisbedragen!$I$7,2)),ROUND(ROUND(Basisbedragen!$D$30*0.65,4)*Basisbedragen!$I$7,2))+Basisbedragen!$I$10) -> 70.14 | D17: =IF(MIN(MAX(ROUND(ROUND('Loonschijven_Tranches salariale'!$Q17*0.6,4)*Basisbedragen!$I$7,2),ROUND(Basisbedragen!$D$49*Basisbedragen!$I$7,2)),ROUND(ROUND(Basisbedragen!$D$30*0.6,4)*Basisbedragen!$I$7,2))<= Basisbedragen!$I$8,MIN(MAX(ROUND(ROUND('Loonschijven_Tranches salariale'!$Q17*0.6,4)*Basisbedragen!$I$2,2),ROUND(Basisbedragen!$D$49*Basisbedragen!$I$2,2)),ROUND(ROUND(Basisbedragen!$D$30*0.6,4)*Basisbedragen!$I$2,2)),MIN(MAX(ROUND(ROUND('Loonschijven_Tranches salariale'!$Q17*0.6,4)*Basisbedragen!$I$7,2),ROUND(Basisbedragen!$D$49*Basisbedragen!$I$7,2)),ROUND(ROUND(Basisbedragen!$D$30*0.6,4)*Basisbedragen!$I$7,2))+Basisbedragen!$I$10) -> 64.74 | F17: =ROUND(B17*1.2,2) -> 84.17 | H17: =ROUND(D17*1.2,2) -> 77.69 | J17: =MIN(MAX(ROUND(ROUND('Loonschijven_Tranches salariale'!$Q17*0.65,4)*Basisbedragen!$I$2,2),ROUND(Basisbedragen!$D$73*Basisbedragen!$I$2,2)),ROUND(ROUND(Basisbedragen!$D$31*0.65,4)*Basisbedragen!$I$2,2)) -> 56.48 | L17: =ROUND(MIN(MAX(ROUND(ROUND('Loonschijven_Tranches salariale'!$Q17*0.65,4)*Basisbedragen!$I$2,2),ROUND(Basisbedragen!$D$48*Basisbedragen!$I$2,2)),ROUND(ROUND(Basisbedragen!$D$30*0.65,4)*Basisbedragen!$I$2,2))/2,2) -> 35.07 | N17: =ROUND(MIN(MAX(ROUND(ROUND('Loonschijven_Tranches salariale'!$Q17*0.6,4)*Basisbedragen!$I$2,2),ROUND(Basisbedragen!$D$49*Basisbedragen!$I$2,2)),ROUND(ROUND(Basisbedragen!$D$30*0.6,4)*Basisbedragen!$I$2,2))/2,2) -> 32.37 | P17: =ROUND(L17*1.2,2) -> 42.08 | R17: =ROUND(N17*1.2,2) -> 38.84 | T17: =ROUND(J17/2,2) -> 28.24
A18: =A17+1 -> 11 | B18: =IF(MIN(MAX(ROUND(ROUND('Loonschijven_Tranches salariale'!$Q18*0.65,4)*Basisbedragen!$I$7,2),ROUND(Basisbedragen!$D$48*Basisbedragen!$I$7,2)),ROUND(ROUND(Basisbedragen!$D$30*0.65,4)*Basisbedragen!$I$7,2))<= Basisbedragen!$I$8,MIN(MAX(ROUND(ROUND('Loonschijven_Tranches salariale'!$Q18*0.65,4)*Basisbedragen!$I$2,2),ROUND(Basisbedragen!$D$48*Basisbedragen!$I$2,2)),ROUND(ROUND(Basisbedragen!$D$30*0.65,4)*Basisbedragen!$I$2,2)),MIN(MAX(ROUND(ROUND('Loonschijven_Tranches salariale'!$Q18*0.65,4)*Basisbedragen!$I$7,2),ROUND(Basisbedragen!$D$48*Basisbedragen!$I$7,2)),ROUND(ROUND(Basisbedragen!$D$30*0.65,4)*Basisbedragen!$I$7,2))+Basisbedragen!$I$10) -> 70.14 | D18: =IF(MIN(MAX(ROUND(ROUND('Loonschijven_Tranches salariale'!$Q18*0.6,4)*Basisbedragen!$I$7,2),ROUND(Basisbedragen!$D$49*Basisbedragen!$I$7,2)),ROUND(ROUND(Basisbedragen!$D$30*0.6,4)*Basisbedragen!$I$7,2))<= Basisbedragen!$I$8,MIN(MAX(ROUND(ROUND('Loonschijven_Tranches salariale'!$Q18*0.6,4)*Basisbedragen!$I$2,2),ROUND(Basisbedragen!$D$49*Basisbedragen!$I$2,2)),ROUND(ROUND(Basisbedragen!$D$30*0.6,4)*Basisbedragen!$I$2,2)),MIN(MAX(ROUND(ROUND('Loonschijven_Tranches salariale'!$Q18*0.6,4)*Basisbedragen!$I$7,2),ROUND(Basisbedragen!$D$49*Basisbedragen!$I$7,2)),ROUND(ROUND(Basisbedragen!$D$30*0.6,4)*Basisbedragen!$I$7,2))+Basisbedragen!$I$10) -> 64.74 | F18: =ROUND(B18*1.2,2) -> 84.17 | H18: =ROUND(D18*1.2,2) -> 77.69 | J18: =MIN(MAX(ROUND(ROUND('Loonschijven_Tranches salariale'!$Q18*0.65,4)*Basisbedragen!$I$2,2),ROUND(Basisbedragen!$D$73*Basisbedragen!$I$2,2)),ROUND(ROUND(Basisbedragen!$D$31*0.65,4)*Basisbedragen!$I$2,2)) -> 56.48 | L18: =ROUND(MIN(MAX(ROUND(ROUND('Loonschijven_Tranches salariale'!$Q18*0.65,4)*Basisbedragen!$I$2,2),ROUND(Basisbedragen!$D$48*Basisbedragen!$I$2,2)),ROUND(ROUND(Basisbedragen!$D$30*0.65,4)*Basisbedragen!$I$2,2))/2,2) -> 35.07 | N18: =ROUND(MIN(MAX(ROUND(ROUND('Loonschijven_Tranches salariale'!$Q18*0.6,4)*Basisbedragen!$I$2,2),ROUND(Basisbedragen!$D$49*Basisbedragen!$I$2,2)),ROUND(ROUND(Basisbedragen!$D$30*0.6,4)*Basisbedragen!$I$2,2))/2,2) -> 32.37 | P18: =ROUND(L18*1.2,2) -> 42.08 | R18: =ROUND(N18*1.2,2) -> 38.84 | T18: =ROUND(J18/2,2) -> 28.24
A19: =A18+1 -> 12 | B19: =IF(MIN(MAX(ROUND(ROUND('Loonschijven_Tranches salariale'!$Q19*0.65,4)*Basisbedragen!$I$7,2),ROUND(Basisbedragen!$D$48*Basisbedragen!$I$7,2)),ROUND(ROUND(Basisbedragen!$D$30*0.65,4)*Basisbedragen!$I$7,2))<= Basisbedragen!$I$8,MIN(MAX(ROUND(ROUND('Loonschijven_Tranches salariale'!$Q19*0.65,4)*Basisbedragen!$I$2,2),ROUND(Basisbedragen!$D$48*Basisbedragen!$I$2,2)),ROUND(ROUND(Basisbedragen!$D$30*0.65,4)*Basisbedragen!$I$2,2)),MIN(MAX(ROUND(ROUND('Loonschijven_Tranches salariale'!$Q19*0.65,4)*Basisbedragen!$I$7,2),ROUND(Basisbedragen!$D$48*Basisbedragen!$I$7,2)),ROUND(ROUND(Basisbedragen!$D$30*0.65,4)*Basisbedragen!$I$7,2))+Basisbedragen!$I$10) -> 70.14 | D19: =IF(MIN(MAX(ROUND(ROUND('Loonschijven_Tranches salariale'!$Q19*0.6,4)*Basisbedragen!$I$7,2),ROUND(Basisbedragen!$D$49*Basisbedragen!$I$7,2)),ROUND(ROUND(Basisbedragen!$D$30*0.6,4)*Basisbedragen!$I$7,2))<= Basisbedragen!$I$8,MIN(MAX(ROUND(ROUND('Loonschijven_Tranches salariale'!$Q19*0.6,4)*Basisbedragen!$I$2,2),ROUND(Basisbedragen!$D$49*Basisbedragen!$I$2,2)),ROUND(ROUND(Basisbedragen!$D$30*0.6,4)*Basisbedragen!$I$2,2)),MIN(MAX(ROUND(ROUND('Loonschijven_Tranches salariale'!$Q19*0.6,4)*Basisbedragen!$I$7,2),ROUND(Basisbedragen!$D$49*Basisbedragen!$I$7,2)),ROUND(ROUND(Basisbedragen!$D$30*0.6,4)*Basisbedragen!$I$7,2))+Basisbedragen!$I$10) -> 64.74 | F19: =ROUND(B19*1.2,2) -> 84.17 | H19: =ROUND(D19*1.2,2) -> 77.69 | J19: =MIN(MAX(ROUND(ROUND('Loonschijven_Tranches salariale'!$Q19*0.65,4)*Basisbedragen!$I$2,2),ROUND(Basisbedragen!$D$73*Basisbedragen!$I$2,2)),ROUND(ROUND(Basisbedragen!$D$31*0.65,4)*Basisbedragen!$I$2,2)) -> 56.48 | L19: =ROUND(MIN(MAX(ROUND(ROUND('Loonschijven_Tranches salariale'!$Q19*0.65,4)*Basisbedragen!$I$2,2),ROUND(Basisbedragen!$D$48*Basisbedragen!$I$2,2)),ROUND(ROUND(Basisbedragen!$D$30*0.65,4)*Basisbedragen!$I$2,2))/2,2) -> 35.07 | N19: =ROUND(MIN(MAX(ROUND(ROUND('Loonschijven_Tranches salariale'!$Q19*0.6,4)*Basisbedragen!$I$2,2),ROUND(Basisbedragen!$D$49*Basisbedragen!$I$2,2)),ROUND(ROUND(Basisbedragen!$D$30*0.6,4)*Basisbedragen!$I$2,2))/2,2) -> 32.37 | P19: =ROUND(L19*1.2,2) -> 42.08 | R19: =ROUND(N19*1.2,2) -> 38.84 | T19: =ROUND(J19/2,2) -> 28.24
A20: =A19+1 -> 13 | B20: =IF(MIN(MAX(ROUND(ROUND('Loonschijven_Tranches salariale'!$Q20*0.65,4)*Basisbedragen!$I$7,2),ROUND(Basisbedragen!$D$48*Basisbedragen!$I$7,2)),ROUND(ROUND(Basisbedragen!$D$30*0.65,4)*Basisbedragen!$I$7,2))<= Basisbedragen!$I$8,MIN(MAX(ROUND(ROUND('Loonschijven_Tranches salariale'!$Q20*0.65,4)*Basisbedragen!$I$2,2),ROUND(Basisbedragen!$D$48*Basisbedragen!$I$2,2)),ROUND(ROUND(Basisbedragen!$D$30*0.65,4)*Basisbedragen!$I$2,2)),MIN(MAX(ROUND(ROUND('Loonschijven_Tranches salariale'!$Q20*0.65,4)*Basisbedragen!$I$7,2),ROUND(Basisbedragen!$D$48*Basisbedragen!$I$7,2)),ROUND(ROUND(Basisbedragen!$D$30*0.65,4)*Basisbedragen!$I$7,2))+Basisbedragen!$I$10) -> 70.14 | D20: =IF(MIN(MAX(ROUND(ROUND('Loonschijven_Tranches salariale'!$Q20*0.6,4)*Basisbedragen!$I$7,2),ROUND(Basisbedragen!$D$49*Basisbedragen!$I$7,2)),ROUND(ROUND(Basisbedragen!$D$30*0.6,4)*Basisbedragen!$I$7,2))<= Basisbedragen!$I$8,MIN(MAX(ROUND(ROUND('Loonschijven_Tranches salariale'!$Q20*0.6,4)*Basisbedragen!$I$2,2),ROUND(Basisbedragen!$D$49*Basisbedragen!$I$2,2)),ROUND(ROUND(Basisbedragen!$D$30*0.6,4)*Basisbedragen!$I$2,2)),MIN(MAX(ROUND(ROUND('Loonschijven_Tranches salariale'!$Q20*0.6,4)*Basisbedragen!$I$7,2),ROUND(Basisbedragen!$D$49*Basisbedragen!$I$7,2)),ROUND(ROUND(Basisbedragen!$D$30*0.6,4)*Basisbedragen!$I$7,2))+Basisbedragen!$I$10) -> 64.74 | F20: =ROUND(B20*1.2,2) -> 84.17 | H20: =ROUND(D20*1.2,2) -> 77.69 | J20: =MIN(MAX(ROUND(ROUND('Loonschijven_Tranches salariale'!$Q20*0.65,4)*Basisbedragen!$I$2,2),ROUND(Basisbedragen!$D$73*Basisbedragen!$I$2,2)),ROUND(ROUND(Basisbedragen!$D$31*0.65,4)*Basisbedragen!$I$2,2)) -> 56.48 | L20: =ROUND(MIN(MAX(ROUND(ROUND('Loonschijven_Tranches salariale'!$Q20*0.65,4)*Basisbedragen!$I$2,2),ROUND(Basisbedragen!$D$48*Basisbedragen!$I$2,2)),ROUND(ROUND(Basisbedragen!$D$30*0.65,4)*Basisbedragen!$I$2,2))/2,2) -> 35.07 | N20: =ROUND(MIN(MAX(ROUND(ROUND('Loonschijven_Tranches salariale'!$Q20*0.6,4)*Basisbedragen!$I$2,2),ROUND(Basisbedragen!$D$49*Basisbedragen!$I$2,2)),ROUND(ROUND(Basisbedragen!$D$30*0.6,4)*Basisbedragen!$I$2,2))/2,2) -> 32.37 | P20: =ROUND(L20*1.2,2) -> 42.08 | R20: =ROUND(N20*1.2,2) -> 38.84 | T20: =ROUND(J20/2,2) -> 28.24
... A106: =A105+1 -> 99 | B106: =IF(MIN(MAX(ROUND(ROUND('Loonschijven_Tranches salariale'!$Q106*0.65,4)*Basisbedragen!$I$7,2),ROUND(Basisbedragen!$D$48*Basisbedragen!$I$7,2)),ROUND(ROUND(Basisbedragen!$D$30*0.65,4)*Basisbedragen!$I$7,2))<= Basisbedragen!$I$8,MIN(MAX(ROUND(ROUND('Loonschijven_Tranches salariale'!$Q106*0.65,4)*Basisbedragen!$I$2,2),ROUND(Basisbedragen!$D$48*Basisbedragen!$I$2,2)),ROUND(ROUND(Basisbedragen!$D$30*0.65,4)*Basisbedragen!$I$2,2)),MIN(MAX(ROUND(ROUND('Loonschijven_Tranches salariale'!$Q106*0.65,4)*Basisbedragen!$I$7,2),ROUND(Basisbedragen!$D$48*Basisbedragen!$I$7,2)),ROUND(ROUND(Basisbedragen!$D$30*0.65,4)*Basisbedragen!$I$7,2))+Basisbedragen!$I$10) -> 89.06 | D106: =IF(MIN(MAX(ROUND(ROUND('Loonschijven_Tranches salariale'!$Q106*0.6,4)*Basisbedragen!$I$7,2),ROUND(Basisbedragen!$D$49*Basisbedragen!$I$7,2)),ROUND(ROUND(Basisbedragen!$D$30*0.6,4)*Basisbedragen!$I$7,2))<= Basisbedragen!$I$8,MIN(MAX(ROUND(ROUND('Loonschijven_Tranches salariale'!$Q106*0.6,4)*Basisbedragen!$I$2,2),ROUND(Basisbedragen!$D$49*Basisbedragen!$I$2,2)),ROUND(ROUND(Basisbedragen!$D$30*0.6,4)*Basisbedragen!$I$2,2)),MIN(MAX(ROUND(ROUND('Loonschijven_Tranches salariale'!$Q106*0.6,4)*Basisbedragen!$I$7,2),ROUND(Basisbedragen!$D$49*Basisbedragen!$I$7,2)),ROUND(ROUND(Basisbedragen!$D$30*0.6,4)*Basisbedragen!$I$7,2))+Basisbedragen!$I$10) -> 82.33 | F106: =ROUND(B106*1.2,2) -> 106.87 | H106: =ROUND(D106*1.2,2) -> 98.8 | J106: =MIN(MAX(ROUND(ROUND('Loonschijven_Tranches salariale'!$Q106*0.65,4)*Basisbedragen!$I$2,2),ROUND(Basisbedragen!$D$73*Basisbedragen!$I$2,2)),ROUND(ROUND(Basisbedragen!$D$31*0.65,4)*Basisbedragen!$I$2,2)) -> 76.8 | L106: =ROUND(MIN(MAX(ROUND(ROUND('Loonschijven_Tranches salariale'!$Q106*0.65,4)*Basisbedragen!$I$2,2),ROUND(Basisbedragen!$D$48*Basisbedragen!$I$2,2)),ROUND(ROUND(Basisbedragen!$D$30*0.65,4)*Basisbedragen!$I$2,2))/2,2) -> 44.64 | N106: =ROUND(MIN(MAX(ROUND(ROUND('Loonschijven_Tranches salariale'!$Q106*0.6,4)*Basisbedragen!$I$2,2),ROUND(Basisbedragen!$D$49*Basisbedragen!$I$2,2)),ROUND(ROUND(Basisbedragen!$D$30*0.6,4)*Basisbedragen!$I$2,2))/2,2) -> 41.21 | P106: =ROUND(L106*1.2,2) -> 53.57 | R106: =ROUND(N106*1.2,2) -> 49.45 | T106: =ROUND(J106/2,2) -> 38.4

Sheet SpecCat
A1: Geldig/valable | C1: Volledige werkloosheidsuitkeringen - dagbedrag van de uitkering - speciale categorieën | S1: Multiplicat(o)(eu)r | U1: =Basisbedragen!$I$2 -> 1.8114
A2: 46266 | C2: Allocations de chômage complet - montant journalier de l'allocation - catégories spéciales
B4: Volle uitkering / Allocation entière | L4: Halve uitkering / Demi allocation
B5: Havenarbeiders Travailleurs de port (Bedragen/montants R5!) | C5: Zeevissers Pêcheurs de mer | E5: Stelsel van werkloosheid met bedrijfstoeslag (voorheen brugpensioen) Régime de chômage avec complément d'entreprise (auparavant prépension) | I5: Kunstwerkers Travailleurs des arts | L5: Havenarbeiders Travailleurs de port (Bedragen/montants R5!) | M5: Zeevissers Pêcheurs de mer | O5: Stelsel van werkloosheid met bedrijfstoeslag (voorheen brugpensioen) Régime de chômage avec complément d'entreprise (auparavant prépension)
A6: Code | B6: A6 | C6: A7 | E6: E FA | F6: GN FN | G6: GB FB | I6: AA | J6: AN AB | L6: A6 | M6: A7 | O6: E FA | P6: GN FN | Q6: GB FB
B7: 0.6 | C7: 0.6 | E7: 0.6 | F7: 0.6 | G7: 0.6 | I7: 0.6 | J7: 0.6 | L7: 0.6 | M7: 0.6 | O7: 0.6 | P7: 0.6 | Q7: 0.6
A8: MIN | B8: =ROUND(C8*1.2,2) -> 85.19 | C8: =ROUND(Basisbedragen!$D$47*$U$1,2) -> 70.99 | E8: =ROUND(Basisbedragen!$D$44*$U$1,2) -> 68.63 | F8: =ROUND(Basisbedragen!$D$45*$U$1,2) -> 55.63 | G8: =ROUND(Basisbedragen!$D$46*$U$1,2) -> 49.43 | I8: =ROUND(Basisbedragen!$D$77*$U$1,2) -> 73.98 | J8: =ROUND(Basisbedragen!$D$78*$U$1,2) -> 65.17 | L8: =ROUND(B8/2,2) -> 42.6 | M8: =ROUND(C8/2,2) -> 35.5 | O8: =ROUND(E8/2,2) -> 34.32 | P8: =ROUND(F8/2,2) -> 27.82 | Q8: =ROUND(G8/2,2) -> 24.72
A9: 1 | B9: =ROUND(C9*1.2,2) -> 85.19 | C9: =IF(MIN(MAX(ROUND(ROUND('Loonschijven_Tranches salariale'!$Q8*0.6,4)*Basisbedragen!$I$7,2),ROUND(Basisbedragen!$D$47*Basisbedragen!$I$7,2)),ROUND(ROUND(Basisbedragen!$D$30*0.6,4)*Basisbedragen!$I$7,2))<= Basisbedragen!$I$8,MIN(MAX(ROUND(ROUND('Loonschijven_Tranches salariale'!$Q8*0.6,4)*Basisbedragen!$I$2,2),ROUND(Basisbedragen!$D$47*Basisbedragen!$I$2,2)),ROUND(ROUND(Basisbedragen!$D$30*0.6,4)*Basisbedragen!$I$2,2)),MIN(MAX(ROUND(ROUND('Loonschijven_Tranches salariale'!$Q8*0.6,4)*Basisbedragen!$I$7,2),ROUND(Basisbedragen!$D$47*Basisbedragen!$I$7,2)),ROUND(ROUND(Basisbedragen!$D$30*0.6,4)*Basisbedragen!$I$7,2))+Basisbedragen!$I$10) -> 70.99 | E9: =MIN(MAX(ROUND(ROUND('Loonschijven_Tranches salariale'!$Q8*0.6,4)*Basisbedragen!$I$2,2),ROUND(Basisbedragen!$D$44*Basisbedragen!$I$2,2)),ROUND(ROUND(Basisbedragen!$D$32*0.6,4)*Basisbedragen!$I$2,2)) -> 68.63 | F9: =MIN(MAX(ROUND(ROUND('Loonschijven_Tranches salariale'!$Q8*0.6,4)*Basisbedragen!$I$2,2),ROUND(Basisbedragen!$D$45*Basisbedragen!$I$2,2)),ROUND(ROUND(Basisbedragen!$D$32*0.6,4)*Basisbedragen!$I$2,2)) -> 55.63 | G9: =MIN(MAX(ROUND(ROUND('Loonschijven_Tranches salariale'!$Q8*0.6,4)*Basisbedragen!$I$2,2),ROUND(Basisbedragen!$D$46*Basisbedragen!$I$2,2)),ROUND(ROUND(Basisbedragen!$D$32*0.6,4)*Basisbedragen!$I$2,2)) -> 49.43 | I9: =MIN(MAX(ROUND(ROUND('Loonschijven_Tranches salariale'!$Q8*0.6,4)*Basisbedragen!$I$2,2),ROUND(Basisbedragen!$D$77*Basisbedragen!$I$2,2)),ROUND(ROUND(Basisbedragen!$D$29*0.6,4)*Basisbedragen!$I$2,2)) -> 73.98 | J9: =MIN(MAX(ROUND(ROUND('Loonschijven_Tranches salariale'!$Q8*0.6,4)*Basisbedragen!$I$2,2),ROUND(Basisbedragen!$D$78*Basisbedragen!$I$2,2)),ROUND(ROUND(Basisbedragen!$D$29*0.6,4)*Basisbedragen!$I$2,2)) -> 65.17 | L9: =ROUND(M9*1.2,2) -> 42.6 | M9: =ROUND(MIN(MAX(ROUND(ROUND('Loonschijven_Tranches salariale'!$Q8*0.6,4)*Basisbedragen!$I$2,2),ROUND(Basisbedragen!$D$47*Basisbedragen!$I$2,2)),ROUND(ROUND(Basisbedragen!$D$30*0.6,4)*Basisbedragen!$I$2,2))/2,2) -> 35.5 | O9: =ROUND(E9/2,2) -> 34.32 | P9: =ROUND(F9/2,2) -> 27.82 | Q9: =ROUND(G9/2,2) -> 24.72
A10: =A9+1 -> 2 | B10: =ROUND(C10*1.2,2) -> 85.19 | C10: =IF(MIN(MAX(ROUND(ROUND('Loonschijven_Tranches salariale'!$Q9*0.6,4)*Basisbedragen!$I$7,2),ROUND(Basisbedragen!$D$47*Basisbedragen!$I$7,2)),ROUND(ROUND(Basisbedragen!$D$30*0.6,4)*Basisbedragen!$I$7,2))<= Basisbedragen!$I$8,MIN(MAX(ROUND(ROUND('Loonschijven_Tranches salariale'!$Q9*0.6,4)*Basisbedragen!$I$2,2),ROUND(Basisbedragen!$D$47*Basisbedragen!$I$2,2)),ROUND(ROUND(Basisbedragen!$D$30*0.6,4)*Basisbedragen!$I$2,2)),MIN(MAX(ROUND(ROUND('Loonschijven_Tranches salariale'!$Q9*0.6,4)*Basisbedragen!$I$7,2),ROUND(Basisbedragen!$D$47*Basisbedragen!$I$7,2)),ROUND(ROUND(Basisbedragen!$D$30*0.6,4)*Basisbedragen!$I$7,2))+Basisbedragen!$I$10) -> 70.99 | E10: =MIN(MAX(ROUND(ROUND('Loonschijven_Tranches salariale'!$Q9*0.6,4)*Basisbedragen!$I$2,2),ROUND(Basisbedragen!$D$44*Basisbedragen!$I$2,2)),ROUND(ROUND(Basisbedragen!$D$32*0.6,4)*Basisbedragen!$I$2,2)) -> 68.63 | F10: =MIN(MAX(ROUND(ROUND('Loonschijven_Tranches salariale'!$Q9*0.6,4)*Basisbedragen!$I$2,2),ROUND(Basisbedragen!$D$45*Basisbedragen!$I$2,2)),ROUND(ROUND(Basisbedragen!$D$32*0.6,4)*Basisbedragen!$I$2,2)) -> 55.63 | G10: =MIN(MAX(ROUND(ROUND('Loonschijven_Tranches salariale'!$Q9*0.6,4)*Basisbedragen!$I$2,2),ROUND(Basisbedragen!$D$46*Basisbedragen!$I$2,2)),ROUND(ROUND(Basisbedragen!$D$32*0.6,4)*Basisbedragen!$I$2,2)) -> 49.43 | I10: =MIN(MAX(ROUND(ROUND('Loonschijven_Tranches salariale'!$Q9*0.6,4)*Basisbedragen!$I$2,2),ROUND(Basisbedragen!$D$77*Basisbedragen!$I$2,2)),ROUND(ROUND(Basisbedragen!$D$29*0.6,4)*Basisbedragen!$I$2,2)) -> 73.98 | J10: =MIN(MAX(ROUND(ROUND('Loonschijven_Tranches salariale'!$Q9*0.6,4)*Basisbedragen!$I$2,2),ROUND(Basisbedragen!$D$78*Basisbedragen!$I$2,2)),ROUND(ROUND(Basisbedragen!$D$29*0.6,4)*Basisbedragen!$I$2,2)) -> 65.17 | L10: =ROUND(M10*1.2,2) -> 42.6 | M10: =ROUND(MIN(MAX(ROUND(ROUND('Loonschijven_Tranches salariale'!$Q9*0.6,4)*Basisbedragen!$I$2,2),ROUND(Basisbedragen!$D$47*Basisbedragen!$I$2,2)),ROUND(ROUND(Basisbedragen!$D$30*0.6,4)*Basisbedragen!$I$2,2))/2,2) -> 35.5 | O10: =ROUND(E10/2,2) -> 34.32 | P10: =ROUND(F10/2,2) -> 27.82 | Q10: =ROUND(G10/2,2) -> 24.72
A11: =A10+1 -> 3 | B11: =ROUND(C11*1.2,2) -> 85.19 | C11: =IF(MIN(MAX(ROUND(ROUND('Loonschijven_Tranches salariale'!$Q10*0.6,4)*Basisbedragen!$I$7,2),ROUND(Basisbedragen!$D$47*Basisbedragen!$I$7,2)),ROUND(ROUND(Basisbedragen!$D$30*0.6,4)*Basisbedragen!$I$7,2))<= Basisbedragen!$I$8,MIN(MAX(ROUND(ROUND('Loonschijven_Tranches salariale'!$Q10*0.6,4)*Basisbedragen!$I$2,2),ROUND(Basisbedragen!$D$47*Basisbedragen!$I$2,2)),ROUND(ROUND(Basisbedragen!$D$30*0.6,4)*Basisbedragen!$I$2,2)),MIN(MAX(ROUND(ROUND('Loonschijven_Tranches salariale'!$Q10*0.6,4)*Basisbedragen!$I$7,2),ROUND(Basisbedragen!$D$47*Basisbedragen!$I$7,2)),ROUND(ROUND(Basisbedragen!$D$30*0.6,4)*Basisbedragen!$I$7,2))+Basisbedragen!$I$10) -> 70.99 | E11: =MIN(MAX(ROUND(ROUND('Loonschijven_Tranches salariale'!$Q10*0.6,4)*Basisbedragen!$I$2,2),ROUND(Basisbedragen!$D$44*Basisbedragen!$I$2,2)),ROUND(ROUND(Basisbedragen!$D$32*0.6,4)*Basisbedragen!$I$2,2)) -> 68.63 | F11: =MIN(MAX(ROUND(ROUND('Loonschijven_Tranches salariale'!$Q10*0.6,4)*Basisbedragen!$I$2,2),ROUND(Basisbedragen!$D$45*Basisbedragen!$I$2,2)),ROUND(ROUND(Basisbedragen!$D$32*0.6,4)*Basisbedragen!$I$2,2)) -> 55.63 | G11: =MIN(MAX(ROUND(ROUND('Loonschijven_Tranches salariale'!$Q10*0.6,4)*Basisbedragen!$I$2,2),ROUND(Basisbedragen!$D$46*Basisbedragen!$I$2,2)),ROUND(ROUND(Basisbedragen!$D$32*0.6,4)*Basisbedragen!$I$2,2)) -> 49.43 | I11: =MIN(MAX(ROUND(ROUND('Loonschijven_Tranches salariale'!$Q10*0.6,4)*Basisbedragen!$I$2,2),ROUND(Basisbedragen!$D$77*Basisbedragen!$I$2,2)),ROUND(ROUND(Basisbedragen!$D$29*0.6,4)*Basisbedragen!$I$2,2)) -> 73.98 | J11: =MIN(MAX(ROUND(ROUND('Loonschijven_Tranches salariale'!$Q10*0.6,4)*Basisbedragen!$I$2,2),ROUND(Basisbedragen!$D$78*Basisbedragen!$I$2,2)),ROUND(ROUND(Basisbedragen!$D$29*0.6,4)*Basisbedragen!$I$2,2)) -> 65.17 | L11: =ROUND(M11*1.2,2) -> 42.6 | M11: =ROUND(MIN(MAX(ROUND(ROUND('Loonschijven_Tranches salariale'!$Q10*0.6,4)*Basisbedragen!$I$2,2),ROUND(Basisbedragen!$D$47*Basisbedragen!$I$2,2)),ROUND(ROUND(Basisbedragen!$D$30*0.6,4)*Basisbedragen!$I$2,2))/2,2) -> 35.5 | O11: =ROUND(E11/2,2) -> 34.32 | P11: =ROUND(F11/2,2) -> 27.82 | Q11: =ROUND(G11/2,2) -> 24.72
A12: =A11+1 -> 4 | B12: =ROUND(C12*1.2,2) -> 85.19 | C12: =IF(MIN(MAX(ROUND(ROUND('Loonschijven_Tranches salariale'!$Q11*0.6,4)*Basisbedragen!$I$7,2),ROUND(Basisbedragen!$D$47*Basisbedragen!$I$7,2)),ROUND(ROUND(Basisbedragen!$D$30*0.6,4)*Basisbedragen!$I$7,2))<= Basisbedragen!$I$8,MIN(MAX(ROUND(ROUND('Loonschijven_Tranches salariale'!$Q11*0.6,4)*Basisbedragen!$I$2,2),ROUND(Basisbedragen!$D$47*Basisbedragen!$I$2,2)),ROUND(ROUND(Basisbedragen!$D$30*0.6,4)*Basisbedragen!$I$2,2)),MIN(MAX(ROUND(ROUND('Loonschijven_Tranches salariale'!$Q11*0.6,4)*Basisbedragen!$I$7,2),ROUND(Basisbedragen!$D$47*Basisbedragen!$I$7,2)),ROUND(ROUND(Basisbedragen!$D$30*0.6,4)*Basisbedragen!$I$7,2))+Basisbedragen!$I$10) -> 70.99 | E12: =MIN(MAX(ROUND(ROUND('Loonschijven_Tranches salariale'!$Q11*0.6,4)*Basisbedragen!$I$2,2),ROUND(Basisbedragen!$D$44*Basisbedragen!$I$2,2)),ROUND(ROUND(Basisbedragen!$D$32*0.6,4)*Basisbedragen!$I$2,2)) -> 68.63 | F12: =MIN(MAX(ROUND(ROUND('Loonschijven_Tranches salariale'!$Q11*0.6,4)*Basisbedragen!$I$2,2),ROUND(Basisbedragen!$D$45*Basisbedragen!$I$2,2)),ROUND(ROUND(Basisbedragen!$D$32*0.6,4)*Basisbedragen!$I$2,2)) -> 55.63 | G12: =MIN(MAX(ROUND(ROUND('Loonschijven_Tranches salariale'!$Q11*0.6,4)*Basisbedragen!$I$2,2),ROUND(Basisbedragen!$D$46*Basisbedragen!$I$2,2)),ROUND(ROUND(Basisbedragen!$D$32*0.6,4)*Basisbedragen!$I$2,2)) -> 49.43 | I12: =MIN(MAX(ROUND(ROUND('Loonschijven_Tranches salariale'!$Q11*0.6,4)*Basisbedragen!$I$2,2),ROUND(Basisbedragen!$D$77*Basisbedragen!$I$2,2)),ROUND(ROUND(Basisbedragen!$D$29*0.6,4)*Basisbedragen!$I$2,2)) -> 73.98 | J12: =MIN(MAX(ROUND(ROUND('Loonschijven_Tranches salariale'!$Q11*0.6,4)*Basisbedragen!$I$2,2),ROUND(Basisbedragen!$D$78*Basisbedragen!$I$2,2)),ROUND(ROUND(Basisbedragen!$D$29*0.6,4)*Basisbedragen!$I$2,2)) -> 65.17 | L12: =ROUND(M12*1.2,2) -> 42.6 | M12: =ROUND(MIN(MAX(ROUND(ROUND('Loonschijven_Tranches salariale'!$Q11*0.6,4)*Basisbedragen!$I$2,2),ROUND(Basisbedragen!$D$47*Basisbedragen!$I$2,2)),ROUND(ROUND(Basisbedragen!$D$30*0.6,4)*Basisbedragen!$I$2,2))/2,2) -> 35.5 | O12: =ROUND(E12/2,2) -> 34.32 | P12: =ROUND(F12/2,2) -> 27.82 | Q12: =ROUND(G12/2,2) -> 24.72
A13: =A12+1 -> 5 | B13: =ROUND(C13*1.2,2) -> 85.19 | C13: =IF(MIN(MAX(ROUND(ROUND('Loonschijven_Tranches salariale'!$Q12*0.6,4)*Basisbedragen!$I$7,2),ROUND(Basisbedragen!$D$47*Basisbedragen!$I$7,2)),ROUND(ROUND(Basisbedragen!$D$30*0.6,4)*Basisbedragen!$I$7,2))<= Basisbedragen!$I$8,MIN(MAX(ROUND(ROUND('Loonschijven_Tranches salariale'!$Q12*0.6,4)*Basisbedragen!$I$2,2),ROUND(Basisbedragen!$D$47*Basisbedragen!$I$2,2)),ROUND(ROUND(Basisbedragen!$D$30*0.6,4)*Basisbedragen!$I$2,2)),MIN(MAX(ROUND(ROUND('Loonschijven_Tranches salariale'!$Q12*0.6,4)*Basisbedragen!$I$7,2),ROUND(Basisbedragen!$D$47*Basisbedragen!$I$7,2)),ROUND(ROUND(Basisbedragen!$D$30*0.6,4)*Basisbedragen!$I$7,2))+Basisbedragen!$I$10) -> 70.99 | E13: =MIN(MAX(ROUND(ROUND('Loonschijven_Tranches salariale'!$Q12*0.6,4)*Basisbedragen!$I$2,2),ROUND(Basisbedragen!$D$44*Basisbedragen!$I$2,2)),ROUND(ROUND(Basisbedragen!$D$32*0.6,4)*Basisbedragen!$I$2,2)) -> 68.63 | F13: =MIN(MAX(ROUND(ROUND('Loonschijven_Tranches salariale'!$Q12*0.6,4)*Basisbedragen!$I$2,2),ROUND(Basisbedragen!$D$45*Basisbedragen!$I$2,2)),ROUND(ROUND(Basisbedragen!$D$32*0.6,4)*Basisbedragen!$I$2,2)) -> 55.63 | G13: =MIN(MAX(ROUND(ROUND('Loonschijven_Tranches salariale'!$Q12*0.6,4)*Basisbedragen!$I$2,2),ROUND(Basisbedragen!$D$46*Basisbedragen!$I$2,2)),ROUND(ROUND(Basisbedragen!$D$32*0.6,4)*Basisbedragen!$I$2,2)) -> 49.43 | I13: =MIN(MAX(ROUND(ROUND('Loonschijven_Tranches salariale'!$Q12*0.6,4)*Basisbedragen!$I$2,2),ROUND(Basisbedragen!$D$77*Basisbedragen!$I$2,2)),ROUND(ROUND(Basisbedragen!$D$29*0.6,4)*Basisbedragen!$I$2,2)) -> 73.98 | J13: =MIN(MAX(ROUND(ROUND('Loonschijven_Tranches salariale'!$Q12*0.6,4)*Basisbedragen!$I$2,2),ROUND(Basisbedragen!$D$78*Basisbedragen!$I$2,2)),ROUND(ROUND(Basisbedragen!$D$29*0.6,4)*Basisbedragen!$I$2,2)) -> 65.17 | L13: =ROUND(M13*1.2,2) -> 42.6 | M13: =ROUND(MIN(MAX(ROUND(ROUND('Loonschijven_Tranches salariale'!$Q12*0.6,4)*Basisbedragen!$I$2,2),ROUND(Basisbedragen!$D$47*Basisbedragen!$I$2,2)),ROUND(ROUND(Basisbedragen!$D$30*0.6,4)*Basisbedragen!$I$2,2))/2,2) -> 35.5 | O13: =ROUND(E13/2,2) -> 34.32 | P13: =ROUND(F13/2,2) -> 27.82 | Q13: =ROUND(G13/2,2) -> 24.72
A14: =A13+1 -> 6 | B14: =ROUND(C14*1.2,2) -> 85.19 | C14: =IF(MIN(MAX(ROUND(ROUND('Loonschijven_Tranches salariale'!$Q13*0.6,4)*Basisbedragen!$I$7,2),ROUND(Basisbedragen!$D$47*Basisbedragen!$I$7,2)),ROUND(ROUND(Basisbedragen!$D$30*0.6,4)*Basisbedragen!$I$7,2))<= Basisbedragen!$I$8,MIN(MAX(ROUND(ROUND('Loonschijven_Tranches salariale'!$Q13*0.6,4)*Basisbedragen!$I$2,2),ROUND(Basisbedragen!$D$47*Basisbedragen!$I$2,2)),ROUND(ROUND(Basisbedragen!$D$30*0.6,4)*Basisbedragen!$I$2,2)),MIN(MAX(ROUND(ROUND('Loonschijven_Tranches salariale'!$Q13*0.6,4)*Basisbedragen!$I$7,2),ROUND(Basisbedragen!$D$47*Basisbedragen!$I$7,2)),ROUND(ROUND(Basisbedragen!$D$30*0.6,4)*Basisbedragen!$I$7,2))+Basisbedragen!$I$10) -> 70.99 | E14: =MIN(MAX(ROUND(ROUND('Loonschijven_Tranches salariale'!$Q13*0.6,4)*Basisbedragen!$I$2,2),ROUND(Basisbedragen!$D$44*Basisbedragen!$I$2,2)),ROUND(ROUND(Basisbedragen!$D$32*0.6,4)*Basisbedragen!$I$2,2)) -> 68.63 | F14: =MIN(MAX(ROUND(ROUND('Loonschijven_Tranches salariale'!$Q13*0.6,4)*Basisbedragen!$I$2,2),ROUND(Basisbedragen!$D$45*Basisbedragen!$I$2,2)),ROUND(ROUND(Basisbedragen!$D$32*0.6,4)*Basisbedragen!$I$2,2)) -> 55.63 | G14: =MIN(MAX(ROUND(ROUND('Loonschijven_Tranches salariale'!$Q13*0.6,4)*Basisbedragen!$I$2,2),ROUND(Basisbedragen!$D$46*Basisbedragen!$I$2,2)),ROUND(ROUND(Basisbedragen!$D$32*0.6,4)*Basisbedragen!$I$2,2)) -> 49.43 | I14: =MIN(MAX(ROUND(ROUND('Loonschijven_Tranches salariale'!$Q13*0.6,4)*Basisbedragen!$I$2,2),ROUND(Basisbedragen!$D$77*Basisbedragen!$I$2,2)),ROUND(ROUND(Basisbedragen!$D$29*0.6,4)*Basisbedragen!$I$2,2)) -> 73.98 | J14: =MIN(MAX(ROUND(ROUND('Loonschijven_Tranches salariale'!$Q13*0.6,4)*Basisbedragen!$I$2,2),ROUND(Basisbedragen!$D$78*Basisbedragen!$I$2,2)),ROUND(ROUND(Basisbedragen!$D$29*0.6,4)*Basisbedragen!$I$2,2)) -> 65.17 | L14: =ROUND(M14*1.2,2) -> 42.6 | M14: =ROUND(MIN(MAX(ROUND(ROUND('Loonschijven_Tranches salariale'!$Q13*0.6,4)*Basisbedragen!$I$2,2),ROUND(Basisbedragen!$D$47*Basisbedragen!$I$2,2)),ROUND(ROUND(Basisbedragen!$D$30*0.6,4)*Basisbedragen!$I$2,2))/2,2) -> 35.5 | O14: =ROUND(E14/2,2) -> 34.32 | P14: =ROUND(F14/2,2) -> 27.82 | Q14: =ROUND(G14/2,2) -> 24.72
A15: =A14+1 -> 7 | B15: =ROUND(C15*1.2,2) -> 85.19 | C15: =IF(MIN(MAX(ROUND(ROUND('Loonschijven_Tranches salariale'!$Q14*0.6,4)*Basisbedragen!$I$7,2),ROUND(Basisbedragen!$D$47*Basisbedragen!$I$7,2)),ROUND(ROUND(Basisbedragen!$D$30*0.6,4)*Basisbedragen!$I$7,2))<= Basisbedragen!$I$8,MIN(MAX(ROUND(ROUND('Loonschijven_Tranches salariale'!$Q14*0.6,4)*Basisbedragen!$I$2,2),ROUND(Basisbedragen!$D$47*Basisbedragen!$I$2,2)),ROUND(ROUND(Basisbedragen!$D$30*0.6,4)*Basisbedragen!$I$2,2)),MIN(MAX(ROUND(ROUND('Loonschijven_Tranches salariale'!$Q14*0.6,4)*Basisbedragen!$I$7,2),ROUND(Basisbedragen!$D$47*Basisbedragen!$I$7,2)),ROUND(ROUND(Basisbedragen!$D$30*0.6,4)*Basisbedragen!$I$7,2))+Basisbedragen!$I$10) -> 70.99 | E15: =MIN(MAX(ROUND(ROUND('Loonschijven_Tranches salariale'!$Q14*0.6,4)*Basisbedragen!$I$2,2),ROUND(Basisbedragen!$D$44*Basisbedragen!$I$2,2)),ROUND(ROUND(Basisbedragen!$D$32*0.6,4)*Basisbedragen!$I$2,2)) -> 68.63 | F15: =MIN(MAX(ROUND(ROUND('Loonschijven_Tranches salariale'!$Q14*0.6,4)*Basisbedragen!$I$2,2),ROUND(Basisbedragen!$D$45*Basisbedragen!$I$2,2)),ROUND(ROUND(Basisbedragen!$D$32*0.6,4)*Basisbedragen!$I$2,2)) -> 55.63 | G15: =MIN(MAX(ROUND(ROUND('Loonschijven_Tranches salariale'!$Q14*0.6,4)*Basisbedragen!$I$2,2),ROUND(Basisbedragen!$D$46*Basisbedragen!$I$2,2)),ROUND(ROUND(Basisbedragen!$D$32*0.6,4)*Basisbedragen!$I$2,2)) -> 49.43 | I15: =MIN(MAX(ROUND(ROUND('Loonschijven_Tranches salariale'!$Q14*0.6,4)*Basisbedragen!$I$2,2),ROUND(Basisbedragen!$D$77*Basisbedragen!$I$2,2)),ROUND(ROUND(Basisbedragen!$D$29*0.6,4)*Basisbedragen!$I$2,2)) -> 73.98 | J15: =MIN(MAX(ROUND(ROUND('Loonschijven_Tranches salariale'!$Q14*0.6,4)*Basisbedragen!$I$2,2),ROUND(Basisbedragen!$D$78*Basisbedragen!$I$2,2)),ROUND(ROUND(Basisbedragen!$D$29*0.6,4)*Basisbedragen!$I$2,2)) -> 65.17 | L15: =ROUND(M15*1.2,2) -> 42.6 | M15: =ROUND(MIN(MAX(ROUND(ROUND('Loonschijven_Tranches salariale'!$Q14*0.6,4)*Basisbedragen!$I$2,2),ROUND(Basisbedragen!$D$47*Basisbedragen!$I$2,2)),ROUND(ROUND(Basisbedragen!$D$30*0.6,4)*Basisbedragen!$I$2,2))/2,2) -> 35.5 | O15: =ROUND(E15/2,2) -> 34.32 | P15: =ROUND(F15/2,2) -> 27.82 | Q15: =ROUND(G15/2,2) -> 24.72
A16: =A15+1 -> 8 | B16: =ROUND(C16*1.2,2) -> 85.19 | C16: =IF(MIN(MAX(ROUND(ROUND('Loonschijven_Tranches salariale'!$Q15*0.6,4)*Basisbedragen!$I$7,2),ROUND(Basisbedragen!$D$47*Basisbedragen!$I$7,2)),ROUND(ROUND(Basisbedragen!$D$30*0.6,4)*Basisbedragen!$I$7,2))<= Basisbedragen!$I$8,MIN(MAX(ROUND(ROUND('Loonschijven_Tranches salariale'!$Q15*0.6,4)*Basisbedragen!$I$2,2),ROUND(Basisbedragen!$D$47*Basisbedragen!$I$2,2)),ROUND(ROUND(Basisbedragen!$D$30*0.6,4)*Basisbedragen!$I$2,2)),MIN(MAX(ROUND(ROUND('Loonschijven_Tranches salariale'!$Q15*0.6,4)*Basisbedragen!$I$7,2),ROUND(Basisbedragen!$D$47*Basisbedragen!$I$7,2)),ROUND(ROUND(Basisbedragen!$D$30*0.6,4)*Basisbedragen!$I$7,2))+Basisbedragen!$I$10) -> 70.99 | E16: =MIN(MAX(ROUND(ROUND('Loonschijven_Tranches salariale'!$Q15*0.6,4)*Basisbedragen!$I$2,2),ROUND(Basisbedragen!$D$44*Basisbedragen!$I$2,2)),ROUND(ROUND(Basisbedragen!$D$32*0.6,4)*Basisbedragen!$I$2,2)) -> 68.63 | F16: =MIN(MAX(ROUND(ROUND('Loonschijven_Tranches salariale'!$Q15*0.6,4)*Basisbedragen!$I$2,2),ROUND(Basisbedragen!$D$45*Basisbedragen!$I$2,2)),ROUND(ROUND(Basisbedragen!$D$32*0.6,4)*Basisbedragen!$I$2,2)) -> 55.63 | G16: =MIN(MAX(ROUND(ROUND('Loonschijven_Tranches salariale'!$Q15*0.6,4)*Basisbedragen!$I$2,2),ROUND(Basisbedragen!$D$46*Basisbedragen!$I$2,2)),ROUND(ROUND(Basisbedragen!$D$32*0.6,4)*Basisbedragen!$I$2,2)) -> 49.43 | I16: =MIN(MAX(ROUND(ROUND('Loonschijven_Tranches salariale'!$Q15*0.6,4)*Basisbedragen!$I$2,2),ROUND(Basisbedragen!$D$77*Basisbedragen!$I$2,2)),ROUND(ROUND(Basisbedragen!$D$29*0.6,4)*Basisbedragen!$I$2,2)) -> 73.98 | J16: =MIN(MAX(ROUND(ROUND('Loonschijven_Tranches salariale'!$Q15*0.6,4)*Basisbedragen!$I$2,2),ROUND(Basisbedragen!$D$78*Basisbedragen!$I$2,2)),ROUND(ROUND(Basisbedragen!$D$29*0.6,4)*Basisbedragen!$I$2,2)) -> 65.17 | L16: =ROUND(M16*1.2,2) -> 42.6 | M16: =ROUND(MIN(MAX(ROUND(ROUND('Loonschijven_Tranches salariale'!$Q15*0.6,4)*Basisbedragen!$I$2,2),ROUND(Basisbedragen!$D$47*Basisbedragen!$I$2,2)),ROUND(ROUND(Basisbedragen!$D$30*0.6,4)*Basisbedragen!$I$2,2))/2,2) -> 35.5 | O16: =ROUND(E16/2,2) -> 34.32 | P16: =ROUND(F16/2,2) -> 27.82 | Q16: =ROUND(G16/2,2) -> 24.72
A17: =A16+1 -> 9 | B17: =ROUND(C17*1.2,2) -> 85.19 | C17: =IF(MIN(MAX(ROUND(ROUND('Loonschijven_Tranches salariale'!$Q16*0.6,4)*Basisbedragen!$I$7,2),ROUND(Basisbedragen!$D$47*Basisbedragen!$I$7,2)),ROUND(ROUND(Basisbedragen!$D$30*0.6,4)*Basisbedragen!$I$7,2))<= Basisbedragen!$I$8,MIN(MAX(ROUND(ROUND('Loonschijven_Tranches salariale'!$Q16*0.6,4)*Basisbedragen!$I$2,2),ROUND(Basisbedragen!$D$47*Basisbedragen!$I$2,2)),ROUND(ROUND(Basisbedragen!$D$30*0.6,4)*Basisbedragen!$I$2,2)),MIN(MAX(ROUND(ROUND('Loonschijven_Tranches salariale'!$Q16*0.6,4)*Basisbedragen!$I$7,2),ROUND(Basisbedragen!$D$47*Basisbedragen!$I$7,2)),ROUND(ROUND(Basisbedragen!$D$30*0.6,4)*Basisbedragen!$I$7,2))+Basisbedragen!$I$10) -> 70.99 | E17: =MIN(MAX(ROUND(ROUND('Loonschijven_Tranches salariale'!$Q16*0.6,4)*Basisbedragen!$I$2,2),ROUND(Basisbedragen!$D$44*Basisbedragen!$I$2,2)),ROUND(ROUND(Basisbedragen!$D$32*0.6,4)*Basisbedragen!$I$2,2)) -> 68.63 | F17: =MIN(MAX(ROUND(ROUND('Loonschijven_Tranches salariale'!$Q16*0.6,4)*Basisbedragen!$I$2,2),ROUND(Basisbedragen!$D$45*Basisbedragen!$I$2,2)),ROUND(ROUND(Basisbedragen!$D$32*0.6,4)*Basisbedragen!$I$2,2)) -> 55.63 | G17: =MIN(MAX(ROUND(ROUND('Loonschijven_Tranches salariale'!$Q16*0.6,4)*Basisbedragen!$I$2,2),ROUND(Basisbedragen!$D$46*Basisbedragen!$I$2,2)),ROUND(ROUND(Basisbedragen!$D$32*0.6,4)*Basisbedragen!$I$2,2)) -> 49.43 | I17: =MIN(MAX(ROUND(ROUND('Loonschijven_Tranches salariale'!$Q16*0.6,4)*Basisbedragen!$I$2,2),ROUND(Basisbedragen!$D$77*Basisbedragen!$I$2,2)),ROUND(ROUND(Basisbedragen!$D$29*0.6,4)*Basisbedragen!$I$2,2)) -> 73.98 | J17: =MIN(MAX(ROUND(ROUND('Loonschijven_Tranches salariale'!$Q16*0.6,4)*Basisbedragen!$I$2,2),ROUND(Basisbedragen!$D$78*Basisbedragen!$I$2,2)),ROUND(ROUND(Basisbedragen!$D$29*0.6,4)*Basisbedragen!$I$2,2)) -> 65.17 | L17: =ROUND(M17*1.2,2) -> 42.6 | M17: =ROUND(MIN(MAX(ROUND(ROUND('Loonschijven_Tranches salariale'!$Q16*0.6,4)*Basisbedragen!$I$2,2),ROUND(Basisbedragen!$D$47*Basisbedragen!$I$2,2)),ROUND(ROUND(Basisbedragen!$D$30*0.6,4)*Basisbedragen!$I$2,2))/2,2) -> 35.5 | O17: =ROUND(E17/2,2) -> 34.32 | P17: =ROUND(F17/2,2) -> 27.82 | Q17: =ROUND(G17/2,2) -> 24.72
A18: =A17+1 -> 10 | B18: =ROUND(C18*1.2,2) -> 85.19 | C18: =IF(MIN(MAX(ROUND(ROUND('Loonschijven_Tranches salariale'!$Q17*0.6,4)*Basisbedragen!$I$7,2),ROUND(Basisbedragen!$D$47*Basisbedragen!$I$7,2)),ROUND(ROUND(Basisbedragen!$D$30*0.6,4)*Basisbedragen!$I$7,2))<= Basisbedragen!$I$8,MIN(MAX(ROUND(ROUND('Loonschijven_Tranches salariale'!$Q17*0.6,4)*Basisbedragen!$I$2,2),ROUND(Basisbedragen!$D$47*Basisbedragen!$I$2,2)),ROUND(ROUND(Basisbedragen!$D$30*0.6,4)*Basisbedragen!$I$2,2)),MIN(MAX(ROUND(ROUND('Loonschijven_Tranches salariale'!$Q17*0.6,4)*Basisbedragen!$I$7,2),ROUND(Basisbedragen!$D$47*Basisbedragen!$I$7,2)),ROUND(ROUND(Basisbedragen!$D$30*0.6,4)*Basisbedragen!$I$7,2))+Basisbedragen!$I$10) -> 70.99 | E18: =MIN(MAX(ROUND(ROUND('Loonschijven_Tranches salariale'!$Q17*0.6,4)*Basisbedragen!$I$2,2),ROUND(Basisbedragen!$D$44*Basisbedragen!$I$2,2)),ROUND(ROUND(Basisbedragen!$D$32*0.6,4)*Basisbedragen!$I$2,2)) -> 68.63 | F18: =MIN(MAX(ROUND(ROUND('Loonschijven_Tranches salariale'!$Q17*0.6,4)*Basisbedragen!$I$2,2),ROUND(Basisbedragen!$D$45*Basisbedragen!$I$2,2)),ROUND(ROUND(Basisbedragen!$D$32*0.6,4)*Basisbedragen!$I$2,2)) -> 55.63 | G18: =MIN(MAX(ROUND(ROUND('Loonschijven_Tranches salariale'!$Q17*0.6,4)*Basisbedragen!$I$2,2),ROUND(Basisbedragen!$D$46*Basisbedragen!$I$2,2)),ROUND(ROUND(Basisbedragen!$D$32*0.6,4)*Basisbedragen!$I$2,2)) -> 49.43 | I18: =MIN(MAX(ROUND(ROUND('Loonschijven_Tranches salariale'!$Q17*0.6,4)*Basisbedragen!$I$2,2),ROUND(Basisbedragen!$D$77*Basisbedragen!$I$2,2)),ROUND(ROUND(Basisbedragen!$D$29*0.6,4)*Basisbedragen!$I$2,2)) -> 73.98 | J18: =MIN(MAX(ROUND(ROUND('Loonschijven_Tranches salariale'!$Q17*0.6,4)*Basisbedragen!$I$2,2),ROUND(Basisbedragen!$D$78*Basisbedragen!$I$2,2)),ROUND(ROUND(Basisbedragen!$D$29*0.6,4)*Basisbedragen!$I$2,2)) -> 65.17 | L18: =ROUND(M18*1.2,2) -> 42.6 | M18: =ROUND(MIN(MAX(ROUND(ROUND('Loonschijven_Tranches salariale'!$Q17*0.6,4)*Basisbedragen!$I$2,2),ROUND(Basisbedragen!$D$47*Basisbedragen!$I$2,2)),ROUND(ROUND(Basisbedragen!$D$30*0.6,4)*Basisbedragen!$I$2,2))/2,2) -> 35.5 | O18: =ROUND(E18/2,2) -> 34.32 | P18: =ROUND(F18/2,2) -> 27.82 | Q18: =ROUND(G18/2,2) -> 24.72
A19: =A18+1 -> 11 | B19: =ROUND(C19*1.2,2) -> 85.19 | C19: =IF(MIN(MAX(ROUND(ROUND('Loonschijven_Tranches salariale'!$Q18*0.6,4)*Basisbedragen!$I$7,2),ROUND(Basisbedragen!$D$47*Basisbedragen!$I$7,2)),ROUND(ROUND(Basisbedragen!$D$30*0.6,4)*Basisbedragen!$I$7,2))<= Basisbedragen!$I$8,MIN(MAX(ROUND(ROUND('Loonschijven_Tranches salariale'!$Q18*0.6,4)*Basisbedragen!$I$2,2),ROUND(Basisbedragen!$D$47*Basisbedragen!$I$2,2)),ROUND(ROUND(Basisbedragen!$D$30*0.6,4)*Basisbedragen!$I$2,2)),MIN(MAX(ROUND(ROUND('Loonschijven_Tranches salariale'!$Q18*0.6,4)*Basisbedragen!$I$7,2),ROUND(Basisbedragen!$D$47*Basisbedragen!$I$7,2)),ROUND(ROUND(Basisbedragen!$D$30*0.6,4)*Basisbedragen!$I$7,2))+Basisbedragen!$I$10) -> 70.99 | E19: =MIN(MAX(ROUND(ROUND('Loonschijven_Tranches salariale'!$Q18*0.6,4)*Basisbedragen!$I$2,2),ROUND(Basisbedragen!$D$44*Basisbedragen!$I$2,2)),ROUND(ROUND(Basisbedragen!$D$32*0.6,4)*Basisbedragen!$I$2,2)) -> 68.63 | F19: =MIN(MAX(ROUND(ROUND('Loonschijven_Tranches salariale'!$Q18*0.6,4)*Basisbedragen!$I$2,2),ROUND(Basisbedragen!$D$45*Basisbedragen!$I$2,2)),ROUND(ROUND(Basisbedragen!$D$32*0.6,4)*Basisbedragen!$I$2,2)) -> 55.63 | G19: =MIN(MAX(ROUND(ROUND('Loonschijven_Tranches salariale'!$Q18*0.6,4)*Basisbedragen!$I$2,2),ROUND(Basisbedragen!$D$46*Basisbedragen!$I$2,2)),ROUND(ROUND(Basisbedragen!$D$32*0.6,4)*Basisbedragen!$I$2,2)) -> 49.43 | I19: =MIN(MAX(ROUND(ROUND('Loonschijven_Tranches salariale'!$Q18*0.6,4)*Basisbedragen!$I$2,2),ROUND(Basisbedragen!$D$77*Basisbedragen!$I$2,2)),ROUND(ROUND(Basisbedragen!$D$29*0.6,4)*Basisbedragen!$I$2,2)) -> 73.98 | J19: =MIN(MAX(ROUND(ROUND('Loonschijven_Tranches salariale'!$Q18*0.6,4)*Basisbedragen!$I$2,2),ROUND(Basisbedragen!$D$78*Basisbedragen!$I$2,2)),ROUND(ROUND(Basisbedragen!$D$29*0.6,4)*Basisbedragen!$I$2,2)) -> 65.17 | L19: =ROUND(M19*1.2,2) -> 42.6 | M19: =ROUND(MIN(MAX(ROUND(ROUND('Loonschijven_Tranches salariale'!$Q18*0.6,4)*Basisbedragen!$I$2,2),ROUND(Basisbedragen!$D$47*Basisbedragen!$I$2,2)),ROUND(ROUND(Basisbedragen!$D$30*0.6,4)*Basisbedragen!$I$2,2))/2,2) -> 35.5 | O19: =ROUND(E19/2,2) -> 34.32 | P19: =ROUND(F19/2,2) -> 27.82 | Q19: =ROUND(G19/2,2) -> 24.72
A20: =A19+1 -> 12 | B20: =ROUND(C20*1.2,2) -> 85.19 | C20: =IF(MIN(MAX(ROUND(ROUND('Loonschijven_Tranches salariale'!$Q19*0.6,4)*Basisbedragen!$I$7,2),ROUND(Basisbedragen!$D$47*Basisbedragen!$I$7,2)),ROUND(ROUND(Basisbedragen!$D$30*0.6,4)*Basisbedragen!$I$7,2))<= Basisbedragen!$I$8,MIN(MAX(ROUND(ROUND('Loonschijven_Tranches salariale'!$Q19*0.6,4)*Basisbedragen!$I$2,2),ROUND(Basisbedragen!$D$47*Basisbedragen!$I$2,2)),ROUND(ROUND(Basisbedragen!$D$30*0.6,4)*Basisbedragen!$I$2,2)),MIN(MAX(ROUND(ROUND('Loonschijven_Tranches salariale'!$Q19*0.6,4)*Basisbedragen!$I$7,2),ROUND(Basisbedragen!$D$47*Basisbedragen!$I$7,2)),ROUND(ROUND(Basisbedragen!$D$30*0.6,4)*Basisbedragen!$I$7,2))+Basisbedragen!$I$10) -> 70.99 | E20: =MIN(MAX(ROUND(ROUND('Loonschijven_Tranches salariale'!$Q19*0.6,4)*Basisbedragen!$I$2,2),ROUND(Basisbedragen!$D$44*Basisbedragen!$I$2,2)),ROUND(ROUND(Basisbedragen!$D$32*0.6,4)*Basisbedragen!$I$2,2)) -> 68.63 | F20: =MIN(MAX(ROUND(ROUND('Loonschijven_Tranches salariale'!$Q19*0.6,4)*Basisbedragen!$I$2,2),ROUND(Basisbedragen!$D$45*Basisbedragen!$I$2,2)),ROUND(ROUND(Basisbedragen!$D$32*0.6,4)*Basisbedragen!$I$2,2)) -> 55.63 | G20: =MIN(MAX(ROUND(ROUND('Loonschijven_Tranches salariale'!$Q19*0.6,4)*Basisbedragen!$I$2,2),ROUND(Basisbedragen!$D$46*Basisbedragen!$I$2,2)),ROUND(ROUND(Basisbedragen!$D$32*0.6,4)*Basisbedragen!$I$2,2)) -> 49.43 | I20: =MIN(MAX(ROUND(ROUND('Loonschijven_Tranches salariale'!$Q19*0.6,4)*Basisbedragen!$I$2,2),ROUND(Basisbedragen!$D$77*Basisbedragen!$I$2,2)),ROUND(ROUND(Basisbedragen!$D$29*0.6,4)*Basisbedragen!$I$2,2)) -> 73.98 | J20: =MIN(MAX(ROUND(ROUND('Loonschijven_Tranches salariale'!$Q19*0.6,4)*Basisbedragen!$I$2,2),ROUND(Basisbedragen!$D$78*Basisbedragen!$I$2,2)),ROUND(ROUND(Basisbedragen!$D$29*0.6,4)*Basisbedragen!$I$2,2)) -> 65.17 | L20: =ROUND(M20*1.2,2) -> 42.6 | M20: =ROUND(MIN(MAX(ROUND(ROUND('Loonschijven_Tranches salariale'!$Q19*0.6,4)*Basisbedragen!$I$2,2),ROUND(Basisbedragen!$D$47*Basisbedragen!$I$2,2)),ROUND(ROUND(Basisbedragen!$D$30*0.6,4)*Basisbedragen!$I$2,2))/2,2) -> 35.5 | O20: =ROUND(E20/2,2) -> 34.32 | P20: =ROUND(F20/2,2) -> 27.82 | Q20: =ROUND(G20/2,2) -> 24.72
A21: =A20+1 -> 13 | B21: =ROUND(C21*1.2,2) -> 85.19 | C21: =IF(MIN(MAX(ROUND(ROUND('Loonschijven_Tranches salariale'!$Q20*0.6,4)*Basisbedragen!$I$7,2),ROUND(Basisbedragen!$D$47*Basisbedragen!$I$7,2)),ROUND(ROUND(Basisbedragen!$D$30*0.6,4)*Basisbedragen!$I$7,2))<= Basisbedragen!$I$8,MIN(MAX(ROUND(ROUND('Loonschijven_Tranches salariale'!$Q20*0.6,4)*Basisbedragen!$I$2,2),ROUND(Basisbedragen!$D$47*Basisbedragen!$I$2,2)),ROUND(ROUND(Basisbedragen!$D$30*0.6,4)*Basisbedragen!$I$2,2)),MIN(MAX(ROUND(ROUND('Loonschijven_Tranches salariale'!$Q20*0.6,4)*Basisbedragen!$I$7,2),ROUND(Basisbedragen!$D$47*Basisbedragen!$I$7,2)),ROUND(ROUND(Basisbedragen!$D$30*0.6,4)*Basisbedragen!$I$7,2))+Basisbedragen!$I$10) -> 70.99 | E21: =MIN(MAX(ROUND(ROUND('Loonschijven_Tranches salariale'!$Q20*0.6,4)*Basisbedragen!$I$2,2),ROUND(Basisbedragen!$D$44*Basisbedragen!$I$2,2)),ROUND(ROUND(Basisbedragen!$D$32*0.6,4)*Basisbedragen!$I$2,2)) -> 68.63 | F21: =MIN(MAX(ROUND(ROUND('Loonschijven_Tranches salariale'!$Q20*0.6,4)*Basisbedragen!$I$2,2),ROUND(Basisbedragen!$D$45*Basisbedragen!$I$2,2)),ROUND(ROUND(Basisbedragen!$D$32*0.6,4)*Basisbedragen!$I$2,2)) -> 55.63 | G21: =MIN(MAX(ROUND(ROUND('Loonschijven_Tranches salariale'!$Q20*0.6,4)*Basisbedragen!$I$2,2),ROUND(Basisbedragen!$D$46*Basisbedragen!$I$2,2)),ROUND(ROUND(Basisbedragen!$D$32*0.6,4)*Basisbedragen!$I$2,2)) -> 49.43 | I21: =MIN(MAX(ROUND(ROUND('Loonschijven_Tranches salariale'!$Q20*0.6,4)*Basisbedragen!$I$2,2),ROUND(Basisbedragen!$D$77*Basisbedragen!$I$2,2)),ROUND(ROUND(Basisbedragen!$D$29*0.6,4)*Basisbedragen!$I$2,2)) -> 73.98 | J21: =MIN(MAX(ROUND(ROUND('Loonschijven_Tranches salariale'!$Q20*0.6,4)*Basisbedragen!$I$2,2),ROUND(Basisbedragen!$D$78*Basisbedragen!$I$2,2)),ROUND(ROUND(Basisbedragen!$D$29*0.6,4)*Basisbedragen!$I$2,2)) -> 65.17 | L21: =ROUND(M21*1.2,2) -> 42.6 | M21: =ROUND(MIN(MAX(ROUND(ROUND('Loonschijven_Tranches salariale'!$Q20*0.6,4)*Basisbedragen!$I$2,2),ROUND(Basisbedragen!$D$47*Basisbedragen!$I$2,2)),ROUND(ROUND(Basisbedragen!$D$30*0.6,4)*Basisbedragen!$I$2,2))/2,2) -> 35.5 | O21: =ROUND(E21/2,2) -> 34.32 | P21: =ROUND(F21/2,2) -> 27.82 | Q21: =ROUND(G21/2,2) -> 24.72
... A71: =A70+1 -> 63 | B71: =ROUND(C71*1.2,2) -> 85.19 | C71: =IF(MIN(MAX(ROUND(ROUND('Loonschijven_Tranches salariale'!$Q70*0.6,4)*Basisbedragen!$I$7,2),ROUND(Basisbedragen!$D$47*Basisbedragen!$I$7,2)),ROUND(ROUND(Basisbedragen!$D$30*0.6,4)*Basisbedragen!$I$7,2))<= Basisbedragen!$I$8,MIN(MAX(ROUND(ROUND('Loonschijven_Tranches salariale'!$Q70*0.6,4)*Basisbedragen!$I$2,2),ROUND(Basisbedragen!$D$47*Basisbedragen!$I$2,2)),ROUND(ROUND(Basisbedragen!$D$30*0.6,4)*Basisbedragen!$I$2,2)),MIN(MAX(ROUND(ROUND('Loonschijven_Tranches salariale'!$Q70*0.6,4)*Basisbedragen!$I$7,2),ROUND(Basisbedragen!$D$47*Basisbedragen!$I$7,2)),ROUND(ROUND(Basisbedragen!$D$30*0.6,4)*Basisbedragen!$I$7,2))+Basisbedragen!$I$10) -> 70.99 | E71: =MIN(MAX(ROUND(ROUND('Loonschijven_Tranches salariale'!$Q70*0.6,4)*Basisbedragen!$I$2,2),ROUND(Basisbedragen!$D$44*Basisbedragen!$I$2,2)),ROUND(ROUND(Basisbedragen!$D$32*0.6,4)*Basisbedragen!$I$2,2)) -> 69.09 | F71: =MIN(MAX(ROUND(ROUND('Loonschijven_Tranches salariale'!$Q70*0.6,4)*Basisbedragen!$I$2,2),ROUND(Basisbedragen!$D$45*Basisbedragen!$I$2,2)),ROUND(ROUND(Basisbedragen!$D$32*0.6,4)*Basisbedragen!$I$2,2)) -> 69.09 | G71: =MIN(MAX(ROUND(ROUND('Loonschijven_Tranches salariale'!$Q70*0.6,4)*Basisbedragen!$I$2,2),ROUND(Basisbedragen!$D$46*Basisbedragen!$I$2,2)),ROUND(ROUND(Basisbedragen!$D$32*0.6,4)*Basisbedragen!$I$2,2)) -> 69.09 | I71: =MIN(MAX(ROUND(ROUND('Loonschijven_Tranches salariale'!$Q70*0.6,4)*Basisbedragen!$I$2,2),ROUND(Basisbedragen!$D$77*Basisbedragen!$I$2,2)),ROUND(ROUND(Basisbedragen!$D$29*0.6,4)*Basisbedragen!$I$2,2)) -> 73.98 | J71: =MIN(MAX(ROUND(ROUND('Loonschijven_Tranches salariale'!$Q70*0.6,4)*Basisbedragen!$I$2,2),ROUND(Basisbedragen!$D$78*Basisbedragen!$I$2,2)),ROUND(ROUND(Basisbedragen!$D$29*0.6,4)*Basisbedragen!$I$2,2)) -> 69.42 | L71: =ROUND(M71*1.2,2) -> 42.6 | M71: =ROUND(MIN(MAX(ROUND(ROUND('Loonschijven_Tranches salariale'!$Q70*0.6,4)*Basisbedragen!$I$2,2),ROUND(Basisbedragen!$D$47*Basisbedragen!$I$2,2)),ROUND(ROUND(Basisbedragen!$D$30*0.6,4)*Basisbedragen!$I$2,2))/2,2) -> 35.5 | O71: =ROUND(E71/2,2) -> 34.55 | P71: =ROUND(F71/2,2) -> 34.55 | Q71: =ROUND(G71/2,2) -> 34.55
A72: =A71+1 -> 64 | B72: =ROUND(C72*1.2,2) -> 85.19 | C72: =IF(MIN(MAX(ROUND(ROUND('Loonschijven_Tranches salariale'!$Q71*0.6,4)*Basisbedragen!$I$7,2),ROUND(Basisbedragen!$D$47*Basisbedragen!$I$7,2)),ROUND(ROUND(Basisbedragen!$D$30*0.6,4)*Basisbedragen!$I$7,2))<= Basisbedragen!$I$8,MIN(MAX(ROUND(ROUND('Loonschijven_Tranches salariale'!$Q71*0.6,4)*Basisbedragen!$I$2,2),ROUND(Basisbedragen!$D$47*Basisbedragen!$I$2,2)),ROUND(ROUND(Basisbedragen!$D$30*0.6,4)*Basisbedragen!$I$2,2)),MIN(MAX(ROUND(ROUND('Loonschijven_Tranches salariale'!$Q71*0.6,4)*Basisbedragen!$I$7,2),ROUND(Basisbedragen!$D$47*Basisbedragen!$I$7,2)),ROUND(ROUND(Basisbedragen!$D$30*0.6,4)*Basisbedragen!$I$7,2))+Basisbedragen!$I$10) -> 70.99 | I72: =MIN(MAX(ROUND(ROUND('Loonschijven_Tranches salariale'!$Q71*0.6,4)*Basisbedragen!$I$2,2),ROUND(Basisbedragen!$D$77*Basisbedragen!$I$2,2)),ROUND(ROUND(Basisbedragen!$D$29*0.6,4)*Basisbedragen!$I$2,2)) -> 73.98 | J72: =MIN(MAX(ROUND(ROUND('Loonschijven_Tranches salariale'!$Q71*0.6,4)*Basisbedragen!$I$2,2),ROUND(Basisbedragen!$D$78*Basisbedragen!$I$2,2)),ROUND(ROUND(Basisbedragen!$D$29*0.6,4)*Basisbedragen!$I$2,2)) -> 70.52 | L72: =ROUND(M72*1.2,2) -> 42.6 | M72: =ROUND(MIN(MAX(ROUND(ROUND('Loonschijven_Tranches salariale'!$Q71*0.6,4)*Basisbedragen!$I$2,2),ROUND(Basisbedragen!$D$47*Basisbedragen!$I$2,2)),ROUND(ROUND(Basisbedragen!$D$30*0.6,4)*Basisbedragen!$I$2,2))/2,2) -> 35.5
A73: =A72+1 -> 65 | B73: =ROUND(C73*1.2,2) -> 85.68 | C73: =IF(MIN(MAX(ROUND(ROUND('Loonschijven_Tranches salariale'!$Q72*0.6,4)*Basisbedragen!$I$7,2),ROUND(Basisbedragen!$D$47*Basisbedragen!$I$7,2)),ROUND(ROUND(Basisbedragen!$D$30*0.6,4)*Basisbedragen!$I$7,2))<= Basisbedragen!$I$8,MIN(MAX(ROUND(ROUND('Loonschijven_Tranches salariale'!$Q72*0.6,4)*Basisbedragen!$I$2,2),ROUND(Basisbedragen!$D$47*Basisbedragen!$I$2,2)),ROUND(ROUND(Basisbedragen!$D$30*0.6,4)*Basisbedragen!$I$2,2)),MIN(MAX(ROUND(ROUND('Loonschijven_Tranches salariale'!$Q72*0.6,4)*Basisbedragen!$I$7,2),ROUND(Basisbedragen!$D$47*Basisbedragen!$I$7,2)),ROUND(ROUND(Basisbedragen!$D$30*0.6,4)*Basisbedragen!$I$7,2))+Basisbedragen!$I$10) -> 71.4 | I73: =MIN(MAX(ROUND(ROUND('Loonschijven_Tranches salariale'!$Q72*0.6,4)*Basisbedragen!$I$2,2),ROUND(Basisbedragen!$D$77*Basisbedragen!$I$2,2)),ROUND(ROUND(Basisbedragen!$D$29*0.6,4)*Basisbedragen!$I$2,2)) -> 73.98 | J73: =MIN(MAX(ROUND(ROUND('Loonschijven_Tranches salariale'!$Q72*0.6,4)*Basisbedragen!$I$2,2),ROUND(Basisbedragen!$D$78*Basisbedragen!$I$2,2)),ROUND(ROUND(Basisbedragen!$D$29*0.6,4)*Basisbedragen!$I$2,2)) -> 71.4 | L73: =ROUND(M73*1.2,2) -> 42.84 | M73: =ROUND(MIN(MAX(ROUND(ROUND('Loonschijven_Tranches salariale'!$Q72*0.6,4)*Basisbedragen!$I$2,2),ROUND(Basisbedragen!$D$47*Basisbedragen!$I$2,2)),ROUND(ROUND(Basisbedragen!$D$30*0.6,4)*Basisbedragen!$I$2,2))/2,2) -> 35.7
A74: =A73+1 -> 66 | B74: =ROUND(C74*1.2,2) -> 86.68 | C74: =IF(MIN(MAX(ROUND(ROUND('Loonschijven_Tranches salariale'!$Q73*0.6,4)*Basisbedragen!$I$7,2),ROUND(Basisbedragen!$D$47*Basisbedragen!$I$7,2)),ROUND(ROUND(Basisbedragen!$D$30*0.6,4)*Basisbedragen!$I$7,2))<= Basisbedragen!$I$8,MIN(MAX(ROUND(ROUND('Loonschijven_Tranches salariale'!$Q73*0.6,4)*Basisbedragen!$I$2,2),ROUND(Basisbedragen!$D$47*Basisbedragen!$I$2,2)),ROUND(ROUND(Basisbedragen!$D$30*0.6,4)*Basisbedragen!$I$2,2)),MIN(MAX(ROUND(ROUND('Loonschijven_Tranches salariale'!$Q73*0.6,4)*Basisbedragen!$I$7,2),ROUND(Basisbedragen!$D$47*Basisbedragen!$I$7,2)),ROUND(ROUND(Basisbedragen!$D$30*0.6,4)*Basisbedragen!$I$7,2))+Basisbedragen!$I$10) -> 72.23 | I74: =MIN(MAX(ROUND(ROUND('Loonschijven_Tranches salariale'!$Q73*0.6,4)*Basisbedragen!$I$2,2),ROUND(Basisbedragen!$D$77*Basisbedragen!$I$2,2)),ROUND(ROUND(Basisbedragen!$D$29*0.6,4)*Basisbedragen!$I$2,2)) -> 73.98 | J74: =MIN(MAX(ROUND(ROUND('Loonschijven_Tranches salariale'!$Q73*0.6,4)*Basisbedragen!$I$2,2),ROUND(Basisbedragen!$D$78*Basisbedragen!$I$2,2)),ROUND(ROUND(Basisbedragen!$D$29*0.6,4)*Basisbedragen!$I$2,2)) -> 72.23 | L74: =ROUND(M74*1.2,2) -> 43.34 | M74: =ROUND(MIN(MAX(ROUND(ROUND('Loonschijven_Tranches salariale'!$Q73*0.6,4)*Basisbedragen!$I$2,2),ROUND(Basisbedragen!$D$47*Basisbedragen!$I$2,2)),ROUND(ROUND(Basisbedragen!$D$30*0.6,4)*Basisbedragen!$I$2,2))/2,2) -> 36.12
A75: =A74+1 -> 67 | B75: =ROUND(C75*1.2,2) -> 87.8 | C75: =IF(MIN(MAX(ROUND(ROUND('Loonschijven_Tranches salariale'!$Q74*0.6,4)*Basisbedragen!$I$7,2),ROUND(Basisbedragen!$D$47*Basisbedragen!$I$7,2)),ROUND(ROUND(Basisbedragen!$D$30*0.6,4)*Basisbedragen!$I$7,2))<= Basisbedragen!$I$8,MIN(MAX(ROUND(ROUND('Loonschijven_Tranches salariale'!$Q74*0.6,4)*Basisbedragen!$I$2,2),ROUND(Basisbedragen!$D$47*Basisbedragen!$I$2,2)),ROUND(ROUND(Basisbedragen!$D$30*0.6,4)*Basisbedragen!$I$2,2)),MIN(MAX(ROUND(ROUND('Loonschijven_Tranches salariale'!$Q74*0.6,4)*Basisbedragen!$I$7,2),ROUND(Basisbedragen!$D$47*Basisbedragen!$I$7,2)),ROUND(ROUND(Basisbedragen!$D$30*0.6,4)*Basisbedragen!$I$7,2))+Basisbedragen!$I$10) -> 73.17 | I75: =MIN(MAX(ROUND(ROUND('Loonschijven_Tranches salariale'!$Q74*0.6,4)*Basisbedragen!$I$2,2),ROUND(Basisbedragen!$D$77*Basisbedragen!$I$2,2)),ROUND(ROUND(Basisbedragen!$D$29*0.6,4)*Basisbedragen!$I$2,2)) -> 73.98 | J75: =MIN(MAX(ROUND(ROUND('Loonschijven_Tranches salariale'!$Q74*0.6,4)*Basisbedragen!$I$2,2),ROUND(Basisbedragen!$D$78*Basisbedragen!$I$2,2)),ROUND(ROUND(Basisbedragen!$D$29*0.6,4)*Basisbedragen!$I$2,2)) -> 73.17 | L75: =ROUND(M75*1.2,2) -> 43.91 | M75: =ROUND(MIN(MAX(ROUND(ROUND('Loonschijven_Tranches salariale'!$Q74*0.6,4)*Basisbedragen!$I$2,2),ROUND(Basisbedragen!$D$47*Basisbedragen!$I$2,2)),ROUND(ROUND(Basisbedragen!$D$30*0.6,4)*Basisbedragen!$I$2,2))/2,2) -> 36.59
A76: =A75+1 -> 68 | B76: =ROUND(C76*1.2,2) -> 88.93 | C76: =IF(MIN(MAX(ROUND(ROUND('Loonschijven_Tranches salariale'!$Q75*0.6,4)*Basisbedragen!$I$7,2),ROUND(Basisbedragen!$D$47*Basisbedragen!$I$7,2)),ROUND(ROUND(Basisbedragen!$D$30*0.6,4)*Basisbedragen!$I$7,2))<= Basisbedragen!$I$8,MIN(MAX(ROUND(ROUND('Loonschijven_Tranches salariale'!$Q75*0.6,4)*Basisbedragen!$I$2,2),ROUND(Basisbedragen!$D$47*Basisbedragen!$I$2,2)),ROUND(ROUND(Basisbedragen!$D$30*0.6,4)*Basisbedragen!$I$2,2)),MIN(MAX(ROUND(ROUND('Loonschijven_Tranches salariale'!$Q75*0.6,4)*Basisbedragen!$I$7,2),ROUND(Basisbedragen!$D$47*Basisbedragen!$I$7,2)),ROUND(ROUND(Basisbedragen!$D$30*0.6,4)*Basisbedragen!$I$7,2))+Basisbedragen!$I$10) -> 74.11 | I76: =MIN(MAX(ROUND(ROUND('Loonschijven_Tranches salariale'!$Q75*0.6,4)*Basisbedragen!$I$2,2),ROUND(Basisbedragen!$D$77*Basisbedragen!$I$2,2)),ROUND(ROUND(Basisbedragen!$D$29*0.6,4)*Basisbedragen!$I$2,2)) -> 74.11 | J76: =MIN(MAX(ROUND(ROUND('Loonschijven_Tranches salariale'!$Q75*0.6,4)*Basisbedragen!$I$2,2),ROUND(Basisbedragen!$D$78*Basisbedragen!$I$2,2)),ROUND(ROUND(Basisbedragen!$D$29*0.6,4)*Basisbedragen!$I$2,2)) -> 74.11 | L76: =ROUND(M76*1.2,2) -> 44.47 | M76: =ROUND(MIN(MAX(ROUND(ROUND('Loonschijven_Tranches salariale'!$Q75*0.6,4)*Basisbedragen!$I$2,2),ROUND(Basisbedragen!$D$47*Basisbedragen!$I$2,2)),ROUND(ROUND(Basisbedragen!$D$30*0.6,4)*Basisbedragen!$I$2,2))/2,2) -> 37.06
A77: =A76+1 -> 69 | B77: =ROUND(C77*1.2,2) -> 90.06 | C77: =IF(MIN(MAX(ROUND(ROUND('Loonschijven_Tranches salariale'!$Q76*0.6,4)*Basisbedragen!$I$7,2),ROUND(Basisbedragen!$D$47*Basisbedragen!$I$7,2)),ROUND(ROUND(Basisbedragen!$D$30*0.6,4)*Basisbedragen!$I$7,2))<= Basisbedragen!$I$8,MIN(MAX(ROUND(ROUND('Loonschijven_Tranches salariale'!$Q76*0.6,4)*Basisbedragen!$I$2,2),ROUND(Basisbedragen!$D$47*Basisbedragen!$I$2,2)),ROUND(ROUND(Basisbedragen!$D$30*0.6,4)*Basisbedragen!$I$2,2)),MIN(MAX(ROUND(ROUND('Loonschijven_Tranches salariale'!$Q76*0.6,4)*Basisbedragen!$I$7,2),ROUND(Basisbedragen!$D$47*Basisbedragen!$I$7,2)),ROUND(ROUND(Basisbedragen!$D$30*0.6,4)*Basisbedragen!$I$7,2))+Basisbedragen!$I$10) -> 75.05 | I77: =MIN(MAX(ROUND(ROUND('Loonschijven_Tranches salariale'!$Q76*0.6,4)*Basisbedragen!$I$2,2),ROUND(Basisbedragen!$D$77*Basisbedragen!$I$2,2)),ROUND(ROUND(Basisbedragen!$D$29*0.6,4)*Basisbedragen!$I$2,2)) -> 75.05 | J77: =MIN(MAX(ROUND(ROUND('Loonschijven_Tranches salariale'!$Q76*0.6,4)*Basisbedragen!$I$2,2),ROUND(Basisbedragen!$D$78*Basisbedragen!$I$2,2)),ROUND(ROUND(Basisbedragen!$D$29*0.6,4)*Basisbedragen!$I$2,2)) -> 75.05 | L77: =ROUND(M77*1.2,2) -> 45.04 | M77: =ROUND(MIN(MAX(ROUND(ROUND('Loonschijven_Tranches salariale'!$Q76*0.6,4)*Basisbedragen!$I$2,2),ROUND(Basisbedragen!$D$47*Basisbedragen!$I$2,2)),ROUND(ROUND(Basisbedragen!$D$30*0.6,4)*Basisbedragen!$I$2,2))/2,2) -> 37.53
A78: =A77+1 -> 70 | B78: =ROUND(C78*1.2,2) -> 90.79 | C78: =IF(MIN(MAX(ROUND(ROUND('Loonschijven_Tranches salariale'!$Q77*0.6,4)*Basisbedragen!$I$7,2),ROUND(Basisbedragen!$D$47*Basisbedragen!$I$7,2)),ROUND(ROUND(Basisbedragen!$D$30*0.6,4)*Basisbedragen!$I$7,2))<= Basisbedragen!$I$8,MIN(MAX(ROUND(ROUND('Loonschijven_Tranches salariale'!$Q77*0.6,4)*Basisbedragen!$I$2,2),ROUND(Basisbedragen!$D$47*Basisbedragen!$I$2,2)),ROUND(ROUND(Basisbedragen!$D$30*0.6,4)*Basisbedragen!$I$2,2)),MIN(MAX(ROUND(ROUND('Loonschijven_Tranches salariale'!$Q77*0.6,4)*Basisbedragen!$I$7,2),ROUND(Basisbedragen!$D$47*Basisbedragen!$I$7,2)),ROUND(ROUND(Basisbedragen!$D$30*0.6,4)*Basisbedragen!$I$7,2))+Basisbedragen!$I$10) -> 75.66 | I78: =MIN(MAX(ROUND(ROUND('Loonschijven_Tranches salariale'!$Q77*0.6,4)*Basisbedragen!$I$2,2),ROUND(Basisbedragen!$D$77*Basisbedragen!$I$2,2)),ROUND(ROUND(Basisbedragen!$D$29*0.6,4)*Basisbedragen!$I$2,2)) -> 75.66 | J78: =MIN(MAX(ROUND(ROUND('Loonschijven_Tranches salariale'!$Q77*0.6,4)*Basisbedragen!$I$2,2),ROUND(Basisbedragen!$D$78*Basisbedragen!$I$2,2)),ROUND(ROUND(Basisbedragen!$D$29*0.6,4)*Basisbedragen!$I$2,2)) -> 75.66 | L78: =ROUND(M78*1.2,2) -> 45.4 | M78: =ROUND(MIN(MAX(ROUND(ROUND('Loonschijven_Tranches salariale'!$Q77*0.6,4)*Basisbedragen!$I$2,2),ROUND(Basisbedragen!$D$47*Basisbedragen!$I$2,2)),ROUND(ROUND(Basisbedragen!$D$30*0.6,4)*Basisbedragen!$I$2,2))/2,2) -> 37.83
A79: =A78+1 -> 71 | B79: =ROUND(C79*1.2,2) -> 91.37 | C79: =IF(MIN(MAX(ROUND(ROUND('Loonschijven_Tranches salariale'!$Q78*0.6,4)*Basisbedragen!$I$7,2),ROUND(Basisbedragen!$D$47*Basisbedragen!$I$7,2)),ROUND(ROUND(Basisbedragen!$D$30*0.6,4)*Basisbedragen!$I$7,2))<= Basisbedragen!$I$8,MIN(MAX(ROUND(ROUND('Loonschijven_Tranches salariale'!$Q78*0.6,4)*Basisbedragen!$I$2,2),ROUND(Basisbedragen!$D$47*Basisbedragen!$I$2,2)),ROUND(ROUND(Basisbedragen!$D$30*0.6,4)*Basisbedragen!$I$2,2)),MIN(MAX(ROUND(ROUND('Loonschijven_Tranches salariale'!$Q78*0.6,4)*Basisbedragen!$I$7,2),ROUND(Basisbedragen!$D$47*Basisbedragen!$I$7,2)),ROUND(ROUND(Basisbedragen!$D$30*0.6,4)*Basisbedragen!$I$7,2))+Basisbedragen!$I$10) -> 76.14 | I79: =MIN(MAX(ROUND(ROUND('Loonschijven_Tranches salariale'!$Q78*0.6,4)*Basisbedragen!$I$2,2),ROUND(Basisbedragen!$D$77*Basisbedragen!$I$2,2)),ROUND(ROUND(Basisbedragen!$D$29*0.6,4)*Basisbedragen!$I$2,2)) -> 76.14 | J79: =MIN(MAX(ROUND(ROUND('Loonschijven_Tranches salariale'!$Q78*0.6,4)*Basisbedragen!$I$2,2),ROUND(Basisbedragen!$D$78*Basisbedragen!$I$2,2)),ROUND(ROUND(Basisbedragen!$D$29*0.6,4)*Basisbedragen!$I$2,2)) -> 76.14 | L79: =ROUND(M79*1.2,2) -> 45.68 | M79: =ROUND(MIN(MAX(ROUND(ROUND('Loonschijven_Tranches salariale'!$Q78*0.6,4)*Basisbedragen!$I$2,2),ROUND(Basisbedragen!$D$47*Basisbedragen!$I$2,2)),ROUND(ROUND(Basisbedragen!$D$30*0.6,4)*Basisbedragen!$I$2,2))/2,2) -> 38.07
A80: =A79+1 -> 72 | B80: =ROUND(C80*1.2,2) -> 91.93 | C80: =IF(MIN(MAX(ROUND(ROUND('Loonschijven_Tranches salariale'!$Q79*0.6,4)*Basisbedragen!$I$7,2),ROUND(Basisbedragen!$D$47*Basisbedragen!$I$7,2)),ROUND(ROUND(Basisbedragen!$D$30*0.6,4)*Basisbedragen!$I$7,2))<= Basisbedragen!$I$8,MIN(MAX(ROUND(ROUND('Loonschijven_Tranches salariale'!$Q79*0.6,4)*Basisbedragen!$I$2,2),ROUND(Basisbedragen!$D$47*Basisbedragen!$I$2,2)),ROUND(ROUND(Basisbedragen!$D$30*0.6,4)*Basisbedragen!$I$2,2)),MIN(MAX(ROUND(ROUND('Loonschijven_Tranches salariale'!$Q79*0.6,4)*Basisbedragen!$I$7,2),ROUND(Basisbedragen!$D$47*Basisbedragen!$I$7,2)),ROUND(ROUND(Basisbedragen!$D$30*0.6,4)*Basisbedragen!$I$7,2))+Basisbedragen!$I$10) -> 76.61 | I80: =MIN(MAX(ROUND(ROUND('Loonschijven_Tranches salariale'!$Q79*0.6,4)*Basisbedragen!$I$2,2),ROUND(Basisbedragen!$D$77*Basisbedragen!$I$2,2)),ROUND(ROUND(Basisbedragen!$D$29*0.6,4)*Basisbedragen!$I$2,2)) -> 76.61 | J80: =MIN(MAX(ROUND(ROUND('Loonschijven_Tranches salariale'!$Q79*0.6,4)*Basisbedragen!$I$2,2),ROUND(Basisbedragen!$D$78*Basisbedragen!$I$2,2)),ROUND(ROUND(Basisbedragen!$D$29*0.6,4)*Basisbedragen!$I$2,2)) -> 76.61 | L80: =ROUND(M80*1.2,2) -> 45.97 | M80: =ROUND(MIN(MAX(ROUND(ROUND('Loonschijven_Tranches salariale'!$Q79*0.6,4)*Basisbedragen!$I$2,2),ROUND(Basisbedragen!$D$47*Basisbedragen!$I$2,2)),ROUND(ROUND(Basisbedragen!$D$30*0.6,4)*Basisbedragen!$I$2,2))/2,2) -> 38.31
A81: =A80+1 -> 73 | B81: =ROUND(C81*1.2,2) -> 93.2 | C81: =IF(MIN(MAX(ROUND(ROUND('Loonschijven_Tranches salariale'!$Q80*0.6,4)*Basisbedragen!$I$7,2),ROUND(Basisbedragen!$D$47*Basisbedragen!$I$7,2)),ROUND(ROUND(Basisbedragen!$D$30*0.6,4)*Basisbedragen!$I$7,2))<= Basisbedragen!$I$8,MIN(MAX(ROUND(ROUND('Loonschijven_Tranches salariale'!$Q80*0.6,4)*Basisbedragen!$I$2,2),ROUND(Basisbedragen!$D$47*Basisbedragen!$I$2,2)),ROUND(ROUND(Basisbedragen!$D$30*0.6,4)*Basisbedragen!$I$2,2)),MIN(MAX(ROUND(ROUND('Loonschijven_Tranches salariale'!$Q80*0.6,4)*Basisbedragen!$I$7,2),ROUND(Basisbedragen!$D$47*Basisbedragen!$I$7,2)),ROUND(ROUND(Basisbedragen!$D$30*0.6,4)*Basisbedragen!$I$7,2))+Basisbedragen!$I$10) -> 77.67 | I81: =MIN(MAX(ROUND(ROUND('Loonschijven_Tranches salariale'!$Q80*0.6,4)*Basisbedragen!$I$2,2),ROUND(Basisbedragen!$D$77*Basisbedragen!$I$2,2)),ROUND(ROUND(Basisbedragen!$D$29*0.6,4)*Basisbedragen!$I$2,2)) -> 76.81 | J81: =MIN(MAX(ROUND(ROUND('Loonschijven_Tranches salariale'!$Q80*0.6,4)*Basisbedragen!$I$2,2),ROUND(Basisbedragen!$D$78*Basisbedragen!$I$2,2)),ROUND(ROUND(Basisbedragen!$D$29*0.6,4)*Basisbedragen!$I$2,2)) -> 76.81 | L81: =ROUND(M81*1.2,2) -> 46.61 | M81: =ROUND(MIN(MAX(ROUND(ROUND('Loonschijven_Tranches salariale'!$Q80*0.6,4)*Basisbedragen!$I$2,2),ROUND(Basisbedragen!$D$47*Basisbedragen!$I$2,2)),ROUND(ROUND(Basisbedragen!$D$30*0.6,4)*Basisbedragen!$I$2,2))/2,2) -> 38.84
A82: =A81+1 -> 74 | B82: =ROUND(C82*1.2,2) -> 93.77 | C82: =IF(MIN(MAX(ROUND(ROUND('Loonschijven_Tranches salariale'!$Q81*0.6,4)*Basisbedragen!$I$7,2),ROUND(Basisbedragen!$D$47*Basisbedragen!$I$7,2)),ROUND(ROUND(Basisbedragen!$D$30*0.6,4)*Basisbedragen!$I$7,2))<= Basisbedragen!$I$8,MIN(MAX(ROUND(ROUND('Loonschijven_Tranches salariale'!$Q81*0.6,4)*Basisbedragen!$I$2,2),ROUND(Basisbedragen!$D$47*Basisbedragen!$I$2,2)),ROUND(ROUND(Basisbedragen!$D$30*0.6,4)*Basisbedragen!$I$2,2)),MIN(MAX(ROUND(ROUND('Loonschijven_Tranches salariale'!$Q81*0.6,4)*Basisbedragen!$I$7,2),ROUND(Basisbedragen!$D$47*Basisbedragen!$I$7,2)),ROUND(ROUND(Basisbedragen!$D$30*0.6,4)*Basisbedragen!$I$7,2))+Basisbedragen!$I$10) -> 78.14 | I82: =MIN(MAX(ROUND(ROUND('Loonschijven_Tranches salariale'!$Q81*0.6,4)*Basisbedragen!$I$2,2),ROUND(Basisbedragen!$D$77*Basisbedragen!$I$2,2)),ROUND(ROUND(Basisbedragen!$D$29*0.6,4)*Basisbedragen!$I$2,2)) -> 76.81 | J82: =MIN(MAX(ROUND(ROUND('Loonschijven_Tranches salariale'!$Q81*0.6,4)*Basisbedragen!$I$2,2),ROUND(Basisbedragen!$D$78*Basisbedragen!$I$2,2)),ROUND(ROUND(Basisbedragen!$D$29*0.6,4)*Basisbedragen!$I$2,2)) -> 76.81 | L82: =ROUND(M82*1.2,2) -> 46.88 | M82: =ROUND(MIN(MAX(ROUND(ROUND('Loonschijven_Tranches salariale'!$Q81*0.6,4)*Basisbedragen!$I$2,2),ROUND(Basisbedragen!$D$47*Basisbedragen!$I$2,2)),ROUND(ROUND(Basisbedragen!$D$30*0.6,4)*Basisbedragen!$I$2,2))/2,2) -> 39.07
A83: =A82+1 -> 75 | B83: =ROUND(C83*1.2,2) -> 94.92 | C83: =IF(MIN(MAX(ROUND(ROUND('Loonschijven_Tranches salariale'!$Q82*0.6,4)*Basisbedragen!$I$7,2),ROUND(Basisbedragen!$D$47*Basisbedragen!$I$7,2)),ROUND(ROUND(Basisbedragen!$D$30*0.6,4)*Basisbedragen!$I$7,2))<= Basisbedragen!$I$8,MIN(MAX(ROUND(ROUND('Loonschijven_Tranches salariale'!$Q82*0.6,4)*Basisbedragen!$I$2,2),ROUND(Basisbedragen!$D$47*Basisbedragen!$I$2,2)),ROUND(ROUND(Basisbedragen!$D$30*0.6,4)*Basisbedragen!$I$2,2)),MIN(MAX(ROUND(ROUND('Loonschijven_Tranches salariale'!$Q82*0.6,4)*Basisbedragen!$I$7,2),ROUND(Basisbedragen!$D$47*Basisbedragen!$I$7,2)),ROUND(ROUND(Basisbedragen!$D$30*0.6,4)*Basisbedragen!$I$7,2))+Basisbedragen!$I$10) -> 79.1 | I83: =MIN(MAX(ROUND(ROUND('Loonschijven_Tranches salariale'!$Q82*0.6,4)*Basisbedragen!$I$2,2),ROUND(Basisbedragen!$D$77*Basisbedragen!$I$2,2)),ROUND(ROUND(Basisbedragen!$D$29*0.6,4)*Basisbedragen!$I$2,2)) -> 76.81 | J83: =MIN(MAX(ROUND(ROUND('Loonschijven_Tranches salariale'!$Q82*0.6,4)*Basisbedragen!$I$2,2),ROUND(Basisbedragen!$D$78*Basisbedragen!$I$2,2)),ROUND(ROUND(Basisbedragen!$D$29*0.6,4)*Basisbedragen!$I$2,2)) -> 76.81 | L83: =ROUND(M83*1.2,2) -> 47.47 | M83: =ROUND(MIN(MAX(ROUND(ROUND('Loonschijven_Tranches salariale'!$Q82*0.6,4)*Basisbedragen!$I$2,2),ROUND(Basisbedragen!$D$47*Basisbedragen!$I$2,2)),ROUND(ROUND(Basisbedragen!$D$30*0.6,4)*Basisbedragen!$I$2,2))/2,2) -> 39.56
... A107: =A106+1 -> 99 | B107: =ROUND(C107*1.2,2) -> 98.8 | C107: =IF(MIN(MAX(ROUND(ROUND('Loonschijven_Tranches salariale'!$Q106*0.6,4)*Basisbedragen!$I$7,2),ROUND(Basisbedragen!$D$47*Basisbedragen!$I$7,2)),ROUND(ROUND(Basisbedragen!$D$30*0.6,4)*Basisbedragen!$I$7,2))<= Basisbedragen!$I$8,MIN(MAX(ROUND(ROUND('Loonschijven_Tranches salariale'!$Q106*0.6,4)*Basisbedragen!$I$2,2),ROUND(Basisbedragen!$D$47*Basisbedragen!$I$2,2)),ROUND(ROUND(Basisbedragen!$D$30*0.6,4)*Basisbedragen!$I$2,2)),MIN(MAX(ROUND(ROUND('Loonschijven_Tranches salariale'!$Q106*0.6,4)*Basisbedragen!$I$7,2),ROUND(Basisbedragen!$D$47*Basisbedragen!$I$7,2)),ROUND(ROUND(Basisbedragen!$D$30*0.6,4)*Basisbedragen!$I$7,2))+Basisbedragen!$I$10) -> 82.33 | I107: =MIN(MAX(ROUND(ROUND('Loonschijven_Tranches salariale'!$Q106*0.6,4)*Basisbedragen!$I$2,2),ROUND(Basisbedragen!$D$77*Basisbedragen!$I$2,2)),ROUND(ROUND(Basisbedragen!$D$29*0.6,4)*Basisbedragen!$I$2,2)) -> 76.81 | J107: =MIN(MAX(ROUND(ROUND('Loonschijven_Tranches salariale'!$Q106*0.6,4)*Basisbedragen!$I$2,2),ROUND(Basisbedragen!$D$78*Basisbedragen!$I$2,2)),ROUND(ROUND(Basisbedragen!$D$29*0.6,4)*Basisbedragen!$I$2,2)) -> 76.81 | L107: =ROUND(M107*1.2,2) -> 49.45 | M107: =ROUND(MIN(MAX(ROUND(ROUND('Loonschijven_Tranches salariale'!$Q106*0.6,4)*Basisbedragen!$I$2,2),ROUND(Basisbedragen!$D$47*Basisbedragen!$I$2,2)),ROUND(ROUND(Basisbedragen!$D$30*0.6,4)*Basisbedragen!$I$2,2))/2,2) -> 41.21

Sheet Loonschijven_Tranches salariale
A1: Geldig/valable | C1: Dagloon en cijfercode | H1: Multiplicat(o)(eu)r | K1: =Basisbedragen!$I$2 -> 1.8114
A2: 46266 | C2: Salaire journalier et code chiffré
B6: dagloon - salaire journalier
B7: =A2 -> 46266 | E7: code
N8: 1 | O8: =O9-0.8631 -> 10.7914 | P8: =O9-0.0001 -> 11.6544 | Q8: =O8+0.4316 -> 11.223
B9: =ROUND((O36*$K$1),4) -> 63.3233 | C9: =B10-0.0001 -> 64.8866 | E9: =29 -> 29 | N9: 2 | O9: =O10-0.8631 -> 11.6545 | P9: =O10-0.0001 -> 12.5175 | Q9: =O9+0.4316 -> 12.0861
B10: =ROUND((O37*$K$1),4) -> 64.8867 | C10: =B11-0.0001 -> 66.45 | E10: =E9+1 -> 30 | N10: 3 | O10: =O11-0.8631 -> 12.5176 | P10: =O11-0.0001 -> 13.3806 | Q10: =O10+0.4316 -> 12.9492
B11: =ROUND((O38*$K$1),4) -> 66.4501 | C11: =B12-0.0001 -> 68.0134 | E11: =E10+1 -> 31 | N11: 4 | O11: =O12-0.8631 -> 13.3807 | P11: =O12-0.0001 -> 14.2437 | Q11: =O11+0.4316 -> 13.8123
B12: =ROUND((O39*$K$1),4) -> 68.0135 | C12: =B13-0.0001 -> 69.5769 | E12: =E11+1 -> 32 | N12: 5 | O12: =O13-0.8631 -> 14.2438 | P12: =O13-0.0001 -> 15.1068 | Q12: =O12+0.4316 -> 14.6754
B13: =ROUND((O40*$K$1),4) -> 69.577 | C13: =B14-0.0001 -> 71.1403 | E13: =E12+1 -> 33 | N13: 6 | O13: =O14-0.8631 -> 15.1069 | P13: =O14-0.0001 -> 15.9699 | Q13: =O13+0.4316 -> 15.5385
B14: =ROUND((O41*$K$1),4) -> 71.1404 | C14: =B15-0.0001 -> 72.7037 | E14: =E13+1 -> 34 | N14: 7 | O14: =O15-0.8631 -> 15.97 | P14: =O15-0.0001 -> 16.833 | Q14: =O14+0.4316 -> 16.4016
B15: =ROUND((O42*$K$1),4) -> 72.7038 | C15: =B16-0.0001 -> 74.2671 | E15: =E14+1 -> 35 | N15: 8 | O15: =O16-0.8631 -> 16.8331 | P15: =O16-0.0001 -> 17.6961 | Q15: =O15+0.4316 -> 17.2647
B16: =ROUND((O43*$K$1),4) -> 74.2672 | C16: =B17-0.0001 -> 75.8305 | E16: =E15+1 -> 36 | N16: 9 | O16: =O17-0.8631 -> 17.6962 | P16: =O17-0.0001 -> 18.5592 | Q16: =O16+0.4316 -> 18.1278
B17: =ROUND((O44*$K$1),4) -> 75.8306 | C17: =B18-0.0001 -> 77.394 | E17: =E16+1 -> 37 | N17: 10 | O17: =O18-0.8631 -> 18.5593 | P17: =O18-0.0001 -> 19.4223 | Q17: =O17+0.4316 -> 18.9909
B18: =ROUND((O45*$K$1),4) -> 77.3941 | C18: =B19-0.0001 -> 78.9574 | E18: =E17+1 -> 38 | N18: 11 | O18: =O19-0.8631 -> 19.4224 | P18: =O19-0.0001 -> 20.2854 | Q18: =O18+0.4316 -> 19.854
B19: =ROUND((O46*$K$1),4) -> 78.9575 | C19: =B20-0.0001 -> 80.5208 | E19: =E18+1 -> 39 | N19: 12 | O19: =O20-0.8631 -> 20.2855 | P19: =O20-0.0001 -> 21.1485 | Q19: =O19+0.4316 -> 20.7171
B20: =ROUND((O47*$K$1),4) -> 80.5209 | C20: =B21-0.0001 -> 82.0842 | E20: =E19+1 -> 40 | N20: 13 | O20: =O21-0.8631 -> 21.1486 | P20: =O21-0.0001 -> 22.0116 | Q20: =O20+0.4316 -> 21.5802
B21: =ROUND((O48*$K$1),4) -> 82.0843 | C21: =B22-0.0001 -> 83.6476 | E21: =E20+1 -> 41 | N21: 14 | O21: =O22-0.8631 -> 22.0117 | P21: =O22-0.0001 -> 22.8747 | Q21: =O21+0.4316 -> 22.4433
... B60: =ROUND((O87*$K$1),4) -> 138.9163 | C60: =B61-0.0001 -> 140.4794 | E60: =E59+1 -> 80 | N60: 53 | O60: =O61-0.8631 -> 55.6726 | P60: =O61-0.0001 -> 56.5356 | Q60: =O60+0.4316 -> 56.1042
B61: =ROUND((O88*$K$1),4) -> 140.4795 | C61: =B62-0.0001 -> 142.0426 | E61: =E60+1 -> 81 | N61: 54 | O61: =O63-0.8631 -> 56.5357 | P61: =O62-0.0001 -> 56.9672 | Q61: =O61 -> 56.5357
B62: =ROUND((O89*$K$1),4) -> 142.0427 | C62: =B63-0.0001 -> 143.6059 | E62: =E61+1 -> 82 | N62: 55 | O62: =ROUND((O63-0.43155),4) -> 56.9673 | P62: =O63-0.0001 -> 57.3987 | Q62: =O62 -> 56.9673
B63: =ROUND((O90*$K$1),4) -> 143.606 | C63: =B64-0.0001 -> 145.1691 | E63: =E62+1 -> 83 | N63: 56 | O63: =O64-0.8631 -> 57.3988 | P63: =O64-0.0001 -> 58.2618 | Q63: =O63+0.4316 -> 57.8304
B64: =ROUND((O91*$K$1),4) -> 145.1692 | C64: =B65-0.0001 -> 146.7324 | E64: =E63+1 -> 84 | N64: 57 | O64: =O65-0.8631 -> 58.2619 | P64: =O65-0.0001 -> 59.1249 | Q64: =O64+0.4316 -> 58.6935
B65: =ROUND((O92*$K$1),4) -> 146.7325 | C65: =B66-0.0001 -> 148.2956 | E65: =E64+1 -> 85 | N65: 58 | O65: =O66-0.8631 -> 59.125 | P65: =O66-0.0001 -> 59.988 | Q65: =O65+0.4316 -> 59.5566
B66: =ROUND((O93*$K$1),4) -> 148.2957 | C66: =B67-0.0001 -> 149.8588 | E66: =E65+1 -> 86 | N66: 59 | O66: =O67-0.8631 -> 59.9881 | P66: =O67-0.0001 -> 60.8511 | Q66: 60.6334
B67: =ROUND((O94*$K$1),4) -> 149.8589 | C67: =B68-0.0001 -> 151.4221 | E67: =E66+1 -> 87 | N67: 60 | O67: =O68-0.8631 -> 60.8512 | P67: =O68-0.0001 -> 61.7142 | Q67: 61.3913
B68: =ROUND((O95*$K$1),4) -> 151.4222 | C68: =B69-0.0001 -> 152.9853 | E68: =E67+1 -> 88 | N68: 61 | O68: =O69-0.8631 -> 61.7143 | P68: =O69-0.0001 -> 62.5773 | Q68: =O68+0.4316 -> 62.1459
B69: =ROUND((O96*$K$1),4) -> 152.9854 | C69: =B70-0.0001 -> 154.5485 | E69: =E68+1 -> 89 | N69: 62 | O69: =O70-0.8631 -> 62.5774 | P69: =O70-0.0001 -> 63.4404 | Q69: =O69+0.4316 -> 63.009
B70: =ROUND((O97*$K$1),4) -> 154.5486 | C70: =B71-0.0001 -> 156.1118 | E70: =E69+1 -> 90 | N70: 63 | O70: =O71-0.8631 -> 63.4405 | P70: =O71-0.0001 -> 64.3035 | Q70: =O70+0.4316 -> 63.8721
B71: =ROUND((O98*$K$1),4) -> 156.1119 | C71: =B72-0.0001 -> 157.675 | E71: =E70+1 -> 91 | N71: 64 | O71: =O72-0.8631 -> 64.3036 | P71: =O72-0.0001 -> 65.1666 | Q71: 64.8848
B72: =ROUND((O99*$K$1),4) -> 157.6751 | C72: =B73-0.0001 -> 159.2383 | E72: =E71+1 -> 92 | N72: 65 | O72: =O73-0.8631 -> 65.1667 | P72: =O73-0.0001 -> 66.0297 | Q72: 65.6959
B73: =ROUND((O100*$K$1),4) -> 159.2384 | C73: =B74-0.0001 -> 160.8015 | E73: =E72+1 -> 93 | N73: 66 | O73: =O74-0.8631 -> 66.0298 | P73: =O74-0.0001 -> 66.8928 | Q73: =O73+0.4316 -> 66.4614
B74: =ROUND((O101*$K$1),4) -> 160.8016 | C74: =B75-0.0001 -> 162.3647 | E74: =E73+1 -> 94 | N74: 67 | O74: =O75-0.8631 -> 66.8929 | P74: =O75-0.0001 -> 67.7559 | Q74: =O74+0.4316 -> 67.3245
B75: =ROUND((O102*$K$1),4) -> 162.3648 | C75: =B76-0.0001 -> 163.928 | E75: =E74+1 -> 95 | N75: 68 | O75: =O76-0.8631 -> 67.756 | P75: =O76-0.0001 -> 68.619 | Q75: =O75+0.4316 -> 68.1876
B76: =ROUND((O103*$K$1),4) -> 163.9281 | C76: =B77-0.0001 -> 165.4912 | E76: =E75+1 -> 96 | N76: 69 | O76: =O77-0.8631 -> 68.6191 | P76: =O77-0.0001 -> 69.4821 | Q76: =O76+0.4316 -> 69.0507
B77: =ROUND((O104*$K$1),4) -> 165.4913 | C77: =B78-0.0001 -> 167.0545 | E77: =E76+1 -> 97 | N77: 70 | O77: =O78-0.1355 -> 69.4822 | P77: =O78-0.0001 -> 69.6176 | Q77: 69.6176
B78: =ROUND((O105*$K$1),4) -> 167.0546 | C78: =B79-0.0001 -> 167.3653 | E78: =E77+1 -> 98 | N78: 71 | O78: 69.6177 | P78: =O79-0.0001 -> 70.4877 | Q78: 70.0528
B79: =ROUND((O106*$K$1),4) -> 167.3654 | E79: =E78+1 -> 99 | N79: 72 | O79: 70.4878 | P79: 71.0344 | Q79: 70.4878
N80: 73 | O80: 71.0345 | P80: 71.8975 | Q80: 71.466
N81: 74 | O81: 71.8976 | P81: 72.7962 | Q81: 71.8976
N82: 75 | O82: 72.7963 | P82: 73.3786 | Q82: 72.7963
N83: 76 | O83: 73.3787 | P83: 74.1858 | Q83: 73.3787
N84: 77 | O84: 74.1859 | P84: 75.0019 | Q84: 74.1859
N85: 78 | O85: 75.002 | P85: 75.8269 | Q85: 75.002
N86: 79 | O86: 75.827 | P86: 76.6899 | Q86: 75.827
N87: 80 | O87: 76.69 | P87: 77.5529 | Q87: 76.69
N88: 81 | O88: 77.553 | P88: 78.4159 | Q88: 77.553
N89: 82 | O89: 78.416 | P89: 79.2789 | Q89: 78.416
N90: 83 | O90: 79.279 | P90: 80.1419 | Q90: 79.279
N91: 84 | O91: 80.142 | P91: 81.0049 | Q91: 80.142
... N105: 98 | O105: 92.224 | P105: 92.3955 | Q105: 92.224
N106: 99 | O106: 92.3956 | Q106: 92.3956

Sheet Uurlonen_Salaires horaires
A1: Geldig/valable | C1: Uurlonen | I1: Multiplicat(o)(eu)r | L1: =Basisbedragen!$I$2 -> 1.8114
A2: ='Loonschijven_Tranches salariale'!A2:B2 -> 46266 | C2: Salaires horaires
D6: =A2 -> 46266
A7: Q | C7: Code | D7: 40 | E7: 39.5 | F7: 39 | G7: 38.5 | H7: 38 | I7: 37.5 | J7: 37 | K7: 36.5 | L7: 36 | M7: 35.5 | N7: 35
C8: =29 -> 29 | D8: =ROUND('Loonschijven_Tranches salariale'!$B9*6/D$7+0.000049,4) -> 9.4985 | E8: =ROUND('Loonschijven_Tranches salariale'!$B9*6/E$7+0.000049,4) -> 9.6188 | F8: =ROUND('Loonschijven_Tranches salariale'!$B9*6/F$7+0.000049,4) -> 9.7421 | G8: =ROUND('Loonschijven_Tranches salariale'!$B9*6/G$7+0.000049,4) -> 9.8686 | H8: =ROUND('Loonschijven_Tranches salariale'!$B9*6/H$7+0.000049,4) -> 9.9985 | I8: =ROUND('Loonschijven_Tranches salariale'!$B9*6/I$7+0.000049,4) -> 10.1318 | J8: =ROUND('Loonschijven_Tranches salariale'!$B9*6/J$7+0.000049,4) -> 10.2687 | K8: =ROUND('Loonschijven_Tranches salariale'!$B9*6/K$7+0.000049,4) -> 10.4094 | ... N8: =ROUND('Loonschijven_Tranches salariale'!$B9*6/N$7+0.000049,4) -> 10.8555
C9: =C8+1 -> 30 | D9: =ROUND('Loonschijven_Tranches salariale'!$B10*6/D$7+0.000049,4) -> 9.7331 | E9: =ROUND('Loonschijven_Tranches salariale'!$B10*6/E$7+0.000049,4) -> 9.8563 | F9: =ROUND('Loonschijven_Tranches salariale'!$B10*6/F$7+0.000049,4) -> 9.9826 | G9: =ROUND('Loonschijven_Tranches salariale'!$B10*6/G$7+0.000049,4) -> 10.1123 | H9: =ROUND('Loonschijven_Tranches salariale'!$B10*6/H$7+0.000049,4) -> 10.2453 | I9: =ROUND('Loonschijven_Tranches salariale'!$B10*6/I$7+0.000049,4) -> 10.3819 | J9: =ROUND('Loonschijven_Tranches salariale'!$B10*6/J$7+0.000049,4) -> 10.5222 | K9: =ROUND('Loonschijven_Tranches salariale'!$B10*6/K$7+0.000049,4) -> 10.6664 | ... N9: =ROUND('Loonschijven_Tranches salariale'!$B10*6/N$7+0.000049,4) -> 11.1235
C10: =C9+1 -> 31 | D10: =ROUND('Loonschijven_Tranches salariale'!$B11*6/D$7+0.000049,4) -> 9.9676 | E10: =ROUND('Loonschijven_Tranches salariale'!$B11*6/E$7+0.000049,4) -> 10.0937 | F10: =ROUND('Loonschijven_Tranches salariale'!$B11*6/F$7+0.000049,4) -> 10.2231 | G10: =ROUND('Loonschijven_Tranches salariale'!$B11*6/G$7+0.000049,4) -> 10.3559 | H10: =ROUND('Loonschijven_Tranches salariale'!$B11*6/H$7+0.000049,4) -> 10.4922 | I10: =ROUND('Loonschijven_Tranches salariale'!$B11*6/I$7+0.000049,4) -> 10.6321 | J10: =ROUND('Loonschijven_Tranches salariale'!$B11*6/J$7+0.000049,4) -> 10.7757 | K10: =ROUND('Loonschijven_Tranches salariale'!$B11*6/K$7+0.000049,4) -> 10.9234 | ... N10: =ROUND('Loonschijven_Tranches salariale'!$B11*6/N$7+0.000049,4) -> 11.3915
C11: =C10+1 -> 32 | D11: =ROUND('Loonschijven_Tranches salariale'!$B12*6/D$7+0.000049,4) -> 10.2021 | E11: =ROUND('Loonschijven_Tranches salariale'!$B12*6/E$7+0.000049,4) -> 10.3312 | F11: =ROUND('Loonschijven_Tranches salariale'!$B12*6/F$7+0.000049,4) -> 10.4637 | G11: =ROUND('Loonschijven_Tranches salariale'!$B12*6/G$7+0.000049,4) -> 10.5996 | H11: =ROUND('Loonschijven_Tranches salariale'!$B12*6/H$7+0.000049,4) -> 10.739 | I11: =ROUND('Loonschijven_Tranches salariale'!$B12*6/I$7+0.000049,4) -> 10.8822 | J11: =ROUND('Loonschijven_Tranches salariale'!$B12*6/J$7+0.000049,4) -> 11.0293 | K11: =ROUND('Loonschijven_Tranches salariale'!$B12*6/K$7+0.000049,4) -> 11.1804 | ... N11: =ROUND('Loonschijven_Tranches salariale'!$B12*6/N$7+0.000049,4) -> 11.6595
C12: =C11+1 -> 33 | D12: =ROUND('Loonschijven_Tranches salariale'!$B13*6/D$7+0.000049,4) -> 10.4366 | E12: =ROUND('Loonschijven_Tranches salariale'!$B13*6/E$7+0.000049,4) -> 10.5687 | F12: =ROUND('Loonschijven_Tranches salariale'!$B13*6/F$7+0.000049,4) -> 10.7042 | G12: =ROUND('Loonschijven_Tranches salariale'!$B13*6/G$7+0.000049,4) -> 10.8432 | H12: =ROUND('Loonschijven_Tranches salariale'!$B13*6/H$7+0.000049,4) -> 10.9859 | I12: =ROUND('Loonschijven_Tranches salariale'!$B13*6/I$7+0.000049,4) -> 11.1324 | J12: =ROUND('Loonschijven_Tranches salariale'!$B13*6/J$7+0.000049,4) -> 11.2828 | K12: =ROUND('Loonschijven_Tranches salariale'!$B13*6/K$7+0.000049,4) -> 11.4374 | ... N12: =ROUND('Loonschijven_Tranches salariale'!$B13*6/N$7+0.000049,4) -> 11.9275
C13: =C12+1 -> 34 | D13: =ROUND('Loonschijven_Tranches salariale'!$B14*6/D$7+0.000049,4) -> 10.6711 | E13: =ROUND('Loonschijven_Tranches salariale'!$B14*6/E$7+0.000049,4) -> 10.8062 | F13: =ROUND('Loonschijven_Tranches salariale'!$B14*6/F$7+0.000049,4) -> 10.9447 | G13: =ROUND('Loonschijven_Tranches salariale'!$B14*6/G$7+0.000049,4) -> 11.0869 | H13: =ROUND('Loonschijven_Tranches salariale'!$B14*6/H$7+0.000049,4) -> 11.2327 | I13: =ROUND('Loonschijven_Tranches salariale'!$B14*6/I$7+0.000049,4) -> 11.3825 | J13: =ROUND('Loonschijven_Tranches salariale'!$B14*6/J$7+0.000049,4) -> 11.5363 | K13: =ROUND('Loonschijven_Tranches salariale'!$B14*6/K$7+0.000049,4) -> 11.6944 | ... N13: =ROUND('Loonschijven_Tranches salariale'!$B14*6/N$7+0.000049,4) -> 12.1955
C14: =C13+1 -> 35 | D14: =ROUND('Loonschijven_Tranches salariale'!$B15*6/D$7+0.000049,4) -> 10.9056 | E14: =ROUND('Loonschijven_Tranches salariale'!$B15*6/E$7+0.000049,4) -> 11.0437 | F14: =ROUND('Loonschijven_Tranches salariale'!$B15*6/F$7+0.000049,4) -> 11.1852 | G14: =ROUND('Loonschijven_Tranches salariale'!$B15*6/G$7+0.000049,4) -> 11.3305 | H14: =ROUND('Loonschijven_Tranches salariale'!$B15*6/H$7+0.000049,4) -> 11.4796 | I14: =ROUND('Loonschijven_Tranches salariale'!$B15*6/I$7+0.000049,4) -> 11.6327 | J14: =ROUND('Loonschijven_Tranches salariale'!$B15*6/J$7+0.000049,4) -> 11.7899 | K14: =ROUND('Loonschijven_Tranches salariale'!$B15*6/K$7+0.000049,4) -> 11.9514 | ... N14: =ROUND('Loonschijven_Tranches salariale'!$B15*6/N$7+0.000049,4) -> 12.4636
C15: =C14+1 -> 36 | D15: =ROUND('Loonschijven_Tranches salariale'!$B16*6/D$7+0.000049,4) -> 11.1401 | E15: =ROUND('Loonschijven_Tranches salariale'!$B16*6/E$7+0.000049,4) -> 11.2811 | F15: =ROUND('Loonschijven_Tranches salariale'!$B16*6/F$7+0.000049,4) -> 11.4258 | G15: =ROUND('Loonschijven_Tranches salariale'!$B16*6/G$7+0.000049,4) -> 11.5742 | H15: =ROUND('Loonschijven_Tranches salariale'!$B16*6/H$7+0.000049,4) -> 11.7264 | I15: =ROUND('Loonschijven_Tranches salariale'!$B16*6/I$7+0.000049,4) -> 11.8828 | J15: =ROUND('Loonschijven_Tranches salariale'!$B16*6/J$7+0.000049,4) -> 12.0434 | K15: =ROUND('Loonschijven_Tranches salariale'!$B16*6/K$7+0.000049,4) -> 12.2084 | ... N15: =ROUND('Loonschijven_Tranches salariale'!$B16*6/N$7+0.000049,4) -> 12.7316
C16: =C15+1 -> 37 | D16: =ROUND('Loonschijven_Tranches salariale'!$B17*6/D$7+0.000049,4) -> 11.3746 | E16: =ROUND('Loonschijven_Tranches salariale'!$B17*6/E$7+0.000049,4) -> 11.5186 | F16: =ROUND('Loonschijven_Tranches salariale'!$B17*6/F$7+0.000049,4) -> 11.6663 | G16: =ROUND('Loonschijven_Tranches salariale'!$B17*6/G$7+0.000049,4) -> 11.8178 | H16: =ROUND('Loonschijven_Tranches salariale'!$B17*6/H$7+0.000049,4) -> 11.9733 | I16: =ROUND('Loonschijven_Tranches salariale'!$B17*6/I$7+0.000049,4) -> 12.1329 | J16: =ROUND('Loonschijven_Tranches salariale'!$B17*6/J$7+0.000049,4) -> 12.2969 | K16: =ROUND('Loonschijven_Tranches salariale'!$B17*6/K$7+0.000049,4) -> 12.4654 | ... N16: =ROUND('Loonschijven_Tranches salariale'!$B17*6/N$7+0.000049,4) -> 12.9996
C17: =C16+1 -> 38 | D17: =ROUND('Loonschijven_Tranches salariale'!$B18*6/D$7+0.000049,4) -> 11.6092 | E17: =ROUND('Loonschijven_Tranches salariale'!$B18*6/E$7+0.000049,4) -> 11.7561 | F17: =ROUND('Loonschijven_Tranches salariale'!$B18*6/F$7+0.000049,4) -> 11.9068 | G17: =ROUND('Loonschijven_Tranches salariale'!$B18*6/G$7+0.000049,4) -> 12.0615 | H17: =ROUND('Loonschijven_Tranches salariale'!$B18*6/H$7+0.000049,4) -> 12.2202 | I17: =ROUND('Loonschijven_Tranches salariale'!$B18*6/I$7+0.000049,4) -> 12.3831 | J17: =ROUND('Loonschijven_Tranches salariale'!$B18*6/J$7+0.000049,4) -> 12.5504 | K17: =ROUND('Loonschijven_Tranches salariale'!$B18*6/K$7+0.000049,4) -> 12.7224 | ... N17: =ROUND('Loonschijven_Tranches salariale'!$B18*6/N$7+0.000049,4) -> 13.2676
C18: =C17+1 -> 39 | D18: =ROUND('Loonschijven_Tranches salariale'!$B19*6/D$7+0.000049,4) -> 11.8437 | E18: =ROUND('Loonschijven_Tranches salariale'!$B19*6/E$7+0.000049,4) -> 11.9936 | F18: =ROUND('Loonschijven_Tranches salariale'!$B19*6/F$7+0.000049,4) -> 12.1474 | G18: =ROUND('Loonschijven_Tranches salariale'!$B19*6/G$7+0.000049,4) -> 12.3051 | H18: =ROUND('Loonschijven_Tranches salariale'!$B19*6/H$7+0.000049,4) -> 12.467 | I18: =ROUND('Loonschijven_Tranches salariale'!$B19*6/I$7+0.000049,4) -> 12.6332 | J18: =ROUND('Loonschijven_Tranches salariale'!$B19*6/J$7+0.000049,4) -> 12.804 | K18: =ROUND('Loonschijven_Tranches salariale'!$B19*6/K$7+0.000049,4) -> 12.9794 | ... N18: =ROUND('Loonschijven_Tranches salariale'!$B19*6/N$7+0.000049,4) -> 13.5356
C19: =C18+1 -> 40 | D19: =ROUND('Loonschijven_Tranches salariale'!$B20*6/D$7+0.000049,4) -> 12.0782 | E19: =ROUND('Loonschijven_Tranches salariale'!$B20*6/E$7+0.000049,4) -> 12.2311 | F19: =ROUND('Loonschijven_Tranches salariale'!$B20*6/F$7+0.000049,4) -> 12.3879 | G19: =ROUND('Loonschijven_Tranches salariale'!$B20*6/G$7+0.000049,4) -> 12.5488 | H19: =ROUND('Loonschijven_Tranches salariale'!$B20*6/H$7+0.000049,4) -> 12.7139 | I19: =ROUND('Loonschijven_Tranches salariale'!$B20*6/I$7+0.000049,4) -> 12.8834 | J19: =ROUND('Loonschijven_Tranches salariale'!$B20*6/J$7+0.000049,4) -> 13.0575 | K19: =ROUND('Loonschijven_Tranches salariale'!$B20*6/K$7+0.000049,4) -> 13.2364 | ... N19: =ROUND('Loonschijven_Tranches salariale'!$B20*6/N$7+0.000049,4) -> 13.8036
C20: =C19+1 -> 41 | D20: =ROUND('Loonschijven_Tranches salariale'!$B21*6/D$7+0.000049,4) -> 12.3127 | E20: =ROUND('Loonschijven_Tranches salariale'!$B21*6/E$7+0.000049,4) -> 12.4686 | F20: =ROUND('Loonschijven_Tranches salariale'!$B21*6/F$7+0.000049,4) -> 12.6284 | G20: =ROUND('Loonschijven_Tranches salariale'!$B21*6/G$7+0.000049,4) -> 12.7924 | H20: =ROUND('Loonschijven_Tranches salariale'!$B21*6/H$7+0.000049,4) -> 12.9607 | I20: =ROUND('Loonschijven_Tranches salariale'!$B21*6/I$7+0.000049,4) -> 13.1335 | J20: =ROUND('Loonschijven_Tranches salariale'!$B21*6/J$7+0.000049,4) -> 13.311 | K20: =ROUND('Loonschijven_Tranches salariale'!$B21*6/K$7+0.000049,4) -> 13.4934 | ... N20: =ROUND('Loonschijven_Tranches salariale'!$B21*6/N$7+0.000049,4) -> 14.0716
... C38: =C37+1 -> 59 | D38: =ROUND('Loonschijven_Tranches salariale'!$B39*6/D$7+0.000049,4) -> 16.2994 | E38: =ROUND('Loonschijven_Tranches salariale'!$B39*6/E$7+0.000049,4) -> 16.5057 | F38: =ROUND('Loonschijven_Tranches salariale'!$B39*6/F$7+0.000049,4) -> 16.7173 | G38: =ROUND('Loonschijven_Tranches salariale'!$B39*6/G$7+0.000049,4) -> 16.9344 | H38: =ROUND('Loonschijven_Tranches salariale'!$B39*6/H$7+0.000049,4) -> 17.1573 | I38: =ROUND('Loonschijven_Tranches salariale'!$B39*6/I$7+0.000049,4) -> 17.386 | J38: =ROUND('Loonschijven_Tranches salariale'!$B39*6/J$7+0.000049,4) -> 17.621 | K38: =ROUND('Loonschijven_Tranches salariale'!$B39*6/K$7+0.000049,4) -> 17.8624 | ... N38: =ROUND('Loonschijven_Tranches salariale'!$B39*6/N$7+0.000049,4) -> 18.6279
C39: 60 | D39: =ROUND('Loonschijven_Tranches salariale'!$B40*6/D$7+0.000049,4) -> 16.5339 | E39: =ROUND('Loonschijven_Tranches salariale'!$B40*6/E$7+0.000049,4) -> 16.7432 | F39: =ROUND('Loonschijven_Tranches salariale'!$B40*6/F$7+0.000049,4) -> 16.9579 | G39: =ROUND('Loonschijven_Tranches salariale'!$B40*6/G$7+0.000049,4) -> 17.1781 | H39: =ROUND('Loonschijven_Tranches salariale'!$B40*6/H$7+0.000049,4) -> 17.4041 | I39: =ROUND('Loonschijven_Tranches salariale'!$B40*6/I$7+0.000049,4) -> 17.6362 | J39: =ROUND('Loonschijven_Tranches salariale'!$B40*6/J$7+0.000049,4) -> 17.8745 | K39: =ROUND('Loonschijven_Tranches salariale'!$B40*6/K$7+0.000049,4) -> 18.1194 | ... N39: =ROUND('Loonschijven_Tranches salariale'!$B40*6/N$7+0.000049,4) -> 18.8959
C40: =C39+1 -> 61 | D40: =ROUND('Loonschijven_Tranches salariale'!$B41*6/D$7+0.000049,4) -> 16.7684 | E40: =ROUND('Loonschijven_Tranches salariale'!$B41*6/E$7+0.000049,4) -> 16.9807 | F40: =ROUND('Loonschijven_Tranches salariale'!$B41*6/F$7+0.000049,4) -> 17.1984 | G40: =ROUND('Loonschijven_Tranches salariale'!$B41*6/G$7+0.000049,4) -> 17.4218 | H40: =ROUND('Loonschijven_Tranches salariale'!$B41*6/H$7+0.000049,4) -> 17.651 | I40: =ROUND('Loonschijven_Tranches salariale'!$B41*6/I$7+0.000049,4) -> 17.8863 | J40: =ROUND('Loonschijven_Tranches salariale'!$B41*6/J$7+0.000049,4) -> 18.128 | K40: =ROUND('Loonschijven_Tranches salariale'!$B41*6/K$7+0.000049,4) -> 18.3764 | ... N40: =ROUND('Loonschijven_Tranches salariale'!$B41*6/N$7+0.000049,4) -> 19.1639
C41: =C40+1 -> 62 | D41: =ROUND('Loonschijven_Tranches salariale'!$B42*6/D$7+0.000049,4) -> 17.003 | E41: =ROUND('Loonschijven_Tranches salariale'!$B42*6/E$7+0.000049,4) -> 17.2182 | F41: =ROUND('Loonschijven_Tranches salariale'!$B42*6/F$7+0.000049,4) -> 17.4389 | G41: =ROUND('Loonschijven_Tranches salariale'!$B42*6/G$7+0.000049,4) -> 17.6654 | H41: =ROUND('Loonschijven_Tranches salariale'!$B42*6/H$7+0.000049,4) -> 17.8978 | I41: =ROUND('Loonschijven_Tranches salariale'!$B42*6/I$7+0.000049,4) -> 18.1365 | J41: =ROUND('Loonschijven_Tranches salariale'!$B42*6/J$7+0.000049,4) -> 18.3816 | K41: =ROUND('Loonschijven_Tranches salariale'!$B42*6/K$7+0.000049,4) -> 18.6334 | ... N41: =ROUND('Loonschijven_Tranches salariale'!$B42*6/N$7+0.000049,4) -> 19.4319
C42: =C41+1 -> 63 | D42: =ROUND('Loonschijven_Tranches salariale'!$B43*6/D$7+0.000049,4) -> 17.2375 | E42: =ROUND('Loonschijven_Tranches salariale'!$B43*6/E$7+0.000049,4) -> 17.4557 | F42: =ROUND('Loonschijven_Tranches salariale'!$B43*6/F$7+0.000049,4) -> 17.6794 | G42: =ROUND('Loonschijven_Tranches salariale'!$B43*6/G$7+0.000049,4) -> 17.9091 | H42: =ROUND('Loonschijven_Tranches salariale'!$B43*6/H$7+0.000049,4) -> 18.1447 | I42: =ROUND('Loonschijven_Tranches salariale'!$B43*6/I$7+0.000049,4) -> 18.3866 | J42: =ROUND('Loonschijven_Tranches salariale'!$B43*6/J$7+0.000049,4) -> 18.6351 | K42: =ROUND('Loonschijven_Tranches salariale'!$B43*6/K$7+0.000049,4) -> 18.8904 | ... N42: =ROUND('Loonschijven_Tranches salariale'!$B43*6/N$7+0.000049,4) -> 19.7
C43: =C42+1 -> 64 | D43: =ROUND('Loonschijven_Tranches salariale'!$B44*6/D$7+0.000049,4) -> 17.472 | E43: =ROUND('Loonschijven_Tranches salariale'!$B44*6/E$7+0.000049,4) -> 17.6931 | F43: =ROUND('Loonschijven_Tranches salariale'!$B44*6/F$7+0.000049,4) -> 17.92 | G43: =ROUND('Loonschijven_Tranches salariale'!$B44*6/G$7+0.000049,4) -> 18.1527 | H43: =ROUND('Loonschijven_Tranches salariale'!$B44*6/H$7+0.000049,4) -> 18.3915 | I43: =ROUND('Loonschijven_Tranches salariale'!$B44*6/I$7+0.000049,4) -> 18.6368 | J43: =ROUND('Loonschijven_Tranches salariale'!$B44*6/J$7+0.000049,4) -> 18.8886 | K43: =ROUND('Loonschijven_Tranches salariale'!$B44*6/K$7+0.000049,4) -> 19.1474 | ... N43: =ROUND('Loonschijven_Tranches salariale'!$B44*6/N$7+0.000049,4) -> 19.968
